Workbook

Sheet Cómo usar
A1: Cronograma de la tesis · cómo usarlo
A2: Sprints semanales (Scrum): lunes a sábado tareas; domingo en la noche, revisión y planificación
A4: Qué es | B4: Una hoja por sprint (semana de trabajo). Cada fila es una tarea con su día, responsable, lugar, resultado y cómo saber que está terminada.
A5: Cada día | B5: Marca el Estado (Pendiente, En curso, Hecho, Movido, Cancelado) y la Fecha real cuando la termines. No borres filas.
A6: Si una tarea se mueve | B6: Estado = Movido, escribe la fecha nueva en Notas y copia la fila al día nuevo. La original queda como registro.
A7: Colores | B7: Verde = hecho · Amarillo = movido · Rojo = atrasado (pasó el día y no está hecho) · Gris tachado = cancelado.
A8: Días de retraso | B8: Se calcula solo: fecha real − día planificado; si no hay fecha real y ya pasó el día, cuenta hasta hoy.
A9: Resumen | B9: Avance por sprint y por persona, horas planificadas y tareas atrasadas, con gráfico. Se calcula solo.
A10: Carga | B10: Horas y tareas por persona y día. Rojo si pasa de 2 h entre semana, 4 h el fin de semana o 4 tareas.
A11: Domingo en la noche | B11: Revisión del sprint (qué hicimos, qué no, qué aprendimos) + 20 minutos de «explícame lo tuyo» + planificación del sprint siguiente. Lo que se decida se anota en 11_Planificacion/Bitacora_Semanal.md.
A12: Entregable (issue) | B12: Cada tarea pertenece a un entregable que tiene su ficha en GitHub (issue). Ejemplo: «S1-07 (#7)» = entregable 7 del sprint 1, ficha #7 en github.com/l333x/Tesis_Torvesa/issues/7.
A13: Códigos | B13: M1–M6 = metas de validación · A1–A47 = afirmaciones que necesitan fuente · LOPDP = ley de datos personales · BPMN = forma estándar de dibujar procesos. Todo está en Glosario.pdf (raíz del repo).
A14: Escenario A | B14: Si la tutora confirma el 15-dic como fecha obligatoria, se comprime diciembre y se eliminan primero las tareas marcadas con ✂.
A15: Versión para la IA | B15: 11_Planificacion/CRONOGRAMA.md se regenera desde este Excel (comando: python 99_Scripts/gestion/generar_cronograma.py --md).

Sheet Resumen
A1: Resumen del avance
A2: Se calcula solo desde las hojas de cada sprint. No escribas aquí.
A4: Sprint | B4: Fechas y objetivo | C4: Tareas | D4: Hechas | E4: % avance | F4: % Víctor | G4: % Diego | H4: Horas Víctor | I4: Horas Diego | J4: Atrasadas
A5: S1 | B5: Sprint 1 · 12–18 oct · Recopilar información | C5: =COUNTA('S1'!D6:D32)-COUNTIF('S1'!K6:K32,"Cancelado") | D5: =COUNTIF('S1'!K6:K32,"Hecho") | E5: =IFERROR(D5/C5,0) | F5: =IFERROR((COUNTIFS('S1'!E6:E32,"Víctor",'S1'!K6:K32,"Hecho")+COUNTIFS('S1'!E6:E32,"Ambos",'S1'!K6:K32,"Hecho"))/(COUNTIF('S1'!E6:E32,"Víctor")+COUNTIF('S1'!E6:E32,"Ambos")),0) | G5: =IFERROR((COUNTIFS('S1'!E6:E32,"Diego",'S1'!K6:K32,"Hecho")+COUNTIFS('S1'!E6:E32,"Ambos",'S1'!K6:K32,"Hecho"))/(COUNTIF('S1'!E6:E32,"Diego")+COUNTIF('S1'!E6:E32,"Ambos")),0) | H5: =SUMIF('S1'!E6:E32,"Víctor",'S1'!I6:I32)+SUMIF('S1'!E6:E32,"Ambos",'S1'!I6:I32) | I5: =SUMIF('S1'!E6:E32,"Diego",'S1'!I6:I32)+SUMIF('S1'!E6:E32,"Ambos",'S1'!I6:I32) | J5: =COUNTIF('S1'!L6:L32,">0")
A6: S2 | B6: Sprint 2 · 19–25 oct · Redactar capítulos | C6: =COUNTA('S2'!D6:D23)-COUNTIF('S2'!K6:K23,"Cancelado") | D6: =COUNTIF('S2'!K6:K23,"Hecho") | E6: =IFERROR(D6/C6,0) | F6: =IFERROR((COUNTIFS('S2'!E6:E23,"Víctor",'S2'!K6:K23,"Hecho")+COUNTIFS('S2'!E6:E23,"Ambos",'S2'!K6:K23,"Hecho"))/(COUNTIF('S2'!E6:E23,"Víctor")+COUNTIF('S2'!E6:E23,"Ambos")),0) | G6: =IFERROR((COUNTIFS('S2'!E6:E23,"Diego",'S2'!K6:K23,"Hecho")+COUNTIFS('S2'!E6:E23,"Ambos",'S2'!K6:K23,"Hecho"))/(COUNTIF('S2'!E6:E23,"Diego")+COUNTIF('S2'!E6:E23,"Ambos")),0) | H6: =SUMIF('S2'!E6:E23,"Víctor",'S2'!I6:I23)+SUMIF('S2'!E6:E23,"Ambos",'S2'!I6:I23) | I6: =SUMIF('S2'!E6:E23,"Diego",'S2'!I6:I23)+SUMIF('S2'!E6:E23,"Ambos",'S2'!I6:I23) | J6: =COUNTIF('S2'!L6:L23,">0")
A7: S3 | B7: Sprint 3 · 26 oct–1 nov · Revisión 1 con la tutora | C7: =COUNTA('S3'!D6:D24)-COUNTIF('S3'!K6:K24,"Cancelado") | D7: =COUNTIF('S3'!K6:K24,"Hecho") | E7: =IFERROR(D7/C7,0) | F7: =IFERROR((COUNTIFS('S3'!E6:E24,"Víctor",'S3'!K6:K24,"Hecho")+COUNTIFS('S3'!E6:E24,"Ambos",'S3'!K6:K24,"Hecho"))/(COUNTIF('S3'!E6:E24,"Víctor")+COUNTIF('S3'!E6:E24,"Ambos")),0) | G7: =IFERROR((COUNTIFS('S3'!E6:E24,"Diego",'S3'!K6:K24,"Hecho")+COUNTIFS('S3'!E6:E24,"Ambos",'S3'!K6:K24,"Hecho"))/(COUNTIF('S3'!E6:E24,"Diego")+COUNTIF('S3'!E6:E24,"Ambos")),0) | H7: =SUMIF('S3'!E6:E24,"Víctor",'S3'!I6:I24)+SUMIF('S3'!E6:E24,"Ambos",'S3'!I6:I24) | I7: =SUMIF('S3'!E6:E24,"Diego",'S3'!I6:I24)+SUMIF('S3'!E6:E24,"Ambos",'S3'!I6:I24) | J7: =COUNTIF('S3'!L6:L24,">0")
A8: S4 | B8: Sprint 4 · 2–8 nov · Diseñar el sistema | C8: =COUNTA('S4'!D6:D22)-COUNTIF('S4'!K6:K22,"Cancelado") | D8: =COUNTIF('S4'!K6:K22,"Hecho") | E8: =IFERROR(D8/C8,0) | F8: =IFERROR((COUNTIFS('S4'!E6:E22,"Víctor",'S4'!K6:K22,"Hecho")+COUNTIFS('S4'!E6:E22,"Ambos",'S4'!K6:K22,"Hecho"))/(COUNTIF('S4'!E6:E22,"Víctor")+COUNTIF('S4'!E6:E22,"Ambos")),0) | G8: =IFERROR((COUNTIFS('S4'!E6:E22,"Diego",'S4'!K6:K22,"Hecho")+COUNTIFS('S4'!E6:E22,"Ambos",'S4'!K6:K22,"Hecho"))/(COUNTIF('S4'!E6:E22,"Diego")+COUNTIF('S4'!E6:E22,"Ambos")),0) | H8: =SUMIF('S4'!E6:E22,"Víctor",'S4'!I6:I22)+SUMIF('S4'!E6:E22,"Ambos",'S4'!I6:I22) | I8: =SUMIF('S4'!E6:E22,"Diego",'S4'!I6:I22)+SUMIF('S4'!E6:E22,"Ambos",'S4'!I6:I22) | J8: =COUNTIF('S4'!L6:L22,">0")
A9: S5 | B9: Sprint 5 · 9–15 nov · Prueba de concepto y finanzas | C9: =COUNTA('S5'!D6:D20)-COUNTIF('S5'!K6:K20,"Cancelado") | D9: =COUNTIF('S5'!K6:K20,"Hecho") | E9: =IFERROR(D9/C9,0) | F9: =IFERROR((COUNTIFS('S5'!E6:E20,"Víctor",'S5'!K6:K20,"Hecho")+COUNTIFS('S5'!E6:E20,"Ambos",'S5'!K6:K20,"Hecho"))/(COUNTIF('S5'!E6:E20,"Víctor")+COUNTIF('S5'!E6:E20,"Ambos")),0) | G9: =IFERROR((COUNTIFS('S5'!E6:E20,"Diego",'S5'!K6:K20,"Hecho")+COUNTIFS('S5'!E6:E20,"Ambos",'S5'!K6:K20,"Hecho"))/(COUNTIF('S5'!E6:E20,"Diego")+COUNTIF('S5'!E6:E20,"Ambos")),0) | H9: =SUMIF('S5'!E6:E20,"Víctor",'S5'!I6:I20)+SUMIF('S5'!E6:E20,"Ambos",'S5'!I6:I20) | I9: =SUMIF('S5'!E6:E20,"Diego",'S5'!I6:I20)+SUMIF('S5'!E6:E20,"Ambos",'S5'!I6:I20) | J9: =COUNTIF('S5'!L6:L20,">0")
A10: S6 | B10: Sprint 6 · 16–22 nov · Revisión 2 con la tutora | C10: =COUNTA('S6'!D6:D17)-COUNTIF('S6'!K6:K17,"Cancelado") | D10: =COUNTIF('S6'!K6:K17,"Hecho") | E10: =IFERROR(D10/C10,0) | F10: =IFERROR((COUNTIFS('S6'!E6:E17,"Víctor",'S6'!K6:K17,"Hecho")+COUNTIFS('S6'!E6:E17,"Ambos",'S6'!K6:K17,"Hecho"))/(COUNTIF('S6'!E6:E17,"Víctor")+COUNTIF('S6'!E6:E17,"Ambos")),0) | G10: =IFERROR((COUNTIFS('S6'!E6:E17,"Diego",'S6'!K6:K17,"Hecho")+COUNTIFS('S6'!E6:E17,"Ambos",'S6'!K6:K17,"Hecho"))/(COUNTIF('S6'!E6:E17,"Diego")+COUNTIF('S6'!E6:E17,"Ambos")),0) | H10: =SUMIF('S6'!E6:E17,"Víctor",'S6'!I6:I17)+SUMIF('S6'!E6:E17,"Ambos",'S6'!I6:I17) | I10: =SUMIF('S6'!E6:E17,"Diego",'S6'!I6:I17)+SUMIF('S6'!E6:E17,"Ambos",'S6'!I6:I17) | J10: =COUNTIF('S6'!L6:L17,">0")
A11: S7 | B11: Sprint 7 · 23–29 nov · Arranca la validación | C11: =COUNTA('S7'!D6:D19)-COUNTIF('S7'!K6:K19,"Cancelado") | D11: =COUNTIF('S7'!K6:K19,"Hecho") | E11: =IFERROR(D11/C11,0) | F11: =IFERROR((COUNTIFS('S7'!E6:E19,"Víctor",'S7'!K6:K19,"Hecho")+COUNTIFS('S7'!E6:E19,"Ambos",'S7'!K6:K19,"Hecho"))/(COUNTIF('S7'!E6:E19,"Víctor")+COUNTIF('S7'!E6:E19,"Ambos")),0) | G11: =IFERROR((COUNTIFS('S7'!E6:E19,"Diego",'S7'!K6:K19,"Hecho")+COUNTIFS('S7'!E6:E19,"Ambos",'S7'!K6:K19,"Hecho"))/(COUNTIF('S7'!E6:E19,"Diego")+COUNTIF('S7'!E6:E19,"Ambos")),0) | H11: =SUMIF('S7'!E6:E19,"Víctor",'S7'!I6:I19)+SUMIF('S7'!E6:E19,"Ambos",'S7'!I6:I19) | I11: =SUMIF('S7'!E6:E19,"Diego",'S7'!I6:I19)+SUMIF('S7'!E6:E19,"Ambos",'S7'!I6:I19) | J11: =COUNTIF('S7'!L6:L19,">0")
A12: S8 | B12: Sprint 8 · 30 nov–6 dic · Documentar el sistema | C12: =COUNTA('S8'!D6:D23)-COUNTIF('S8'!K6:K23,"Cancelado") | D12: =COUNTIF('S8'!K6:K23,"Hecho") | E12: =IFERROR(D12/C12,0) | F12: =IFERROR((COUNTIFS('S8'!E6:E23,"Víctor",'S8'!K6:K23,"Hecho")+COUNTIFS('S8'!E6:E23,"Ambos",'S8'!K6:K23,"Hecho"))/(COUNTIF('S8'!E6:E23,"Víctor")+COUNTIF('S8'!E6:E23,"Ambos")),0) | G12: =IFERROR((COUNTIFS('S8'!E6:E23,"Diego",'S8'!K6:K23,"Hecho")+COUNTIFS('S8'!E6:E23,"Ambos",'S8'!K6:K23,"Hecho"))/(COUNTIF('S8'!E6:E23,"Diego")+COUNTIF('S8'!E6:E23,"Ambos")),0) | H12: =SUMIF('S8'!E6:E23,"Víctor",'S8'!I6:I23)+SUMIF('S8'!E6:E23,"Ambos",'S8'!I6:I23) | I12: =SUMIF('S8'!E6:E23,"Diego",'S8'!I6:I23)+SUMIF('S8'!E6:E23,"Ambos",'S8'!I6:I23) | J12: =COUNTIF('S8'!L6:L23,">0")
A13: S9 | B13: Sprint 9 · 7–13 dic · Medir el «después» y comparar | C13: =COUNTA('S9'!D6:D15)-COUNTIF('S9'!K6:K15,"Cancelado") | D13: =COUNTIF('S9'!K6:K15,"Hecho") | E13: =IFERROR(D13/C13,0) | F13: =IFERROR((COUNTIFS('S9'!E6:E15,"Víctor",'S9'!K6:K15,"Hecho")+COUNTIFS('S9'!E6:E15,"Ambos",'S9'!K6:K15,"Hecho"))/(COUNTIF('S9'!E6:E15,"Víctor")+COUNTIF('S9'!E6:E15,"Ambos")),0) | G13: =IFERROR((COUNTIFS('S9'!E6:E15,"Diego",'S9'!K6:K15,"Hecho")+COUNTIFS('S9'!E6:E15,"Ambos",'S9'!K6:K15,"Hecho"))/(COUNTIF('S9'!E6:E15,"Diego")+COUNTIF('S9'!E6:E15,"Ambos")),0) | H13: =SUMIF('S9'!E6:E15,"Víctor",'S9'!I6:I15)+SUMIF('S9'!E6:E15,"Ambos",'S9'!I6:I15) | I13: =SUMIF('S9'!E6:E15,"Diego",'S9'!I6:I15)+SUMIF('S9'!E6:E15,"Ambos",'S9'!I6:I15) | J13: =COUNTIF('S9'!L6:L15,">0")
A14: S10 | B14: Sprint 10 · 14–20 dic · Cierre e hito del 90 % | C14: =COUNTA('S10'!D6:D13)-COUNTIF('S10'!K6:K13,"Cancelado") | D14: =COUNTIF('S10'!K6:K13,"Hecho") | E14: =IFERROR(D14/C14,0) | F14: =IFERROR((COUNTIFS('S10'!E6:E13,"Víctor",'S10'!K6:K13,"Hecho")+COUNTIFS('S10'!E6:E13,"Ambos",'S10'!K6:K13,"Hecho"))/(COUNTIF('S10'!E6:E13,"Víctor")+COUNTIF('S10'!E6:E13,"Ambos")),0) | G14: =IFERROR((COUNTIFS('S10'!E6:E13,"Diego",'S10'!K6:K13,"Hecho")+COUNTIFS('S10'!E6:E13,"Ambos",'S10'!K6:K13,"Hecho"))/(COUNTIF('S10'!E6:E13,"Diego")+COUNTIF('S10'!E6:E13,"Ambos")),0) | H14: =SUMIF('S10'!E6:E13,"Víctor",'S10'!I6:I13)+SUMIF('S10'!E6:E13,"Ambos",'S10'!I6:I13) | I14: =SUMIF('S10'!E6:E13,"Diego",'S10'!I6:I13)+SUMIF('S10'!E6:E13,"Ambos",'S10'!I6:I13) | J14: =COUNTIF('S10'!L6:L13,">0")
A15: Holgura | B15: Holgura · 21 dic–3 ene · Pulir | C15: =COUNTA('Holgura'!D6:D11)-COUNTIF('Holgura'!K6:K11,"Cancelado") | D15: =COUNTIF('Holgura'!K6:K11,"Hecho") | E15: =IFERROR(D15/C15,0) | F15: =IFERROR((COUNTIFS('Holgura'!E6:E11,"Víctor",'Holgura'!K6:K11,"Hecho")+COUNTIFS('Holgura'!E6:E11,"Ambos",'Holgura'!K6:K11,"Hecho"))/(COUNTIF('Holgura'!E6:E11,"Víctor")+COUNTIF('Holgura'!E6:E11,"Ambos")),0) | G15: =IFERROR((COUNTIFS('Holgura'!E6:E11,"Diego",'Holgura'!K6:K11,"Hecho")+COUNTIFS('Holgura'!E6:E11,"Ambos",'Holgura'!K6:K11,"Hecho"))/(COUNTIF('Holgura'!E6:E11,"Diego")+COUNTIF('Holgura'!E6:E11,"Ambos")),0) | H15: =SUMIF('Holgura'!E6:E11,"Víctor",'Holgura'!I6:I11)+SUMIF('Holgura'!E6:E11,"Ambos",'Holgura'!I6:I11) | I15: =SUMIF('Holgura'!E6:E11,"Diego",'Holgura'!I6:I11)+SUMIF('Holgura'!E6:E11,"Ambos",'Holgura'!I6:I11) | J15: =COUNTIF('Holgura'!L6:L11,">0")
A16: Entrega | B16: Entrega · 4–10 ene · Revisión final y firma | C16: =COUNTA('Entrega'!D6:D9)-COUNTIF('Entrega'!K6:K9,"Cancelado") | D16: =COUNTIF('Entrega'!K6:K9,"Hecho") | E16: =IFERROR(D16/C16,0) | F16: =IFERROR((COUNTIFS('Entrega'!E6:E9,"Víctor",'Entrega'!K6:K9,"Hecho")+COUNTIFS('Entrega'!E6:E9,"Ambos",'Entrega'!K6:K9,"Hecho"))/(COUNTIF('Entrega'!E6:E9,"Víctor")+COUNTIF('Entrega'!E6:E9,"Ambos")),0) | G16: =IFERROR((COUNTIFS('Entrega'!E6:E9,"Diego",'Entrega'!K6:K9,"Hecho")+COUNTIFS('Entrega'!E6:E9,"Ambos",'Entrega'!K6:K9,"Hecho"))/(COUNTIF('Entrega'!E6:E9,"Diego")+COUNTIF('Entrega'!E6:E9,"Ambos")),0) | H16: =SUMIF('Entrega'!E6:E9,"Víctor",'Entrega'!I6:I9)+SUMIF('Entrega'!E6:E9,"Ambos",'Entrega'!I6:I9) | I16: =SUMIF('Entrega'!E6:E9,"Diego",'Entrega'!I6:I9)+SUMIF('Entrega'!E6:E9,"Ambos",'Entrega'!I6:I9) | J16: =COUNTIF('Entrega'!L6:L9,">0")
A17: Defensa | B17: Defensa · 11 ene–12 feb · Preparar y defender | C17: =COUNTA('Defensa'!D6:D10)-COUNTIF('Defensa'!K6:K10,"Cancelado") | D17: =COUNTIF('Defensa'!K6:K10,"Hecho") | E17: =IFERROR(D17/C17,0) | F17: =IFERROR((COUNTIFS('Defensa'!E6:E10,"Víctor",'Defensa'!K6:K10,"Hecho")+COUNTIFS('Defensa'!E6:E10,"Ambos",'Defensa'!K6:K10,"Hecho"))/(COUNTIF('Defensa'!E6:E10,"Víctor")+COUNTIF('Defensa'!E6:E10,"Ambos")),0) | G17: =IFERROR((COUNTIFS('Defensa'!E6:E10,"Diego",'Defensa'!K6:K10,"Hecho")+COUNTIFS('Defensa'!E6:E10,"Ambos",'Defensa'!K6:K10,"Hecho"))/(COUNTIF('Defensa'!E6:E10,"Diego")+COUNTIF('Defensa'!E6:E10,"Ambos")),0) | H17: =SUMIF('Defensa'!E6:E10,"Víctor",'Defensa'!I6:I10)+SUMIF('Defensa'!E6:E10,"Ambos",'Defensa'!I6:I10) | I17: =SUMIF('Defensa'!E6:E10,"Diego",'Defensa'!I6:I10)+SUMIF('Defensa'!E6:E10,"Ambos",'Defensa'!I6:I10) | J17: =COUNTIF('Defensa'!L6:L10,">0")
A18: TOTAL | C18: =SUM(C5:C17) | D18: =SUM(D5:D17) | E18: =IFERROR(D18/C18,0) | H18: =SUM(H5:H17) | I18: =SUM(I5:I17) | J18: =SUM(J5:J17)

Sheet S1
A1: Sprint 1 · 12–18 oct · Recopilar información
A2: Objetivo: Buscar fuentes, hablar con la tutora y con Torvesa, preparar el campo
A3: Avance del sprint: | C3: =IFERROR(COUNTIF(K6:K32,"Hecho")/(COUNTA(D6:D32)-COUNTIF(K6:K32,"Cancelado")),0) | D3: ="Víctor: "&TEXT(IFERROR((COUNTIFS(E6:E32,"Víctor",K6:K32,"Hecho")+COUNTIFS(E6:E32,"Ambos",K6:K32,"Hecho"))/(COUNTIF(E6:E32,"Víctor")+COUNTIF(E6:E32,"Ambos")),0),"0%")&" · Diego: "&TEXT(IFERROR((COUNTIFS(E6:E32,"Diego",K6:K32,"Hecho")+COUNTIFS(E6:E32,"Ambos",K6:K32,"Hecho"))/(COUNTIF(E6:E32,"Diego")+COUNTIF(E6:E32,"Ambos")),0),"0%")&" · Horas: "&TEXT(SUM(I6:I32),"0.0")
A5: ID | B5: Día planificado | C5: Día | D5: Tarea (verbo + qué + para qué) | E5: Responsable | F5: Dónde se hace | G5: Resultado esperado | H5: Cómo sé que terminé | I5: Horas estimadas | J5: Fecha real | K5: Estado | L5: Días de retraso | M5: Entregable (issue) | N5: Notas
A6: S1-T01 | B6: 46307 | C6: =B6 | D6: Conversar con la tutora sobre los 5 cambios, para tener su aprobación | E6: Víctor | F6: UPS Quito, en persona · llevar 08_Reuniones_Tutora/2026-10-12_Puntos_Tutora.pdf | G6: Respuestas de la tutora anotadas | H6: Las 5 preguntas tienen respuesta (sí / no / pendiente) | I6: 1 | J6: 46307 | K6: Hecho | L6: =IF(K6="Cancelado","",IF(J6<>"",J6-B6,IF(AND(K6<>"Hecho",TODAY()>B6),TODAY()-B6,0))) | M6: S1-07 (#7) | N6: Víctor conversó con la tutora: sin objeciones a los 5 puntos (lo dijo Víctor el 18-oct). Falta confirmar la fecha de entrega (D5)
A7: S1-T02 | B7: 46307 | C7: =B7 | D7: Escribir el acta de la conversación, para que quede por escrito lo que decidió | E7: Víctor | F7: 08_Reuniones_Tutora/ | G7: 08_Reuniones_Tutora/2026-10-12_Acta_Conversacion.md | H7: Acta con decisiones y fechas | I7: 0.5 | K7: Movido | L7: =IF(K7="Cancelado","",IF(J7<>"",J7-B7,IF(AND(K7<>"Hecho",TODAY()>B7),TODAY()-B7,0))) | M7: S1-07 (#7) | N7: Víctor decidió hacer el acta más adelante (18-oct)
A8: S1-T03 | B8: 46307 | C8: =B8 | D8: Enviar el correo a Torvesa (giro, nota de respaldo, catálogo, permisos), para trabajar con datos oficiales | E8: Víctor | F8: Correo electrónico · borrador en 11_Planificacion/2026-10-12_Correo_Torvesa_borrador.docx | G8: Correo enviado con el catálogo adjunto | H8: Copia del correo enviado | I8: 0.5 | K8: Movido | L8: =IF(K8="Cancelado","",IF(J8<>"",J8-B8,IF(AND(K8<>"Hecho",TODAY()>B8),TODAY()-B8,0))) | M8: S1-05 (#5) | N8: Diego se encarga de conseguir la información de Torvesa (decisión de Víctor, 18-oct)
A9: S1-T04 | B9: 46307 | C9: =B9 | D9: Aceptar la invitación de GitHub y clonar el repo, para trabajar en la bóveda compartida | E9: Diego | F9: PC de Diego · pasos en GUIA_DIEGO.pdf (raíz) | G9: Repo clonado + 00_Inbox/hola_diego.md | H9: El commit de prueba aparece en GitHub | I9: 1 | J9: 46314 | K9: Hecho | L9: =IF(K9="Cancelado","",IF(J9<>"",J9-B9,IF(AND(K9<>"Hecho",TODAY()>B9),TODAY()-B9,0))) | M9: S1-10 (#10) | N9: Diego acepta la invitación el 18-oct (vencía ese día) · 19-oct: repo clonado y commit de prueba (00_Inbox/hola_diego.md)
A10: S1-T05 | B10: 46307 | C10: =B10 | D10: Levantar el buscador RAG en su PC, para consultar la bóveda | E10: Diego | F10: PC de Diego · pasos en RAG_README.md (raíz) | G10: Consulta de prueba con resultados | H10: rag.py consultar devuelve fragmentos | I10: 1 | J10: 46314 | K10: Hecho | L10: =IF(K10="Cancelado","",IF(J10<>"",J10-B10,IF(AND(K10<>"Hecho",TODAY()>B10),TODAY()-B10,0))) | M10: S1-10 (#10) | N10: Movido a la semana 19–24 oct (bloques dobles de Diego en IA_DIEGO.md) · 19-oct: RAG funcionando en la PC de Diego (586 notas indexadas)
A11: S1-T06 | B11: 46308 | C11: =B11 | D11: Buscar y verificar fuentes sobre el tiempo de respuesta a clientes (Oldroyd y estudios 2023+), para respaldar el problema (A9, A10) | E11: Víctor | F11: 02_Fuentes/Problema/ · con 99_Scripts/busqueda/ | G11: ≥5 fichas, ≥2 verificadas con página | H11: Cada ficha con estado y página | I11: 1 | K11: En curso | L11: =IF(K11="Cancelado","",IF(J11<>"",J11-B11,IF(AND(K11<>"Hecho",TODAY()>B11),TODAY()-B11,0))) | M11: S1-01 (#1) | N11: A9 parcial (falta el PDF de Oldroyd); A10 hay que reformularla como decisión de diseño. Ver la matriz del 18-oct
A12: S1-T07 | B12: 46308 | C12: =B12 | D12: Buscar fuentes sobre la digitalización de la construcción, para respaldar el contexto (A5, A6) | E12: Víctor | F12: 02_Fuentes/Problema/ | G12: ≥4 fichas | H12: Cada ficha con estado | I12: 1 | J12: 46307 | K12: Hecho | L12: =IF(K12="Cancelado","",IF(J12<>"",J12-B12,IF(AND(K12<>"Hecho",TODAY()>B12),TODAY()-B12,0))) | M12: S1-01 (#1) | N12: A5 y A6 respaldadas (Manyika 2015, Cathles 2023, Samuelson 2023, McKinsey 2023). Nyqvist 2024 opcional
A13: S1-T08 | B13: 46308 | C13: =B13 | D13: Investigar cómo consolidar bóvedas de conocimiento, para diseñar la bóveda del sistema | E13: Diego | F13: 02_Fuentes/Tecnologia_IA/ · con 99_Scripts/busqueda/ | G13: ≥5 fichas | H13: Cada ficha dice qué respalda | I13: 1.5 | J13: 46316 | K13: Hecho | L13: =IF(K13="Cancelado","",IF(J13<>"",J13-B13,IF(AND(K13<>"Hecho",TODAY()>B13),TODAY()-B13,0))) | M13: S1-13 (#54) | N13: Movido a la semana 19–24 oct (bloques dobles de Diego en IA_DIEGO.md) · 21-oct: 7 fichas verificadas de gestión del conocimiento (D01)
A14: S1-T09 | B14: 46308 | C14: =B14 | D14: Leer el Documento madre y el Glosario, para entender el proyecto completo | E14: Diego | F14: 00_DOCUMENTO_MADRE.pdf y Glosario.pdf (raíz) | G14: Dudas anotadas en el issue #10 | H14: Dudas enviadas a Víctor | I14: 0.5 | J14: 46314 | K14: Hecho | L14: =IF(K14="Cancelado","",IF(J14<>"",J14-B14,IF(AND(K14<>"Hecho",TODAY()>B14),TODAY()-B14,0))) | M14: S1-10 (#10) | N14: Movido a la semana 19–24 oct (bloques dobles de Diego en IA_DIEGO.md) · 19-oct: leído; 5 dudas en 00_Inbox/2026-10-19_reporte_Diego.md
A15: S1-T10 | B15: 46309 | C15: =B15 | D15: Revisar la respuesta de Torvesa y ajustar el campo del jueves y viernes, para saber qué se puede aplicar | E15: Víctor | F15: Correo · 11_Planificacion/Cronograma_Tesis.xlsx | G15: Campo confirmado o reprogramado | H15: Notas de esta fila actualizadas | I15: 0.25 | K15: Movido | L15: =IF(K15="Cancelado","",IF(J15<>"",J15-B15,IF(AND(K15<>"Hecho",TODAY()>B15),TODAY()-B15,0))) | M15: S1-05 (#5) | N15: Movido: se aplica cuando Torvesa autorice (Diego consigue la información y los permisos)
A16: S1-T11 | B16: 46309 | C16: =B16 | D16: Corregir los instrumentos a la versión 0.2, para aplicarlos en Torvesa | E16: Víctor | F16: 04_Instrumentos/ | G16: 04_Instrumentos/2026-10-14_*_v0.2 (.md + Word) | H16: Aprobados e impresos | I16: 0.75 | J16: 46313 | K16: Hecho | L16: =IF(K16="Cancelado","",IF(J16<>"",J16-B16,IF(AND(K16<>"Hecho",TODAY()>B16),TODAY()-B16,0))) | M16: S1-04 (#4) | N16: C1 v0.2 (artículos de la LOPDP) e I1 v0.2 (SUS validada en español) en 04_Instrumentos/2026-10-18_*. I2, I3, P1 y P2 siguen en v0.1
A17: S1-T12 | B17: 46309 | C17: =B17 | D17: Hacer el corte de fuentes: armar la matriz afirmación–fuente–estado, para decidir qué entra al capítulo 1 | E17: Víctor | F17: 03_Matriz_Objetivos/ | G17: 03_Matriz_Objetivos/2026-10-14_Matriz_Afirmaciones_v0.1.xlsx | H17: Las 47 afirmaciones tienen estado | I17: 1 | J17: 46313 | K17: Hecho | L17: =IF(K17="Cancelado","",IF(J17<>"",J17-B17,IF(AND(K17<>"Hecho",TODAY()>B17),TODAY()-B17,0))) | M17: S1-03 (#3) | N17: 03_Matriz_Objetivos/2026-10-18_Matriz_Afirmaciones_v0.1.xlsx: 9 respaldadas, 7 parciales, 1 reformular, 5 de campo, 1 no se usa, 19 sin fuente
A18: S1-T13 | B18: 46309 | C18: =B18 | D18: Investigar arquitecturas RAG para negocio, para proponer cómo el asistente consultará la bóveda | E18: Diego | F18: 02_Fuentes/Tecnologia_IA/ | G18: ≥5 fichas | H18: Cada ficha dice qué respalda | I18: 1.5 | J18: 46316 | K18: Hecho | L18: =IF(K18="Cancelado","",IF(J18<>"",J18-B18,IF(AND(K18<>"Hecho",TODAY()>B18),TODAY()-B18,0))) | M18: S1-13 (#54) | N18: Movido a la semana 19–24 oct (bloques dobles de Diego en IA_DIEGO.md) · 21-oct: 6 fichas verificadas de RAG (D02); A37 cubierta
A19: S1-T14 | B19: 46309 | C19: =B19 | D19: Escribir un resumen de 1 página para Víctor sobre bóvedas y RAG, para compartir lo aprendido | E19: Diego | F19: 02_Fuentes/Tecnologia_IA/ | G19: 02_Fuentes/Tecnologia_IA/2026-10-14_Resumen_Bovedas_RAG.md | H19: Víctor lo leyó | I19: 0.5 | J19: 46320 | K19: Hecho | L19: =IF(K19="Cancelado","",IF(J19<>"",J19-B19,IF(AND(K19<>"Hecho",TODAY()>B19),TODAY()-B19,0))) | M19: S1-13 (#54) | N19: Movido a la semana 19–24 oct (bloques dobles de Diego en IA_DIEGO.md) · 25-oct: 02_Fuentes/Tecnologia_IA/2026-10-25_Resumen_Bovedas_RAG.md
A20: S1-T15 | B20: 46310 | C20: =B20 | D20: Aplicar la encuesta a colaboradores y 2 entrevistas en Torvesa (si autorizó), para la línea base real | E20: Víctor | F20: Torvesa (oficina, Quito) · registro en 05_Datos_Campo/LineaBase_2026-10/ | G20: Hojas firmadas + 05_Datos_Campo/LineaBase_2026-10/registro_aplicacion.csv | H20: Cada aplicación está en el registro | I20: 2 | K20: Movido | L20: =IF(K20="Cancelado","",IF(J20<>"",J20-B20,IF(AND(K20<>"Hecho",TODAY()>B20),TODAY()-B20,0))) | M20: S1-08 (#8) | N20: Movido: se aplica cuando Torvesa autorice (Diego consigue la información y los permisos)
A21: S1-T16 | B21: 46310 | C21: =B21 | D21: Cronometrar las cotizaciones del día en Torvesa (si autorizó), para medir el tiempo real (meta M2) | E21: Diego | F21: Torvesa (oficina, Quito) | G21: 05_Datos_Campo/LineaBase_2026-10/P2A_cronometraje.csv | H21: Todas las cotizaciones observadas registradas | I21: 2 | K21: Movido | L21: =IF(K21="Cancelado","",IF(J21<>"",J21-B21,IF(AND(K21<>"Hecho",TODAY()>B21),TODAY()-B21,0))) | M21: S1-09 (#9) | N21: Movido: se aplica cuando Torvesa autorice (Diego consigue la información y los permisos) · 27-oct: bloqueada, Torvesa aún no autoriza el campo; copia en S4-T16 (reprogramada 27-oct)
A22: S1-T17 | B22: 46311 | C22: =B22 | D22: Llamar a los clientes para la encuesta corta (si autorizó), para conocer su experiencia | E22: Víctor | F22: Teléfono · lista solo en 05_Datos_Campo/_crudo/ (privada) | G22: Respuestas codificadas CLI-xx | H22: Cada llamada con consentimiento verbal registrado | I22: 2 | K22: Movido | L22: =IF(K22="Cancelado","",IF(J22<>"",J22-B22,IF(AND(K22<>"Hecho",TODAY()>B22),TODAY()-B22,0))) | M22: S1-08 (#8) | N22: Movido: se aplica cuando Torvesa autorice (Diego consigue la información y los permisos)
A23: S1-T18 | B23: 46311 | C23: =B23 | D23: Revisar solicitudes y cotizaciones de los últimos 3 meses (solo fechas y horas), para medir el tiempo de respuesta (meta M1) | E23: Diego | F23: Torvesa (oficina, Quito) | G23: 05_Datos_Campo/LineaBase_2026-10/P2B_muestra_documental.csv | H23: ≥20 solicitudes o todas las disponibles | I23: 2 | K23: Movido | L23: =IF(K23="Cancelado","",IF(J23<>"",J23-B23,IF(AND(K23<>"Hecho",TODAY()>B23),TODAY()-B23,0))) | M23: S1-09 (#9) | N23: Movido: se aplica cuando Torvesa autorice (Diego consigue la información y los permisos) · 27-oct: bloqueada, Torvesa aún no autoriza el campo; copia en S4-T16 (reprogramada 27-oct)
A24: S1-T19 | B24: 46312 | C24: =B24 | D24: Buscar el texto oficial de la ley de datos (LOPDP) y agregar sus artículos al consentimiento, para cumplir la ley | E24: Víctor | F24: 02_Fuentes/Normativa/ y 04_Instrumentos/ | G24: Ficha LOPDP + consentimiento v0.2 con artículos | H24: Artículos citados desde el Registro Oficial | I24: 1.5 | J24: 46313 | K24: Hecho | L24: =IF(K24="Cancelado","",IF(J24<>"",J24-B24,IF(AND(K24<>"Hecho",TODAY()>B24),TODAY()-B24,0))) | M24: S1-02 (#2) | N24: LOPDP verificada en el Registro Oficial (RO 459, Quinto Suplemento, 26-may-2021) y Reglamento (Decreto 904, RO 435). Artículos en C1 v0.2
A25: S1-T20 | B25: 46312 | C25: =B25 | D25: Buscar la versión validada en español de la escala SUS, para medir la usabilidad correctamente | E25: Víctor | F25: 02_Fuentes/Metodologia/ | G25: Ficha verificada + encuesta I1 v0.2 con la traducción | H25: Traducción con fuente | I25: 1 | J25: 46313 | K25: Hecho | L25: =IF(K25="Cancelado","",IF(J25<>"",J25-B25,IF(AND(K25<>"Hecho",TODAY()>B25),TODAY()-B25,0))) | M25: S1-02 (#2) | N25: Sevilla-Gonzalez et al. (2020), JMIR Human Factors: α = 0,812. Falta el umbral 68 (Lewis y Sauro 2018, PDF a mano)
A26: S1-T21 | B26: 46312 | C26: =B26 | D26: Buscar fuentes de metodología (DSR, Design Thinking, Scrum, censo), para justificar el método | E26: Víctor | F26: 02_Fuentes/Metodologia/ | G26: ≥6 fichas | H26: Cada método con 2–3 fuentes | I26: 1.5 | K26: En curso | L26: =IF(K26="Cancelado","",IF(J26<>"",J26-B26,IF(AND(K26<>"Hecho",TODAY()>B26),TODAY()-B26,0))) | M26: S1-02 (#2) | N26: Verificadas: Guía Scrum 2020, Sassa 2023, Tuunanen 2024 (DSR), Dawadi 2021 (mixto), Cuadrado Torres 2023 (DT). Falta: censo (Hernández-Sampieri), DT teórico (Auernhammer 2021)
A27: S1-T22 | B27: 46312 | C27: =B27 | D27: Investigar flujos de información y diseño de procesos (BPMN), para dibujar el proceso de Torvesa | E27: Diego | F27: 02_Fuentes/Metodologia/ | G27: ≥5 fichas | H27: Cada ficha dice qué respalda | I27: 1.5 | J27: 46320 | K27: Hecho | L27: =IF(K27="Cancelado","",IF(J27<>"",J27-B27,IF(AND(K27<>"Hecho",TODAY()>B27),TODAY()-B27,0))) | M27: S1-14 (#55) | N27: Movido a la semana 19–24 oct (bloques dobles de Diego en IA_DIEGO.md) · 25-oct: 6 fichas verificadas de BPMN y procesos, incluida la especificación OMG
A28: S1-T23 | B28: 46312 | C28: =B28 | D28: Investigar CRMs móviles y herramientas existentes con sus precios, para comparar y calcular costos | E28: Diego | F28: 02_Fuentes/Casos_Estudio/ y 02_Fuentes/Costos_Viabilidad/ | G28: Tabla de ≥6 herramientas con precio y fecha | H28: Cada precio con enlace oficial | I28: 2 | J28: 46320 | K28: Hecho | L28: =IF(K28="Cancelado","",IF(J28<>"",J28-B28,IF(AND(K28<>"Hecho",TODAY()>B28),TODAY()-B28,0))) | M28: S1-15 (#56) | N28: Movido a la semana 19–24 oct (bloques dobles de Diego en IA_DIEGO.md) · 25-oct: fichas de precios de CRM, mensajería, bóveda y LLM (bloques G y H)
A29: S1-T24 | B29: 46313 | C29: =B29 | D29: Tabular y anonimizar los datos de campo, para que estén listos y sean confiables | E29: Ambos | F29: 05_Datos_Campo/LineaBase_2026-10/ | G29: CSV anonimizados + hashes + auditoría | H29: auditoria_pii.py dice 0 hallazgos | I29: 2 | K29: Movido | L29: =IF(K29="Cancelado","",IF(J29<>"",J29-B29,IF(AND(K29<>"Hecho",TODAY()>B29),TODAY()-B29,0))) | M29: S1-12 (#12) | N29: Movido: se aplica cuando Torvesa autorice (Diego consigue la información y los permisos). Al día siguiente del campo · 27-oct: bloqueada, sin datos de campo; se hace al día siguiente del campo (S4-T16)
A30: S1-T25 | B30: 46313 | C30: =B30 | D30: Escribir un resumen de 1 página para Diego sobre el problema y sus fuentes | E30: Víctor | F30: 02_Fuentes/Problema/ | G30: 02_Fuentes/Problema/2026-10-18_Resumen_Problema.md | H30: Diego lo leyó | I30: 0.5 | J30: 46313 | K30: Hecho | L30: =IF(K30="Cancelado","",IF(J30<>"",J30-B30,IF(AND(K30<>"Hecho",TODAY()>B30),TODAY()-B30,0))) | M30: S1-01 (#1) | N30: Borrador de Claude en 02_Fuentes/Problema/2026-10-18_Resumen_Problema.md; falta que Víctor lo revise
A31: S1-T26 | B31: 46313 | C31: =B31 | D31: Escribir un resumen de 1 página para Víctor sobre CRMs y flujos | E31: Diego | F31: 02_Fuentes/Casos_Estudio/ | G31: 02_Fuentes/Casos_Estudio/2026-10-18_Resumen_CRM_Flujos.md | H31: Víctor lo leyó | I31: 0.5 | J31: 46320 | K31: Hecho | L31: =IF(K31="Cancelado","",IF(J31<>"",J31-B31,IF(AND(K31<>"Hecho",TODAY()>B31),TODAY()-B31,0))) | M31: S1-15 (#56) | N31: Movido a la semana 19–24 oct (bloques dobles de Diego en IA_DIEGO.md) · 25-oct: 02_Fuentes/Casos_Estudio/2026-10-25_Resumen_CRM_Flujos.md
A32: S1-T27 | B32: 46313 | C32: =B32 | D32: Revisar el sprint (qué hicimos, qué no, qué aprendimos), hacer 20 min de «explícame lo tuyo» y planificar el siguiente | E32: Ambos | F32: Llamada Víctor–Diego · 11_Planificacion/Bitacora_Semanal.md y 11_Planificacion/Cronograma_Tesis.xlsx | G32: Sección de la semana en la bitácora + hoja del sprint siguiente ajustada | H32: El informe del domingo (21:00) sale con la sección nueva | I32: 1 | K32: En curso | L32: =IF(K32="Cancelado","",IF(J32<>"",J32-B32,IF(AND(K32<>"Hecho",TODAY()>B32),TODAY()-B32,0))) | M32: S1-16 (#57) | N32: Revisión del sprint hecha por Víctor y Claude el 18-oct; falta la llamada de 20 min con Diego

Sheet Carga
A1: Carga por persona y día
A2: Rojo = más horas que el límite (2 h entre semana, 4 h fin de semana) o más de 4 tareas
A4: Fecha | B4: Día | C4: Límite (h) | D4: Horas Víctor | E4: Horas Diego | F4: Tareas Víctor | G4: Tareas Diego
A5: 46307 | B5: =A5 | C5: =IF(WEEKDAY(A5,2)>5,4,2) | D5: =SUMIFS('S1'!$I$6:$I$32,'S1'!$B$6:$B$32,$A5,'S1'!$E$6:$E$32,"Víctor")+SUMIFS('S1'!$I$6:$I$32,'S1'!$B$6:$B$32,$A5,'S1'!$E$6:$E$32,"Ambos")+SUMIFS('S2'!$I$6:$I$23,'S2'!$B$6:$B$23,$A5,'S2'!$E$6:$E$23,"Víctor")+SUMIFS('S2'!$I$6:$I$23,'S2'!$B$6:$B$23,$A5,'S2'!$E$6:$E$23,"Ambos")+SUMIFS('S3'!$I$6:$I$24,'S3'!$B$6:$B$24,$A5,'S3'!$E$6:$E$24,"Víctor")+SUMIFS('S3'!$I$6:$I$24,'S3'!$B$6:$B$24,$A5,'S3'!$E$6:$E$24,"Ambos")+SUMIFS('S4'!$I$6:$I$22,'S4'!$B$6:$B$22,$A5,'S4'!$E$6:$E$22,"Víctor")+SUMIFS('S4'!$I$6:$I$22,'S4'!$B$6:$B$22,$A5,'S4'!$E$6:$E$22,"Ambos")+SUMIFS('S5'!$I$6:$I$20,'S5'!$B$6:$B$20,$A5,'S5'!$E$6:$E$20,"Víctor")+SUMIFS('S5'!$I$6:$I$20,'S5'!$B$6:$B$20,$A5,'S5'!$E$6:$E$20,"Ambos")+SUMIFS('S6'!$I$6:$I$17,'S6'!$B$6:$B$17,$A5,'S6'!$E$6:$E$17,"Víctor")+SUMIFS('S6'!$I$6:$I$17,'S6'!$B$6:$B$17,$A5,'S6'!$E$6:$E$17,"Ambos")+SUMIFS('S7'!$I$6:$I$19,'S7'!$B$6:$B$19,$A5,'S7'!$E$6:$E$19,"Víctor")+SUMIFS('S7'!$I$6:$I$19,'S7'!$B$6:$B$19,$A5,'S7'!$E$6:$E$19,"Ambos")+SUMIFS('S8'!$I$6:$I$23,'S8'!$B$6:$B$23,$A5,'S8'!$E$6:$E$23,"Víctor")+SUMIFS('S8'!$I$6:$I$23,'S8'!$B$6:$B$23,$A5,'S8'!$E$6:$E$23,"Ambos")+SUMIFS('S9'!$I$6:$I$15,'S9'!$B$6:$B$15,$A5,'S9'!$E$6:$E$15,"Víctor")+SUMIFS('S9'!$I$6:$I$15,'S9'!$B$6:$B$15,$A5,'S9'!$E$6:$E$15,"Ambos")+SUMIFS('S10'!$I$6:$I$13,'S10'!$B$6:$B$13,$A5,'S10'!$E$6:$E$13,"Víctor")+SUMIFS('S10'!$I$6:$I$13,'S10'!$B$6:$B$13,$A5,'S10'!$E$6:$E$13,"Ambos")+SUMIFS('Holgura'!$I$6:$I$11,'Holgura'!$B$6:$B$11,$A5,'Holgura'!$E$6:$E$11,"Víctor")+SUMIFS('Holgura'!$I$6:$I$11,'Holgura'!$B$6:$B$11,$A5,'Holgura'!$E$6:$E$11,"Ambos")+SUMIFS('Entrega'!$I$6:$I$9,'Entrega'!$B$6:$B$9,$A5,'Entrega'!$E$6:$E$9,"Víctor")+SUMIFS('Entrega'!$I$6:$I$9,'Entrega'!$B$6:$B$9,$A5,'Entrega'!$E$6:$E$9,"Ambos")+SUMIFS('Defensa'!$I$6:$I$10,'Defensa'!$B$6:$B$10,$A5,'Defensa'!$E$6:$E$10,"Víctor")+SUMIFS('Defensa'!$I$6:$I$10,'Defensa'!$B$6:$B$10,$A5,'Defensa'!$E$6:$E$10,"Ambos") | E5: =SUMIFS('S1'!$I$6:$I$32,'S1'!$B$6:$B$32,$A5,'S1'!$E$6:$E$32,"Diego")+SUMIFS('S1'!$I$6:$I$32,'S1'!$B$6:$B$32,$A5,'S1'!$E$6:$E$32,"Ambos")+SUMIFS('S2'!$I$6:$I$23,'S2'!$B$6:$B$23,$A5,'S2'!$E$6:$E$23,"Diego")+SUMIFS('S2'!$I$6:$I$23,'S2'!$B$6:$B$23,$A5,'S2'!$E$6:$E$23,"Ambos")+SUMIFS('S3'!$I$6:$I$24,'S3'!$B$6:$B$24,$A5,'S3'!$E$6:$E$24,"Diego")+SUMIFS('S3'!$I$6:$I$24,'S3'!$B$6:$B$24,$A5,'S3'!$E$6:$E$24,"Ambos")+SUMIFS('S4'!$I$6:$I$22,'S4'!$B$6:$B$22,$A5,'S4'!$E$6:$E$22,"Diego")+SUMIFS('S4'!$I$6:$I$22,'S4'!$B$6:$B$22,$A5,'S4'!$E$6:$E$22,"Ambos")+SUMIFS('S5'!$I$6:$I$20,'S5'!$B$6:$B$20,$A5,'S5'!$E$6:$E$20,"Diego")+SUMIFS('S5'!$I$6:$I$20,'S5'!$B$6:$B$20,$A5,'S5'!$E$6:$E$20,"Ambos")+SUMIFS('S6'!$I$6:$I$17,'S6'!$B$6:$B$17,$A5,'S6'!$E$6:$E$17,"Diego")+SUMIFS('S6'!$I$6:$I$17,'S6'!$B$6:$B$17,$A5,'S6'!$E$6:$E$17,"Ambos")+SUMIFS('S7'!$I$6:$I$19,'S7'!$B$6:$B$19,$A5,'S7'!$E$6:$E$19,"Diego")+SUMIFS('S7'!$I$6:$I$19,'S7'!$B$6:$B$19,$A5,'S7'!$E$6:$E$19,"Ambos")+SUMIFS('S8'!$I$6:$I$23,'S8'!$B$6:$B$23,$A5,'S8'!$E$6:$E$23,"Diego")+SUMIFS('S8'!$I$6:$I$23,'S8'!$B$6:$B$23,$A5,'S8'!$E$6:$E$23,"Ambos")+SUMIFS('S9'!$I$6:$I$15,'S9'!$B$6:$B$15,$A5,'S9'!$E$6:$E$15,"Diego")+SUMIFS('S9'!$I$6:$I$15,'S9'!$B$6:$B$15,$A5,'S9'!$E$6:$E$15,"Ambos")+SUMIFS('S10'!$I$6:$I$13,'S10'!$B$6:$B$13,$A5,'S10'!$E$6:$E$13,"Diego")+SUMIFS('S10'!$I$6:$I$13,'S10'!$B$6:$B$13,$A5,'S10'!$E$6:$E$13,"Ambos")+SUMIFS('Holgura'!$I$6:$I$11,'Holgura'!$B$6:$B$11,$A5,'Holgura'!$E$6:$E$11,"Diego")+SUMIFS('Holgura'!$I$6:$I$11,'Holgura'!$B$6:$B$11,$A5,'Holgura'!$E$6:$E$11,"Ambos")+SUMIFS('Entrega'!$I$6:$I$9,'Entrega'!$B$6:$B$9,$A5,'Entrega'!$E$6:$E$9,"Diego")+SUMIFS('Entrega'!$I$6:$I$9,'Entrega'!$B$6:$B$9,$A5,'Entrega'!$E$6:$E$9,"Ambos")+SUMIFS('Defensa'!$I$6:$I$10,'Defensa'!$B$6:$B$10,$A5,'Defensa'!$E$6:$E$10,"Diego")+SUMIFS('Defensa'!$I$6:$I$10,'Defensa'!$B$6:$B$10,$A5,'Defensa'!$E$6:$E$10,"Ambos") | F5: =COUNTIFS('S1'!$B$6:$B$32,$A5,'S1'!$E$6:$E$32,"Víctor")+COUNTIFS('S1'!$B$6:$B$32,$A5,'S1'!$E$6:$E$32,"Ambos")+COUNTIFS('S2'!$B$6:$B$23,$A5,'S2'!$E$6:$E$23,"Víctor")+COUNTIFS('S2'!$B$6:$B$23,$A5,'S2'!$E$6:$E$23,"Ambos")+COUNTIFS('S3'!$B$6:$B$24,$A5,'S3'!$E$6:$E$24,"Víctor")+COUNTIFS('S3'!$B$6:$B$24,$A5,'S3'!$E$6:$E$24,"Ambos")+COUNTIFS('S4'!$B$6:$B$22,$A5,'S4'!$E$6:$E$22,"Víctor")+COUNTIFS('S4'!$B$6:$B$22,$A5,'S4'!$E$6:$E$22,"Ambos")+COUNTIFS('S5'!$B$6:$B$20,$A5,'S5'!$E$6:$E$20,"Víctor")+COUNTIFS('S5'!$B$6:$B$20,$A5,'S5'!$E$6:$E$20,"Ambos")+COUNTIFS('S6'!$B$6:$B$17,$A5,'S6'!$E$6:$E$17,"Víctor")+COUNTIFS('S6'!$B$6:$B$17,$A5,'S6'!$E$6:$E$17,"Ambos")+COUNTIFS('S7'!$B$6:$B$19,$A5,'S7'!$E$6:$E$19,"Víctor")+COUNTIFS('S7'!$B$6:$B$19,$A5,'S7'!$E$6:$E$19,"Ambos")+COUNTIFS('S8'!$B$6:$B$23,$A5,'S8'!$E$6:$E$23,"Víctor")+COUNTIFS('S8'!$B$6:$B$23,$A5,'S8'!$E$6:$E$23,"Ambos")+COUNTIFS('S9'!$B$6:$B$15,$A5,'S9'!$E$6:$E$15,"Víctor")+COUNTIFS('S9'!$B$6:$B$15,$A5,'S9'!$E$6:$E$15,"Ambos")+COUNTIFS('S10'!$B$6:$B$13,$A5,'S10'!$E$6:$E$13,"Víctor")+COUNTIFS('S10'!$B$6:$B$13,$A5,'S10'!$E$6:$E$13,"Ambos")+COUNTIFS('Holgura'!$B$6:$B$11,$A5,'Holgura'!$E$6:$E$11,"Víctor")+COUNTIFS('Holgura'!$B$6:$B$11,$A5,'Holgura'!$E$6:$E$11,"Ambos")+COUNTIFS('Entrega'!$B$6:$B$9,$A5,'Entrega'!$E$6:$E$9,"Víctor")+COUNTIFS('Entrega'!$B$6:$B$9,$A5,'Entrega'!$E$6:$E$9,"Ambos")+COUNTIFS('Defensa'!$B$6:$B$10,$A5,'Defensa'!$E$6:$E$10,"Víctor")+COUNTIFS('Defensa'!$B$6:$B$10,$A5,'Defensa'!$E$6:$E$10,"Ambos") | G5: =COUNTIFS('S1'!$B$6:$B$32,$A5,'S1'!$E$6:$E$32,"Diego")+COUNTIFS('S1'!$B$6:$B$32,$A5,'S1'!$E$6:$E$32,"Ambos")+COUNTIFS('S2'!$B$6:$B$23,$A5,'S2'!$E$6:$E$23,"Diego")+COUNTIFS('S2'!$B$6:$B$23,$A5,'S2'!$E$6:$E$23,"Ambos")+COUNTIFS('S3'!$B$6:$B$24,$A5,'S3'!$E$6:$E$24,"Diego")+COUNTIFS('S3'!$B$6:$B$24,$A5,'S3'!$E$6:$E$24,"Ambos")+COUNTIFS('S4'!$B$6:$B$22,$A5,'S4'!$E$6:$E$22,"Diego")+COUNTIFS('S4'!$B$6:$B$22,$A5,'S4'!$E$6:$E$22,"Ambos")+COUNTIFS('S5'!$B$6:$B$20,$A5,'S5'!$E$6:$E$20,"Diego")+COUNTIFS('S5'!$B$6:$B$20,$A5,'S5'!$E$6:$E$20,"Ambos")+COUNTIFS('S6'!$B$6:$B$17,$A5,'S6'!$E$6:$E$17,"Diego")+COUNTIFS('S6'!$B$6:$B$17,$A5,'S6'!$E$6:$E$17,"Ambos")+COUNTIFS('S7'!$B$6:$B$19,$A5,'S7'!$E$6:$E$19,"Diego")+COUNTIFS('S7'!$B$6:$B$19,$A5,'S7'!$E$6:$E$19,"Ambos")+COUNTIFS('S8'!$B$6:$B$23,$A5,'S8'!$E$6:$E$23,"Diego")+COUNTIFS('S8'!$B$6:$B$23,$A5,'S8'!$E$6:$E$23,"Ambos")+COUNTIFS('S9'!$B$6:$B$15,$A5,'S9'!$E$6:$E$15,"Diego")+COUNTIFS('S9'!$B$6:$B$15,$A5,'S9'!$E$6:$E$15,"Ambos")+COUNTIFS('S10'!$B$6:$B$13,$A5,'S10'!$E$6:$E$13,"Diego")+COUNTIFS('S10'!$B$6:$B$13,$A5,'S10'!$E$6:$E$13,"Ambos")+COUNTIFS('Holgura'!$B$6:$B$11,$A5,'Holgura'!$E$6:$E$11,"Diego")+COUNTIFS('Holgura'!$B$6:$B$11,$A5,'Holgura'!$E$6:$E$11,"Ambos")+COUNTIFS('Entrega'!$B$6:$B$9,$A5,'Entrega'!$E$6:$E$9,"Diego")+COUNTIFS('Entrega'!$B$6:$B$9,$A5,'Entrega'!$E$6:$E$9,"Ambos")+COUNTIFS('Defensa'!$B$6:$B$10,$A5,'Defensa'!$E$6:$E$10,"Diego")+COUNTIFS('Defensa'!$B$6:$B$10,$A5,'Defensa'!$E$6:$E$10,"Ambos")
A6: 46308 | B6: =A6 | C6: =IF(WEEKDAY(A6,2)>5,4,2) | D6: =SUMIFS('S1'!$I$6:$I$32,'S1'!$B$6:$B$32,$A6,'S1'!$E$6:$E$32,"Víctor")+SUMIFS('S1'!$I$6:$I$32,'S1'!$B$6:$B$32,$A6,'S1'!$E$6:$E$32,"Ambos")+SUMIFS('S2'!$I$6:$I$23,'S2'!$B$6:$B$23,$A6,'S2'!$E$6:$E$23,"Víctor")+SUMIFS('S2'!$I$6:$I$23,'S2'!$B$6:$B$23,$A6,'S2'!$E$6:$E$23,"Ambos")+SUMIFS('S3'!$I$6:$I$24,'S3'!$B$6:$B$24,$A6,'S3'!$E$6:$E$24,"Víctor")+SUMIFS('S3'!$I$6:$I$24,'S3'!$B$6:$B$24,$A6,'S3'!$E$6:$E$24,"Ambos")+SUMIFS('S4'!$I$6:$I$22,'S4'!$B$6:$B$22,$A6,'S4'!$E$6:$E$22,"Víctor")+SUMIFS('S4'!$I$6:$I$22,'S4'!$B$6:$B$22,$A6,'S4'!$E$6:$E$22,"Ambos")+SUMIFS('S5'!$I$6:$I$20,'S5'!$B$6:$B$20,$A6,'S5'!$E$6:$E$20,"Víctor")+SUMIFS('S5'!$I$6:$I$20,'S5'!$B$6:$B$20,$A6,'S5'!$E$6:$E$20,"Ambos")+SUMIFS('S6'!$I$6:$I$17,'S6'!$B$6:$B$17,$A6,'S6'!$E$6:$E$17,"Víctor")+SUMIFS('S6'!$I$6:$I$17,'S6'!$B$6:$B$17,$A6,'S6'!$E$6:$E$17,"Ambos")+SUMIFS('S7'!$I$6:$I$19,'S7'!$B$6:$B$19,$A6,'S7'!$E$6:$E$19,"Víctor")+SUMIFS('S7'!$I$6:$I$19,'S7'!$B$6:$B$19,$A6,'S7'!$E$6:$E$19,"Ambos")+SUMIFS('S8'!$I$6:$I$23,'S8'!$B$6:$B$23,$A6,'S8'!$E$6:$E$23,"Víctor")+SUMIFS('S8'!$I$6:$I$23,'S8'!$B$6:$B$23,$A6,'S8'!$E$6:$E$23,"Ambos")+SUMIFS('S9'!$I$6:$I$15,'S9'!$B$6:$B$15,$A6,'S9'!$E$6:$E$15,"Víctor")+SUMIFS('S9'!$I$6:$I$15,'S9'!$B$6:$B$15,$A6,'S9'!$E$6:$E$15,"Ambos")+SUMIFS('S10'!$I$6:$I$13,'S10'!$B$6:$B$13,$A6,'S10'!$E$6:$E$13,"Víctor")+SUMIFS('S10'!$I$6:$I$13,'S10'!$B$6:$B$13,$A6,'S10'!$E$6:$E$13,"Ambos")+SUMIFS('Holgura'!$I$6:$I$11,'Holgura'!$B$6:$B$11,$A6,'Holgura'!$E$6:$E$11,"Víctor")+SUMIFS('Holgura'!$I$6:$I$11,'Holgura'!$B$6:$B$11,$A6,'Holgura'!$E$6:$E$11,"Ambos")+SUMIFS('Entrega'!$I$6:$I$9,'Entrega'!$B$6:$B$9,$A6,'Entrega'!$E$6:$E$9,"Víctor")+SUMIFS('Entrega'!$I$6:$I$9,'Entrega'!$B$6:$B$9,$A6,'Entrega'!$E$6:$E$9,"Ambos")+SUMIFS('Defensa'!$I$6:$I$10,'Defensa'!$B$6:$B$10,$A6,'Defensa'!$E$6:$E$10,"Víctor")+SUMIFS('Defensa'!$I$6:$I$10,'Defensa'!$B$6:$B$10,$A6,'Defensa'!$E$6:$E$10,"Ambos") | E6: =SUMIFS('S1'!$I$6:$I$32,'S1'!$B$6:$B$32,$A6,'S1'!$E$6:$E$32,"Diego")+SUMIFS('S1'!$I$6:$I$32,'S1'!$B$6:$B$32,$A6,'S1'!$E$6:$E$32,"Ambos")+SUMIFS('S2'!$I$6:$I$23,'S2'!$B$6:$B$23,$A6,'S2'!$E$6:$E$23,"Diego")+SUMIFS('S2'!$I$6:$I$23,'S2'!$B$6:$B$23,$A6,'S2'!$E$6:$E$23,"Ambos")+SUMIFS('S3'!$I$6:$I$24,'S3'!$B$6:$B$24,$A6,'S3'!$E$6:$E$24,"Diego")+SUMIFS('S3'!$I$6:$I$24,'S3'!$B$6:$B$24,$A6,'S3'!$E$6:$E$24,"Ambos")+SUMIFS('S4'!$I$6:$I$22,'S4'!$B$6:$B$22,$A6,'S4'!$E$6:$E$22,"Diego")+SUMIFS('S4'!$I$6:$I$22,'S4'!$B$6:$B$22,$A6,'S4'!$E$6:$E$22,"Ambos")+SUMIFS('S5'!$I$6:$I$20,'S5'!$B$6:$B$20,$A6,'S5'!$E$6:$E$20,"Diego")+SUMIFS('S5'!$I$6:$I$20,'S5'!$B$6:$B$20,$A6,'S5'!$E$6:$E$20,"Ambos")+SUMIFS('S6'!$I$6:$I$17,'S6'!$B$6:$B$17,$A6,'S6'!$E$6:$E$17,"Diego")+SUMIFS('S6'!$I$6:$I$17,'S6'!$B$6:$B$17,$A6,'S6'!$E$6:$E$17,"Ambos")+SUMIFS('S7'!$I$6:$I$19,'S7'!$B$6:$B$19,$A6,'S7'!$E$6:$E$19,"Diego")+SUMIFS('S7'!$I$6:$I$19,'S7'!$B$6:$B$19,$A6,'S7'!$E$6:$E$19,"Ambos")+SUMIFS('S8'!$I$6:$I$23,'S8'!$B$6:$B$23,$A6,'S8'!$E$6:$E$23,"Diego")+SUMIFS('S8'!$I$6:$I$23,'S8'!$B$6:$B$23,$A6,'S8'!$E$6:$E$23,"Ambos")+SUMIFS('S9'!$I$6:$I$15,'S9'!$B$6:$B$15,$A6,'S9'!$E$6:$E$15,"Diego")+SUMIFS('S9'!$I$6:$I$15,'S9'!$B$6:$B$15,$A6,'S9'!$E$6:$E$15,"Ambos")+SUMIFS('S10'!$I$6:$I$13,'S10'!$B$6:$B$13,$A6,'S10'!$E$6:$E$13,"Diego")+SUMIFS('S10'!$I$6:$I$13,'S10'!$B$6:$B$13,$A6,'S10'!$E$6:$E$13,"Ambos")+SUMIFS('Holgura'!$I$6:$I$11,'Holgura'!$B$6:$B$11,$A6,'Holgura'!$E$6:$E$11,"Diego")+SUMIFS('Holgura'!$I$6:$I$11,'Holgura'!$B$6:$B$11,$A6,'Holgura'!$E$6:$E$11,"Ambos")+SUMIFS('Entrega'!$I$6:$I$9,'Entrega'!$B$6:$B$9,$A6,'Entrega'!$E$6:$E$9,"Diego")+SUMIFS('Entrega'!$I$6:$I$9,'Entrega'!$B$6:$B$9,$A6,'Entrega'!$E$6:$E$9,"Ambos")+SUMIFS('Defensa'!$I$6:$I$10,'Defensa'!$B$6:$B$10,$A6,'Defensa'!$E$6:$E$10,"Diego")+SUMIFS('Defensa'!$I$6:$I$10,'Defensa'!$B$6:$B$10,$A6,'Defensa'!$E$6:$E$10,"Ambos") | F6: =COUNTIFS('S1'!$B$6:$B$32,$A6,'S1'!$E$6:$E$32,"Víctor")+COUNTIFS('S1'!$B$6:$B$32,$A6,'S1'!$E$6:$E$32,"Ambos")+COUNTIFS('S2'!$B$6:$B$23,$A6,'S2'!$E$6:$E$23,"Víctor")+COUNTIFS('S2'!$B$6:$B$23,$A6,'S2'!$E$6:$E$23,"Ambos")+COUNTIFS('S3'!$B$6:$B$24,$A6,'S3'!$E$6:$E$24,"Víctor")+COUNTIFS('S3'!$B$6:$B$24,$A6,'S3'!$E$6:$E$24,"Ambos")+COUNTIFS('S4'!$B$6:$B$22,$A6,'S4'!$E$6:$E$22,"Víctor")+COUNTIFS('S4'!$B$6:$B$22,$A6,'S4'!$E$6:$E$22,"Ambos")+COUNTIFS('S5'!$B$6:$B$20,$A6,'S5'!$E$6:$E$20,"Víctor")+COUNTIFS('S5'!$B$6:$B$20,$A6,'S5'!$E$6:$E$20,"Ambos")+COUNTIFS('S6'!$B$6:$B$17,$A6,'S6'!$E$6:$E$17,"Víctor")+COUNTIFS('S6'!$B$6:$B$17,$A6,'S6'!$E$6:$E$17,"Ambos")+COUNTIFS('S7'!$B$6:$B$19,$A6,'S7'!$E$6:$E$19,"Víctor")+COUNTIFS('S7'!$B$6:$B$19,$A6,'S7'!$E$6:$E$19,"Ambos")+COUNTIFS('S8'!$B$6:$B$23,$A6,'S8'!$E$6:$E$23,"Víctor")+COUNTIFS('S8'!$B$6:$B$23,$A6,'S8'!$E$6:$E$23,"Ambos")+COUNTIFS('S9'!$B$6:$B$15,$A6,'S9'!$E$6:$E$15,"Víctor")+COUNTIFS('S9'!$B$6:$B$15,$A6,'S9'!$E$6:$E$15,"Ambos")+COUNTIFS('S10'!$B$6:$B$13,$A6,'S10'!$E$6:$E$13,"Víctor")+COUNTIFS('S10'!$B$6:$B$13,$A6,'S10'!$E$6:$E$13,"Ambos")+COUNTIFS('Holgura'!$B$6:$B$11,$A6,'Holgura'!$E$6:$E$11,"Víctor")+COUNTIFS('Holgura'!$B$6:$B$11,$A6,'Holgura'!$E$6:$E$11,"Ambos")+COUNTIFS('Entrega'!$B$6:$B$9,$A6,'Entrega'!$E$6:$E$9,"Víctor")+COUNTIFS('Entrega'!$B$6:$B$9,$A6,'Entrega'!$E$6:$E$9,"Ambos")+COUNTIFS('Defensa'!$B$6:$B$10,$A6,'Defensa'!$E$6:$E$10,"Víctor")+COUNTIFS('Defensa'!$B$6:$B$10,$A6,'Defensa'!$E$6:$E$10,"Ambos") | G6: =COUNTIFS('S1'!$B$6:$B$32,$A6,'S1'!$E$6:$E$32,"Diego")+COUNTIFS('S1'!$B$6:$B$32,$A6,'S1'!$E$6:$E$32,"Ambos")+COUNTIFS('S2'!$B$6:$B$23,$A6,'S2'!$E$6:$E$23,"Diego")+COUNTIFS('S2'!$B$6:$B$23,$A6,'S2'!$E$6:$E$23,"Ambos")+COUNTIFS('S3'!$B$6:$B$24,$A6,'S3'!$E$6:$E$24,"Diego")+COUNTIFS('S3'!$B$6:$B$24,$A6,'S3'!$E$6:$E$24,"Ambos")+COUNTIFS('S4'!$B$6:$B$22,$A6,'S4'!$E$6:$E$22,"Diego")+COUNTIFS('S4'!$B$6:$B$22,$A6,'S4'!$E$6:$E$22,"Ambos")+COUNTIFS('S5'!$B$6:$B$20,$A6,'S5'!$E$6:$E$20,"Diego")+COUNTIFS('S5'!$B$6:$B$20,$A6,'S5'!$E$6:$E$20,"Ambos")+COUNTIFS('S6'!$B$6:$B$17,$A6,'S6'!$E$6:$E$17,"Diego")+COUNTIFS('S6'!$B$6:$B$17,$A6,'S6'!$E$6:$E$17,"Ambos")+COUNTIFS('S7'!$B$6:$B$19,$A6,'S7'!$E$6:$E$19,"Diego")+COUNTIFS('S7'!$B$6:$B$19,$A6,'S7'!$E$6:$E$19,"Ambos")+COUNTIFS('S8'!$B$6:$B$23,$A6,'S8'!$E$6:$E$23,"Diego")+COUNTIFS('S8'!$B$6:$B$23,$A6,'S8'!$E$6:$E$23,"Ambos")+COUNTIFS('S9'!$B$6:$B$15,$A6,'S9'!$E$6:$E$15,"Diego")+COUNTIFS('S9'!$B$6:$B$15,$A6,'S9'!$E$6:$E$15,"Ambos")+COUNTIFS('S10'!$B$6:$B$13,$A6,'S10'!$E$6:$E$13,"Diego")+COUNTIFS('S10'!$B$6:$B$13,$A6,'S10'!$E$6:$E$13,"Ambos")+COUNTIFS('Holgura'!$B$6:$B$11,$A6,'Holgura'!$E$6:$E$11,"Diego")+COUNTIFS('Holgura'!$B$6:$B$11,$A6,'Holgura'!$E$6:$E$11,"Ambos")+COUNTIFS('Entrega'!$B$6:$B$9,$A6,'Entrega'!$E$6:$E$9,"Diego")+COUNTIFS('Entrega'!$B$6:$B$9,$A6,'Entrega'!$E$6:$E$9,"Ambos")+COUNTIFS('Defensa'!$B$6:$B$10,$A6,'Defensa'!$E$6:$E$10,"Diego")+COUNTIFS('Defensa'!$B$6:$B$10,$A6,'Defensa'!$E$6:$E$10,"Ambos")
A7: 46309 | B7: =A7 | C7: =IF(WEEKDAY(A7,2)>5,4,2) | D7: =SUMIFS('S1'!$I$6:$I$32,'S1'!$B$6:$B$32,$A7,'S1'!$E$6:$E$32,"Víctor")+SUMIFS('S1'!$I$6:$I$32,'S1'!$B$6:$B$32,$A7,'S1'!$E$6:$E$32,"Ambos")+SUMIFS('S2'!$I$6:$I$23,'S2'!$B$6:$B$23,$A7,'S2'!$E$6:$E$23,"Víctor")+SUMIFS('S2'!$I$6:$I$23,'S2'!$B$6:$B$23,$A7,'S2'!$E$6:$E$23,"Ambos")+SUMIFS('S3'!$I$6:$I$24,'S3'!$B$6:$B$24,$A7,'S3'!$E$6:$E$24,"Víctor")+SUMIFS('S3'!$I$6:$I$24,'S3'!$B$6:$B$24,$A7,'S3'!$E$6:$E$24,"Ambos")+SUMIFS('S4'!$I$6:$I$22,'S4'!$B$6:$B$22,$A7,'S4'!$E$6:$E$22,"Víctor")+SUMIFS('S4'!$I$6:$I$22,'S4'!$B$6:$B$22,$A7,'S4'!$E$6:$E$22,"Ambos")+SUMIFS('S5'!$I$6:$I$20,'S5'!$B$6:$B$20,$A7,'S5'!$E$6:$E$20,"Víctor")+SUMIFS('S5'!$I$6:$I$20,'S5'!$B$6:$B$20,$A7,'S5'!$E$6:$E$20,"Ambos")+SUMIFS('S6'!$I$6:$I$17,'S6'!$B$6:$B$17,$A7,'S6'!$E$6:$E$17,"Víctor")+SUMIFS('S6'!$I$6:$I$17,'S6'!$B$6:$B$17,$A7,'S6'!$E$6:$E$17,"Ambos")+SUMIFS('S7'!$I$6:$I$19,'S7'!$B$6:$B$19,$A7,'S7'!$E$6:$E$19,"Víctor")+SUMIFS('S7'!$I$6:$I$19,'S7'!$B$6:$B$19,$A7,'S7'!$E$6:$E$19,"Ambos")+SUMIFS('S8'!$I$6:$I$23,'S8'!$B$6:$B$23,$A7,'S8'!$E$6:$E$23,"Víctor")+SUMIFS('S8'!$I$6:$I$23,'S8'!$B$6:$B$23,$A7,'S8'!$E$6:$E$23,"Ambos")+SUMIFS('S9'!$I$6:$I$15,'S9'!$B$6:$B$15,$A7,'S9'!$E$6:$E$15,"Víctor")+SUMIFS('S9'!$I$6:$I$15,'S9'!$B$6:$B$15,$A7,'S9'!$E$6:$E$15,"Ambos")+SUMIFS('S10'!$I$6:$I$13,'S10'!$B$6:$B$13,$A7,'S10'!$E$6:$E$13,"Víctor")+SUMIFS('S10'!$I$6:$I$13,'S10'!$B$6:$B$13,$A7,'S10'!$E$6:$E$13,"Ambos")+SUMIFS('Holgura'!$I$6:$I$11,'Holgura'!$B$6:$B$11,$A7,'Holgura'!$E$6:$E$11,"Víctor")+SUMIFS('Holgura'!$I$6:$I$11,'Holgura'!$B$6:$B$11,$A7,'Holgura'!$E$6:$E$11,"Ambos")+SUMIFS('Entrega'!$I$6:$I$9,'Entrega'!$B$6:$B$9,$A7,'Entrega'!$E$6:$E$9,"Víctor")+SUMIFS('Entrega'!$I$6:$I$9,'Entrega'!$B$6:$B$9,$A7,'Entrega'!$E$6:$E$9,"Ambos")+SUMIFS('Defensa'!$I$6:$I$10,'Defensa'!$B$6:$B$10,$A7,'Defensa'!$E$6:$E$10,"Víctor")+SUMIFS('Defensa'!$I$6:$I$10,'Defensa'!$B$6:$B$10,$A7,'Defensa'!$E$6:$E$10,"Ambos") | E7: =SUMIFS('S1'!$I$6:$I$32,'S1'!$B$6:$B$32,$A7,'S1'!$E$6:$E$32,"Diego")+SUMIFS('S1'!$I$6:$I$32,'S1'!$B$6:$B$32,$A7,'S1'!$E$6:$E$32,"Ambos")+SUMIFS('S2'!$I$6:$I$23,'S2'!$B$6:$B$23,$A7,'S2'!$E$6:$E$23,"Diego")+SUMIFS('S2'!$I$6:$I$23,'S2'!$B$6:$B$23,$A7,'S2'!$E$6:$E$23,"Ambos")+SUMIFS('S3'!$I$6:$I$24,'S3'!$B$6:$B$24,$A7,'S3'!$E$6:$E$24,"Diego")+SUMIFS('S3'!$I$6:$I$24,'S3'!$B$6:$B$24,$A7,'S3'!$E$6:$E$24,"Ambos")+SUMIFS('S4'!$I$6:$I$22,'S4'!$B$6:$B$22,$A7,'S4'!$E$6:$E$22,"Diego")+SUMIFS('S4'!$I$6:$I$22,'S4'!$B$6:$B$22,$A7,'S4'!$E$6:$E$22,"Ambos")+SUMIFS('S5'!$I$6:$I$20,'S5'!$B$6:$B$20,$A7,'S5'!$E$6:$E$20,"Diego")+SUMIFS('S5'!$I$6:$I$20,'S5'!$B$6:$B$20,$A7,'S5'!$E$6:$E$20,"Ambos")+SUMIFS('S6'!$I$6:$I$17,'S6'!$B$6:$B$17,$A7,'S6'!$E$6:$E$17,"Diego")+SUMIFS('S6'!$I$6:$I$17,'S6'!$B$6:$B$17,$A7,'S6'!$E$6:$E$17,"Ambos")+SUMIFS('S7'!$I$6:$I$19,'S7'!$B$6:$B$19,$A7,'S7'!$E$6:$E$19,"Diego")+SUMIFS('S7'!$I$6:$I$19,'S7'!$B$6:$B$19,$A7,'S7'!$E$6:$E$19,"Ambos")+SUMIFS('S8'!$I$6:$I$23,'S8'!$B$6:$B$23,$A7,'S8'!$E$6:$E$23,"Diego")+SUMIFS('S8'!$I$6:$I$23,'S8'!$B$6:$B$23,$A7,'S8'!$E$6:$E$23,"Ambos")+SUMIFS('S9'!$I$6:$I$15,'S9'!$B$6:$B$15,$A7,'S9'!$E$6:$E$15,"Diego")+SUMIFS('S9'!$I$6:$I$15,'S9'!$B$6:$B$15,$A7,'S9'!$E$6:$E$15,"Ambos")+SUMIFS('S10'!$I$6:$I$13,'S10'!$B$6:$B$13,$A7,'S10'!$E$6:$E$13,"Diego")+SUMIFS('S10'!$I$6:$I$13,'S10'!$B$6:$B$13,$A7,'S10'!$E$6:$E$13,"Ambos")+SUMIFS('Holgura'!$I$6:$I$11,'Holgura'!$B$6:$B$11,$A7,'Holgura'!$E$6:$E$11,"Diego")+SUMIFS('Holgura'!$I$6:$I$11,'Holgura'!$B$6:$B$11,$A7,'Holgura'!$E$6:$E$11,"Ambos")+SUMIFS('Entrega'!$I$6:$I$9,'Entrega'!$B$6:$B$9,$A7,'Entrega'!$E$6:$E$9,"Diego")+SUMIFS('Entrega'!$I$6:$I$9,'Entrega'!$B$6:$B$9,$A7,'Entrega'!$E$6:$E$9,"Ambos")+SUMIFS('Defensa'!$I$6:$I$10,'Defensa'!$B$6:$B$10,$A7,'Defensa'!$E$6:$E$10,"Diego")+SUMIFS('Defensa'!$I$6:$I$10,'Defensa'!$B$6:$B$10,$A7,'Defensa'!$E$6:$E$10,"Ambos") | F7: =COUNTIFS('S1'!$B$6:$B$32,$A7,'S1'!$E$6:$E$32,"Víctor")+COUNTIFS('S1'!$B$6:$B$32,$A7,'S1'!$E$6:$E$32,"Ambos")+COUNTIFS('S2'!$B$6:$B$23,$A7,'S2'!$E$6:$E$23,"Víctor")+COUNTIFS('S2'!$B$6:$B$23,$A7,'S2'!$E$6:$E$23,"Ambos")+COUNTIFS('S3'!$B$6:$B$24,$A7,'S3'!$E$6:$E$24,"Víctor")+COUNTIFS('S3'!$B$6:$B$24,$A7,'S3'!$E$6:$E$24,"Ambos")+COUNTIFS('S4'!$B$6:$B$22,$A7,'S4'!$E$6:$E$22,"Víctor")+COUNTIFS('S4'!$B$6:$B$22,$A7,'S4'!$E$6:$E$22,"Ambos")+COUNTIFS('S5'!$B$6:$B$20,$A7,'S5'!$E$6:$E$20,"Víctor")+COUNTIFS('S5'!$B$6:$B$20,$A7,'S5'!$E$6:$E$20,"Ambos")+COUNTIFS('S6'!$B$6:$B$17,$A7,'S6'!$E$6:$E$17,"Víctor")+COUNTIFS('S6'!$B$6:$B$17,$A7,'S6'!$E$6:$E$17,"Ambos")+COUNTIFS('S7'!$B$6:$B$19,$A7,'S7'!$E$6:$E$19,"Víctor")+COUNTIFS('S7'!$B$6:$B$19,$A7,'S7'!$E$6:$E$19,"Ambos")+COUNTIFS('S8'!$B$6:$B$23,$A7,'S8'!$E$6:$E$23,"Víctor")+COUNTIFS('S8'!$B$6:$B$23,$A7,'S8'!$E$6:$E$23,"Ambos")+COUNTIFS('S9'!$B$6:$B$15,$A7,'S9'!$E$6:$E$15,"Víctor")+COUNTIFS('S9'!$B$6:$B$15,$A7,'S9'!$E$6:$E$15,"Ambos")+COUNTIFS('S10'!$B$6:$B$13,$A7,'S10'!$E$6:$E$13,"Víctor")+COUNTIFS('S10'!$B$6:$B$13,$A7,'S10'!$E$6:$E$13,"Ambos")+COUNTIFS('Holgura'!$B$6:$B$11,$A7,'Holgura'!$E$6:$E$11,"Víctor")+COUNTIFS('Holgura'!$B$6:$B$11,$A7,'Holgura'!$E$6:$E$11,"Ambos")+COUNTIFS('Entrega'!$B$6:$B$9,$A7,'Entrega'!$E$6:$E$9,"Víctor")+COUNTIFS('Entrega'!$B$6:$B$9,$A7,'Entrega'!$E$6:$E$9,"Ambos")+COUNTIFS('Defensa'!$B$6:$B$10,$A7,'Defensa'!$E$6:$E$10,"Víctor")+COUNTIFS('Defensa'!$B$6:$B$10,$A7,'Defensa'!$E$6:$E$10,"Ambos") | G7: =COUNTIFS('S1'!$B$6:$B$32,$A7,'S1'!$E$6:$E$32,"Diego")+COUNTIFS('S1'!$B$6:$B$32,$A7,'S1'!$E$6:$E$32,"Ambos")+COUNTIFS('S2'!$B$6:$B$23,$A7,'S2'!$E$6:$E$23,"Diego")+COUNTIFS('S2'!$B$6:$B$23,$A7,'S2'!$E$6:$E$23,"Ambos")+COUNTIFS('S3'!$B$6:$B$24,$A7,'S3'!$E$6:$E$24,"Diego")+COUNTIFS('S3'!$B$6:$B$24,$A7,'S3'!$E$6:$E$24,"Ambos")+COUNTIFS('S4'!$B$6:$B$22,$A7,'S4'!$E$6:$E$22,"Diego")+COUNTIFS('S4'!$B$6:$B$22,$A7,'S4'!$E$6:$E$22,"Ambos")+COUNTIFS('S5'!$B$6:$B$20,$A7,'S5'!$E$6:$E$20,"Diego")+COUNTIFS('S5'!$B$6:$B$20,$A7,'S5'!$E$6:$E$20,"Ambos")+COUNTIFS('S6'!$B$6:$B$17,$A7,'S6'!$E$6:$E$17,"Diego")+COUNTIFS('S6'!$B$6:$B$17,$A7,'S6'!$E$6:$E$17,"Ambos")+COUNTIFS('S7'!$B$6:$B$19,$A7,'S7'!$E$6:$E$19,"Diego")+COUNTIFS('S7'!$B$6:$B$19,$A7,'S7'!$E$6:$E$19,"Ambos")+COUNTIFS('S8'!$B$6:$B$23,$A7,'S8'!$E$6:$E$23,"Diego")+COUNTIFS('S8'!$B$6:$B$23,$A7,'S8'!$E$6:$E$23,"Ambos")+COUNTIFS('S9'!$B$6:$B$15,$A7,'S9'!$E$6:$E$15,"Diego")+COUNTIFS('S9'!$B$6:$B$15,$A7,'S9'!$E$6:$E$15,"Ambos")+COUNTIFS('S10'!$B$6:$B$13,$A7,'S10'!$E$6:$E$13,"Diego")+COUNTIFS('S10'!$B$6:$B$13,$A7,'S10'!$E$6:$E$13,"Ambos")+COUNTIFS('Holgura'!$B$6:$B$11,$A7,'Holgura'!$E$6:$E$11,"Diego")+COUNTIFS('Holgura'!$B$6:$B$11,$A7,'Holgura'!$E$6:$E$11,"Ambos")+COUNTIFS('Entrega'!$B$6:$B$9,$A7,'Entrega'!$E$6:$E$9,"Diego")+COUNTIFS('Entrega'!$B$6:$B$9,$A7,'Entrega'!$E$6:$E$9,"Ambos")+COUNTIFS('Defensa'!$B$6:$B$10,$A7,'Defensa'!$E$6:$E$10,"Diego")+COUNTIFS('Defensa'!$B$6:$B$10,$A7,'Defensa'!$E$6:$E$10,"Ambos")
A8: 46310 | B8: =A8 | C8: =IF(WEEKDAY(A8,2)>5,4,2) | D8: =SUMIFS('S1'!$I$6:$I$32,'S1'!$B$6:$B$32,$A8,'S1'!$E$6:$E$32,"Víctor")+SUMIFS('S1'!$I$6:$I$32,'S1'!$B$6:$B$32,$A8,'S1'!$E$6:$E$32,"Ambos")+SUMIFS('S2'!$I$6:$I$23,'S2'!$B$6:$B$23,$A8,'S2'!$E$6:$E$23,"Víctor")+SUMIFS('S2'!$I$6:$I$23,'S2'!$B$6:$B$23,$A8,'S2'!$E$6:$E$23,"Ambos")+SUMIFS('S3'!$I$6:$I$24,'S3'!$B$6:$B$24,$A8,'S3'!$E$6:$E$24,"Víctor")+SUMIFS('S3'!$I$6:$I$24,'S3'!$B$6:$B$24,$A8,'S3'!$E$6:$E$24,"Ambos")+SUMIFS('S4'!$I$6:$I$22,'S4'!$B$6:$B$22,$A8,'S4'!$E$6:$E$22,"Víctor")+SUMIFS('S4'!$I$6:$I$22,'S4'!$B$6:$B$22,$A8,'S4'!$E$6:$E$22,"Ambos")+SUMIFS('S5'!$I$6:$I$20,'S5'!$B$6:$B$20,$A8,'S5'!$E$6:$E$20,"Víctor")+SUMIFS('S5'!$I$6:$I$20,'S5'!$B$6:$B$20,$A8,'S5'!$E$6:$E$20,"Ambos")+SUMIFS('S6'!$I$6:$I$17,'S6'!$B$6:$B$17,$A8,'S6'!$E$6:$E$17,"Víctor")+SUMIFS('S6'!$I$6:$I$17,'S6'!$B$6:$B$17,$A8,'S6'!$E$6:$E$17,"Ambos")+SUMIFS('S7'!$I$6:$I$19,'S7'!$B$6:$B$19,$A8,'S7'!$E$6:$E$19,"Víctor")+SUMIFS('S7'!$I$6:$I$19,'S7'!$B$6:$B$19,$A8,'S7'!$E$6:$E$19,"Ambos")+SUMIFS('S8'!$I$6:$I$23,'S8'!$B$6:$B$23,$A8,'S8'!$E$6:$E$23,"Víctor")+SUMIFS('S8'!$I$6:$I$23,'S8'!$B$6:$B$23,$A8,'S8'!$E$6:$E$23,"Ambos")+SUMIFS('S9'!$I$6:$I$15,'S9'!$B$6:$B$15,$A8,'S9'!$E$6:$E$15,"Víctor")+SUMIFS('S9'!$I$6:$I$15,'S9'!$B$6:$B$15,$A8,'S9'!$E$6:$E$15,"Ambos")+SUMIFS('S10'!$I$6:$I$13,'S10'!$B$6:$B$13,$A8,'S10'!$E$6:$E$13,"Víctor")+SUMIFS('S10'!$I$6:$I$13,'S10'!$B$6:$B$13,$A8,'S10'!$E$6:$E$13,"Ambos")+SUMIFS('Holgura'!$I$6:$I$11,'Holgura'!$B$6:$B$11,$A8,'Holgura'!$E$6:$E$11,"Víctor")+SUMIFS('Holgura'!$I$6:$I$11,'Holgura'!$B$6:$B$11,$A8,'Holgura'!$E$6:$E$11,"Ambos")+SUMIFS('Entrega'!$I$6:$I$9,'Entrega'!$B$6:$B$9,$A8,'Entrega'!$E$6:$E$9,"Víctor")+SUMIFS('Entrega'!$I$6:$I$9,'Entrega'!$B$6:$B$9,$A8,'Entrega'!$E$6:$E$9,"Ambos")+SUMIFS('Defensa'!$I$6:$I$10,'Defensa'!$B$6:$B$10,$A8,'Defensa'!$E$6:$E$10,"Víctor")+SUMIFS('Defensa'!$I$6:$I$10,'Defensa'!$B$6:$B$10,$A8,'Defensa'!$E$6:$E$10,"Ambos") | E8: =SUMIFS('S1'!$I$6:$I$32,'S1'!$B$6:$B$32,$A8,'S1'!$E$6:$E$32,"Diego")+SUMIFS('S1'!$I$6:$I$32,'S1'!$B$6:$B$32,$A8,'S1'!$E$6:$E$32,"Ambos")+SUMIFS('S2'!$I$6:$I$23,'S2'!$B$6:$B$23,$A8,'S2'!$E$6:$E$23,"Diego")+SUMIFS('S2'!$I$6:$I$23,'S2'!$B$6:$B$23,$A8,'S2'!$E$6:$E$23,"Ambos")+SUMIFS('S3'!$I$6:$I$24,'S3'!$B$6:$B$24,$A8,'S3'!$E$6:$E$24,"Diego")+SUMIFS('S3'!$I$6:$I$24,'S3'!$B$6:$B$24,$A8,'S3'!$E$6:$E$24,"Ambos")+SUMIFS('S4'!$I$6:$I$22,'S4'!$B$6:$B$22,$A8,'S4'!$E$6:$E$22,"Diego")+SUMIFS('S4'!$I$6:$I$22,'S4'!$B$6:$B$22,$A8,'S4'!$E$6:$E$22,"Ambos")+SUMIFS('S5'!$I$6:$I$20,'S5'!$B$6:$B$20,$A8,'S5'!$E$6:$E$20,"Diego")+SUMIFS('S5'!$I$6:$I$20,'S5'!$B$6:$B$20,$A8,'S5'!$E$6:$E$20,"Ambos")+SUMIFS('S6'!$I$6:$I$17,'S6'!$B$6:$B$17,$A8,'S6'!$E$6:$E$17,"Diego")+SUMIFS('S6'!$I$6:$I$17,'S6'!$B$6:$B$17,$A8,'S6'!$E$6:$E$17,"Ambos")+SUMIFS('S7'!$I$6:$I$19,'S7'!$B$6:$B$19,$A8,'S7'!$E$6:$E$19,"Diego")+SUMIFS('S7'!$I$6:$I$19,'S7'!$B$6:$B$19,$A8,'S7'!$E$6:$E$19,"Ambos")+SUMIFS('S8'!$I$6:$I$23,'S8'!$B$6:$B$23,$A8,'S8'!$E$6:$E$23,"Diego")+SUMIFS('S8'!$I$6:$I$23,'S8'!$B$6:$B$23,$A8,'S8'!$E$6:$E$23,"Ambos")+SUMIFS('S9'!$I$6:$I$15,'S9'!$B$6:$B$15,$A8,'S9'!$E$6:$E$15,"Diego")+SUMIFS('S9'!$I$6:$I$15,'S9'!$B$6:$B$15,$A8,'S9'!$E$6:$E$15,"Ambos")+SUMIFS('S10'!$I$6:$I$13,'S10'!$B$6:$B$13,$A8,'S10'!$E$6:$E$13,"Diego")+SUMIFS('S10'!$I$6:$I$13,'S10'!$B$6:$B$13,$A8,'S10'!$E$6:$E$13,"Ambos")+SUMIFS('Holgura'!$I$6:$I$11,'Holgura'!$B$6:$B$11,$A8,'Holgura'!$E$6:$E$11,"Diego")+SUMIFS('Holgura'!$I$6:$I$11,'Holgura'!$B$6:$B$11,$A8,'Holgura'!$E$6:$E$11,"Ambos")+SUMIFS('Entrega'!$I$6:$I$9,'Entrega'!$B$6:$B$9,$A8,'Entrega'!$E$6:$E$9,"Diego")+SUMIFS('Entrega'!$I$6:$I$9,'Entrega'!$B$6:$B$9,$A8,'Entrega'!$E$6:$E$9,"Ambos")+SUMIFS('Defensa'!$I$6:$I$10,'Defensa'!$B$6:$B$10,$A8,'Defensa'!$E$6:$E$10,"Diego")+SUMIFS('Defensa'!$I$6:$I$10,'Defensa'!$B$6:$B$10,$A8,'Defensa'!$E$6:$E$10,"Ambos") | F8: =COUNTIFS('S1'!$B$6:$B$32,$A8,'S1'!$E$6:$E$32,"Víctor")+COUNTIFS('S1'!$B$6:$B$32,$A8,'S1'!$E$6:$E$32,"Ambos")+COUNTIFS('S2'!$B$6:$B$23,$A8,'S2'!$E$6:$E$23,"Víctor")+COUNTIFS('S2'!$B$6:$B$23,$A8,'S2'!$E$6:$E$23,"Ambos")+COUNTIFS('S3'!$B$6:$B$24,$A8,'S3'!$E$6:$E$24,"Víctor")+COUNTIFS('S3'!$B$6:$B$24,$A8,'S3'!$E$6:$E$24,"Ambos")+COUNTIFS('S4'!$B$6:$B$22,$A8,'S4'!$E$6:$E$22,"Víctor")+COUNTIFS('S4'!$B$6:$B$22,$A8,'S4'!$E$6:$E$22,"Ambos")+COUNTIFS('S5'!$B$6:$B$20,$A8,'S5'!$E$6:$E$20,"Víctor")+COUNTIFS('S5'!$B$6:$B$20,$A8,'S5'!$E$6:$E$20,"Ambos")+COUNTIFS('S6'!$B$6:$B$17,$A8,'S6'!$E$6:$E$17,"Víctor")+COUNTIFS('S6'!$B$6:$B$17,$A8,'S6'!$E$6:$E$17,"Ambos")+COUNTIFS('S7'!$B$6:$B$19,$A8,'S7'!$E$6:$E$19,"Víctor")+COUNTIFS('S7'!$B$6:$B$19,$A8,'S7'!$E$6:$E$19,"Ambos")+COUNTIFS('S8'!$B$6:$B$23,$A8,'S8'!$E$6:$E$23,"Víctor")+COUNTIFS('S8'!$B$6:$B$23,$A8,'S8'!$E$6:$E$23,"Ambos")+COUNTIFS('S9'!$B$6:$B$15,$A8,'S9'!$E$6:$E$15,"Víctor")+COUNTIFS('S9'!$B$6:$B$15,$A8,'S9'!$E$6:$E$15,"Ambos")+COUNTIFS('S10'!$B$6:$B$13,$A8,'S10'!$E$6:$E$13,"Víctor")+COUNTIFS('S10'!$B$6:$B$13,$A8,'S10'!$E$6:$E$13,"Ambos")+COUNTIFS('Holgura'!$B$6:$B$11,$A8,'Holgura'!$E$6:$E$11,"Víctor")+COUNTIFS('Holgura'!$B$6:$B$11,$A8,'Holgura'!$E$6:$E$11,"Ambos")+COUNTIFS('Entrega'!$B$6:$B$9,$A8,'Entrega'!$E$6:$E$9,"Víctor")+COUNTIFS('Entrega'!$B$6:$B$9,$A8,'Entrega'!$E$6:$E$9,"Ambos")+COUNTIFS('Defensa'!$B$6:$B$10,$A8,'Defensa'!$E$6:$E$10,"Víctor")+COUNTIFS('Defensa'!$B$6:$B$10,$A8,'Defensa'!$E$6:$E$10,"Ambos") | G8: =COUNTIFS('S1'!$B$6:$B$32,$A8,'S1'!$E$6:$E$32,"Diego")+COUNTIFS('S1'!$B$6:$B$32,$A8,'S1'!$E$6:$E$32,"Ambos")+COUNTIFS('S2'!$B$6:$B$23,$A8,'S2'!$E$6:$E$23,"Diego")+COUNTIFS('S2'!$B$6:$B$23,$A8,'S2'!$E$6:$E$23,"Ambos")+COUNTIFS('S3'!$B$6:$B$24,$A8,'S3'!$E$6:$E$24,"Diego")+COUNTIFS('S3'!$B$6:$B$24,$A8,'S3'!$E$6:$E$24,"Ambos")+COUNTIFS('S4'!$B$6:$B$22,$A8,'S4'!$E$6:$E$22,"Diego")+COUNTIFS('S4'!$B$6:$B$22,$A8,'S4'!$E$6:$E$22,"Ambos")+COUNTIFS('S5'!$B$6:$B$20,$A8,'S5'!$E$6:$E$20,"Diego")+COUNTIFS('S5'!$B$6:$B$20,$A8,'S5'!$E$6:$E$20,"Ambos")+COUNTIFS('S6'!$B$6:$B$17,$A8,'S6'!$E$6:$E$17,"Diego")+COUNTIFS('S6'!$B$6:$B$17,$A8,'S6'!$E$6:$E$17,"Ambos")+COUNTIFS('S7'!$B$6:$B$19,$A8,'S7'!$E$6:$E$19,"Diego")+COUNTIFS('S7'!$B$6:$B$19,$A8,'S7'!$E$6:$E$19,"Ambos")+COUNTIFS('S8'!$B$6:$B$23,$A8,'S8'!$E$6:$E$23,"Diego")+COUNTIFS('S8'!$B$6:$B$23,$A8,'S8'!$E$6:$E$23,"Ambos")+COUNTIFS('S9'!$B$6:$B$15,$A8,'S9'!$E$6:$E$15,"Diego")+COUNTIFS('S9'!$B$6:$B$15,$A8,'S9'!$E$6:$E$15,"Ambos")+COUNTIFS('S10'!$B$6:$B$13,$A8,'S10'!$E$6:$E$13,"Diego")+COUNTIFS('S10'!$B$6:$B$13,$A8,'S10'!$E$6:$E$13,"Ambos")+COUNTIFS('Holgura'!$B$6:$B$11,$A8,'Holgura'!$E$6:$E$11,"Diego")+COUNTIFS('Holgura'!$B$6:$B$11,$A8,'Holgura'!$E$6:$E$11,"Ambos")+COUNTIFS('Entrega'!$B$6:$B$9,$A8,'Entrega'!$E$6:$E$9,"Diego")+COUNTIFS('Entrega'!$B$6:$B$9,$A8,'Entrega'!$E$6:$E$9,"Ambos")+COUNTIFS('Defensa'!$B$6:$B$10,$A8,'Defensa'!$E$6:$E$10,"Diego")+COUNTIFS('Defensa'!$B$6:$B$10,$A8,'Defensa'!$E$6:$E$10,"Ambos")
A9: 46311 | B9: =A9 | C9: =IF(WEEKDAY(A9,2)>5,4,2) | D9: =SUMIFS('S1'!$I$6:$I$32,'S1'!$B$6:$B$32,$A9,'S1'!$E$6:$E$32,"Víctor")+SUMIFS('S1'!$I$6:$I$32,'S1'!$B$6:$B$32,$A9,'S1'!$E$6:$E$32,"Ambos")+SUMIFS('S2'!$I$6:$I$23,'S2'!$B$6:$B$23,$A9,'S2'!$E$6:$E$23,"Víctor")+SUMIFS('S2'!$I$6:$I$23,'S2'!$B$6:$B$23,$A9,'S2'!$E$6:$E$23,"Ambos")+SUMIFS('S3'!$I$6:$I$24,'S3'!$B$6:$B$24,$A9,'S3'!$E$6:$E$24,"Víctor")+SUMIFS('S3'!$I$6:$I$24,'S3'!$B$6:$B$24,$A9,'S3'!$E$6:$E$24,"Ambos")+SUMIFS('S4'!$I$6:$I$22,'S4'!$B$6:$B$22,$A9,'S4'!$E$6:$E$22,"Víctor")+SUMIFS('S4'!$I$6:$I$22,'S4'!$B$6:$B$22,$A9,'S4'!$E$6:$E$22,"Ambos")+SUMIFS('S5'!$I$6:$I$20,'S5'!$B$6:$B$20,$A9,'S5'!$E$6:$E$20,"Víctor")+SUMIFS('S5'!$I$6:$I$20,'S5'!$B$6:$B$20,$A9,'S5'!$E$6:$E$20,"Ambos")+SUMIFS('S6'!$I$6:$I$17,'S6'!$B$6:$B$17,$A9,'S6'!$E$6:$E$17,"Víctor")+SUMIFS('S6'!$I$6:$I$17,'S6'!$B$6:$B$17,$A9,'S6'!$E$6:$E$17,"Ambos")+SUMIFS('S7'!$I$6:$I$19,'S7'!$B$6:$B$19,$A9,'S7'!$E$6:$E$19,"Víctor")+SUMIFS('S7'!$I$6:$I$19,'S7'!$B$6:$B$19,$A9,'S7'!$E$6:$E$19,"Ambos")+SUMIFS('S8'!$I$6:$I$23,'S8'!$B$6:$B$23,$A9,'S8'!$E$6:$E$23,"Víctor")+SUMIFS('S8'!$I$6:$I$23,'S8'!$B$6:$B$23,$A9,'S8'!$E$6:$E$23,"Ambos")+SUMIFS('S9'!$I$6:$I$15,'S9'!$B$6:$B$15,$A9,'S9'!$E$6:$E$15,"Víctor")+SUMIFS('S9'!$I$6:$I$15,'S9'!$B$6:$B$15,$A9,'S9'!$E$6:$E$15,"Ambos")+SUMIFS('S10'!$I$6:$I$13,'S10'!$B$6:$B$13,$A9,'S10'!$E$6:$E$13,"Víctor")+SUMIFS('S10'!$I$6:$I$13,'S10'!$B$6:$B$13,$A9,'S10'!$E$6:$E$13,"Ambos")+SUMIFS('Holgura'!$I$6:$I$11,'Holgura'!$B$6:$B$11,$A9,'Holgura'!$E$6:$E$11,"Víctor")+SUMIFS('Holgura'!$I$6:$I$11,'Holgura'!$B$6:$B$11,$A9,'Holgura'!$E$6:$E$11,"Ambos")+SUMIFS('Entrega'!$I$6:$I$9,'Entrega'!$B$6:$B$9,$A9,'Entrega'!$E$6:$E$9,"Víctor")+SUMIFS('Entrega'!$I$6:$I$9,'Entrega'!$B$6:$B$9,$A9,'Entrega'!$E$6:$E$9,"Ambos")+SUMIFS('Defensa'!$I$6:$I$10,'Defensa'!$B$6:$B$10,$A9,'Defensa'!$E$6:$E$10,"Víctor")+SUMIFS('Defensa'!$I$6:$I$10,'Defensa'!$B$6:$B$10,$A9,'Defensa'!$E$6:$E$10,"Ambos") | E9: =SUMIFS('S1'!$I$6:$I$32,'S1'!$B$6:$B$32,$A9,'S1'!$E$6:$E$32,"Diego")+SUMIFS('S1'!$I$6:$I$32,'S1'!$B$6:$B$32,$A9,'S1'!$E$6:$E$32,"Ambos")+SUMIFS('S2'!$I$6:$I$23,'S2'!$B$6:$B$23,$A9,'S2'!$E$6:$E$23,"Diego")+SUMIFS('S2'!$I$6:$I$23,'S2'!$B$6:$B$23,$A9,'S2'!$E$6:$E$23,"Ambos")+SUMIFS('S3'!$I$6:$I$24,'S3'!$B$6:$B$24,$A9,'S3'!$E$6:$E$24,"Diego")+SUMIFS('S3'!$I$6:$I$24,'S3'!$B$6:$B$24,$A9,'S3'!$E$6:$E$24,"Ambos")+SUMIFS('S4'!$I$6:$I$22,'S4'!$B$6:$B$22,$A9,'S4'!$E$6:$E$22,"Diego")+SUMIFS('S4'!$I$6:$I$22,'S4'!$B$6:$B$22,$A9,'S4'!$E$6:$E$22,"Ambos")+SUMIFS('S5'!$I$6:$I$20,'S5'!$B$6:$B$20,$A9,'S5'!$E$6:$E$20,"Diego")+SUMIFS('S5'!$I$6:$I$20,'S5'!$B$6:$B$20,$A9,'S5'!$E$6:$E$20,"Ambos")+SUMIFS('S6'!$I$6:$I$17,'S6'!$B$6:$B$17,$A9,'S6'!$E$6:$E$17,"Diego")+SUMIFS('S6'!$I$6:$I$17,'S6'!$B$6:$B$17,$A9,'S6'!$E$6:$E$17,"Ambos")+SUMIFS('S7'!$I$6:$I$19,'S7'!$B$6:$B$19,$A9,'S7'!$E$6:$E$19,"Diego")+SUMIFS('S7'!$I$6:$I$19,'S7'!$B$6:$B$19,$A9,'S7'!$E$6:$E$19,"Ambos")+SUMIFS('S8'!$I$6:$I$23,'S8'!$B$6:$B$23,$A9,'S8'!$E$6:$E$23,"Diego")+SUMIFS('S8'!$I$6:$I$23,'S8'!$B$6:$B$23,$A9,'S8'!$E$6:$E$23,"Ambos")+SUMIFS('S9'!$I$6:$I$15,'S9'!$B$6:$B$15,$A9,'S9'!$E$6:$E$15,"Diego")+SUMIFS('S9'!$I$6:$I$15,'S9'!$B$6:$B$15,$A9,'S9'!$E$6:$E$15,"Ambos")+SUMIFS('S10'!$I$6:$I$13,'S10'!$B$6:$B$13,$A9,'S10'!$E$6:$E$13,"Diego")+SUMIFS('S10'!$I$6:$I$13,'S10'!$B$6:$B$13,$A9,'S10'!$E$6:$E$13,"Ambos")+SUMIFS('Holgura'!$I$6:$I$11,'Holgura'!$B$6:$B$11,$A9,'Holgura'!$E$6:$E$11,"Diego")+SUMIFS('Holgura'!$I$6:$I$11,'Holgura'!$B$6:$B$11,$A9,'Holgura'!$E$6:$E$11,"Ambos")+SUMIFS('Entrega'!$I$6:$I$9,'Entrega'!$B$6:$B$9,$A9,'Entrega'!$E$6:$E$9,"Diego")+SUMIFS('Entrega'!$I$6:$I$9,'Entrega'!$B$6:$B$9,$A9,'Entrega'!$E$6:$E$9,"Ambos")+SUMIFS('Defensa'!$I$6:$I$10,'Defensa'!$B$6:$B$10,$A9,'Defensa'!$E$6:$E$10,"Diego")+SUMIFS('Defensa'!$I$6:$I$10,'Defensa'!$B$6:$B$10,$A9,'Defensa'!$E$6:$E$10,"Ambos") | F9: =COUNTIFS('S1'!$B$6:$B$32,$A9,'S1'!$E$6:$E$32,"Víctor")+COUNTIFS('S1'!$B$6:$B$32,$A9,'S1'!$E$6:$E$32,"Ambos")+COUNTIFS('S2'!$B$6:$B$23,$A9,'S2'!$E$6:$E$23,"Víctor")+COUNTIFS('S2'!$B$6:$B$23,$A9,'S2'!$E$6:$E$23,"Ambos")+COUNTIFS('S3'!$B$6:$B$24,$A9,'S3'!$E$6:$E$24,"Víctor")+COUNTIFS('S3'!$B$6:$B$24,$A9,'S3'!$E$6:$E$24,"Ambos")+COUNTIFS('S4'!$B$6:$B$22,$A9,'S4'!$E$6:$E$22,"Víctor")+COUNTIFS('S4'!$B$6:$B$22,$A9,'S4'!$E$6:$E$22,"Ambos")+COUNTIFS('S5'!$B$6:$B$20,$A9,'S5'!$E$6:$E$20,"Víctor")+COUNTIFS('S5'!$B$6:$B$20,$A9,'S5'!$E$6:$E$20,"Ambos")+COUNTIFS('S6'!$B$6:$B$17,$A9,'S6'!$E$6:$E$17,"Víctor")+COUNTIFS('S6'!$B$6:$B$17,$A9,'S6'!$E$6:$E$17,"Ambos")+COUNTIFS('S7'!$B$6:$B$19,$A9,'S7'!$E$6:$E$19,"Víctor")+COUNTIFS('S7'!$B$6:$B$19,$A9,'S7'!$E$6:$E$19,"Ambos")+COUNTIFS('S8'!$B$6:$B$23,$A9,'S8'!$E$6:$E$23,"Víctor")+COUNTIFS('S8'!$B$6:$B$23,$A9,'S8'!$E$6:$E$23,"Ambos")+COUNTIFS('S9'!$B$6:$B$15,$A9,'S9'!$E$6:$E$15,"Víctor")+COUNTIFS('S9'!$B$6:$B$15,$A9,'S9'!$E$6:$E$15,"Ambos")+COUNTIFS('S10'!$B$6:$B$13,$A9,'S10'!$E$6:$E$13,"Víctor")+COUNTIFS('S10'!$B$6:$B$13,$A9,'S10'!$E$6:$E$13,"Ambos")+COUNTIFS('Holgura'!$B$6:$B$11,$A9,'Holgura'!$E$6:$E$11,"Víctor")+COUNTIFS('Holgura'!$B$6:$B$11,$A9,'Holgura'!$E$6:$E$11,"Ambos")+COUNTIFS('Entrega'!$B$6:$B$9,$A9,'Entrega'!$E$6:$E$9,"Víctor")+COUNTIFS('Entrega'!$B$6:$B$9,$A9,'Entrega'!$E$6:$E$9,"Ambos")+COUNTIFS('Defensa'!$B$6:$B$10,$A9,'Defensa'!$E$6:$E$10,"Víctor")+COUNTIFS('Defensa'!$B$6:$B$10,$A9,'Defensa'!$E$6:$E$10,"Ambos") | G9: =COUNTIFS('S1'!$B$6:$B$32,$A9,'S1'!$E$6:$E$32,"Diego")+COUNTIFS('S1'!$B$6:$B$32,$A9,'S1'!$E$6:$E$32,"Ambos")+COUNTIFS('S2'!$B$6:$B$23,$A9,'S2'!$E$6:$E$23,"Diego")+COUNTIFS('S2'!$B$6:$B$23,$A9,'S2'!$E$6:$E$23,"Ambos")+COUNTIFS('S3'!$B$6:$B$24,$A9,'S3'!$E$6:$E$24,"Diego")+COUNTIFS('S3'!$B$6:$B$24,$A9,'S3'!$E$6:$E$24,"Ambos")+COUNTIFS('S4'!$B$6:$B$22,$A9,'S4'!$E$6:$E$22,"Diego")+COUNTIFS('S4'!$B$6:$B$22,$A9,'S4'!$E$6:$E$22,"Ambos")+COUNTIFS('S5'!$B$6:$B$20,$A9,'S5'!$E$6:$E$20,"Diego")+COUNTIFS('S5'!$B$6:$B$20,$A9,'S5'!$E$6:$E$20,"Ambos")+COUNTIFS('S6'!$B$6:$B$17,$A9,'S6'!$E$6:$E$17,"Diego")+COUNTIFS('S6'!$B$6:$B$17,$A9,'S6'!$E$6:$E$17,"Ambos")+COUNTIFS('S7'!$B$6:$B$19,$A9,'S7'!$E$6:$E$19,"Diego")+COUNTIFS('S7'!$B$6:$B$19,$A9,'S7'!$E$6:$E$19,"Ambos")+COUNTIFS('S8'!$B$6:$B$23,$A9,'S8'!$E$6:$E$23,"Diego")+COUNTIFS('S8'!$B$6:$B$23,$A9,'S8'!$E$6:$E$23,"Ambos")+COUNTIFS('S9'!$B$6:$B$15,$A9,'S9'!$E$6:$E$15,"Diego")+COUNTIFS('S9'!$B$6:$B$15,$A9,'S9'!$E$6:$E$15,"Ambos")+COUNTIFS('S10'!$B$6:$B$13,$A9,'S10'!$E$6:$E$13,"Diego")+COUNTIFS('S10'!$B$6:$B$13,$A9,'S10'!$E$6:$E$13,"Ambos")+COUNTIFS('Holgura'!$B$6:$B$11,$A9,'Holgura'!$E$6:$E$11,"Diego")+COUNTIFS('Holgura'!$B$6:$B$11,$A9,'Holgura'!$E$6:$E$11,"Ambos")+COUNTIFS('Entrega'!$B$6:$B$9,$A9,'Entrega'!$E$6:$E$9,"Diego")+COUNTIFS('Entrega'!$B$6:$B$9,$A9,'Entrega'!$E$6:$E$9,"Ambos")+COUNTIFS('Defensa'!$B$6:$B$10,$A9,'Defensa'!$E$6:$E$10,"Diego")+COUNTIFS('Defensa'!$B$6:$B$10,$A9,'Defensa'!$E$6:$E$10,"Ambos")
A10: 46312 | B10: =A10 | C10: =IF(WEEKDAY(A10,2)>5,4,2) | D10: =SUMIFS('S1'!$I$6:$I$32,'S1'!$B$6:$B$32,$A10,'S1'!$E$6:$E$32,"Víctor")+SUMIFS('S1'!$I$6:$I$32,'S1'!$B$6:$B$32,$A10,'S1'!$E$6:$E$32,"Ambos")+SUMIFS('S2'!$I$6:$I$23,'S2'!$B$6:$B$23,$A10,'S2'!$E$6:$E$23,"Víctor")+SUMIFS('S2'!$I$6:$I$23,'S2'!$B$6:$B$23,$A10,'S2'!$E$6:$E$23,"Ambos")+SUMIFS('S3'!$I$6:$I$24,'S3'!$B$6:$B$24,$A10,'S3'!$E$6:$E$24,"Víctor")+SUMIFS('S3'!$I$6:$I$24,'S3'!$B$6:$B$24,$A10,'S3'!$E$6:$E$24,"Ambos")+SUMIFS('S4'!$I$6:$I$22,'S4'!$B$6:$B$22,$A10,'S4'!$E$6:$E$22,"Víctor")+SUMIFS('S4'!$I$6:$I$22,'S4'!$B$6:$B$22,$A10,'S4'!$E$6:$E$22,"Ambos")+SUMIFS('S5'!$I$6:$I$20,'S5'!$B$6:$B$20,$A10,'S5'!$E$6:$E$20,"Víctor")+SUMIFS('S5'!$I$6:$I$20,'S5'!$B$6:$B$20,$A10,'S5'!$E$6:$E$20,"Ambos")+SUMIFS('S6'!$I$6:$I$17,'S6'!$B$6:$B$17,$A10,'S6'!$E$6:$E$17,"Víctor")+SUMIFS('S6'!$I$6:$I$17,'S6'!$B$6:$B$17,$A10,'S6'!$E$6:$E$17,"Ambos")+SUMIFS('S7'!$I$6:$I$19,'S7'!$B$6:$B$19,$A10,'S7'!$E$6:$E$19,"Víctor")+SUMIFS('S7'!$I$6:$I$19,'S7'!$B$6:$B$19,$A10,'S7'!$E$6:$E$19,"Ambos")+SUMIFS('S8'!$I$6:$I$23,'S8'!$B$6:$B$23,$A10,'S8'!$E$6:$E$23,"Víctor")+SUMIFS('S8'!$I$6:$I$23,'S8'!$B$6:$B$23,$A10,'S8'!$E$6:$E$23,"Ambos")+SUMIFS('S9'!$I$6:$I$15,'S9'!$B$6:$B$15,$A10,'S9'!$E$6:$E$15,"Víctor")+SUMIFS('S9'!$I$6:$I$15,'S9'!$B$6:$B$15,$A10,'S9'!$E$6:$E$15,"Ambos")+SUMIFS('S10'!$I$6:$I$13,'S10'!$B$6:$B$13,$A10,'S10'!$E$6:$E$13,"Víctor")+SUMIFS('S10'!$I$6:$I$13,'S10'!$B$6:$B$13,$A10,'S10'!$E$6:$E$13,"Ambos")+SUMIFS('Holgura'!$I$6:$I$11,'Holgura'!$B$6:$B$11,$A10,'Holgura'!$E$6:$E$11,"Víctor")+SUMIFS('Holgura'!$I$6:$I$11,'Holgura'!$B$6:$B$11,$A10,'Holgura'!$E$6:$E$11,"Ambos")+SUMIFS('Entrega'!$I$6:$I$9,'Entrega'!$B$6:$B$9,$A10,'Entrega'!$E$6:$E$9,"Víctor")+SUMIFS('Entrega'!$I$6:$I$9,'Entrega'!$B$6:$B$9,$A10,'Entrega'!$E$6:$E$9,"Ambos")+SUMIFS('Defensa'!$I$6:$I$10,'Defensa'!$B$6:$B$10,$A10,'Defensa'!$E$6:$E$10,"Víctor")+SUMIFS('Defensa'!$I$6:$I$10,'Defensa'!$B$6:$B$10,$A10,'Defensa'!$E$6:$E$10,"Ambos") | E10: =SUMIFS('S1'!$I$6:$I$32,'S1'!$B$6:$B$32,$A10,'S1'!$E$6:$E$32,"Diego")+SUMIFS('S1'!$I$6:$I$32,'S1'!$B$6:$B$32,$A10,'S1'!$E$6:$E$32,"Ambos")+SUMIFS('S2'!$I$6:$I$23,'S2'!$B$6:$B$23,$A10,'S2'!$E$6:$E$23,"Diego")+SUMIFS('S2'!$I$6:$I$23,'S2'!$B$6:$B$23,$A10,'S2'!$E$6:$E$23,"Ambos")+SUMIFS('S3'!$I$6:$I$24,'S3'!$B$6:$B$24,$A10,'S3'!$E$6:$E$24,"Diego")+SUMIFS('S3'!$I$6:$I$24,'S3'!$B$6:$B$24,$A10,'S3'!$E$6:$E$24,"Ambos")+SUMIFS('S4'!$I$6:$I$22,'S4'!$B$6:$B$22,$A10,'S4'!$E$6:$E$22,"Diego")+SUMIFS('S4'!$I$6:$I$22,'S4'!$B$6:$B$22,$A10,'S4'!$E$6:$E$22,"Ambos")+SUMIFS('S5'!$I$6:$I$20,'S5'!$B$6:$B$20,$A10,'S5'!$E$6:$E$20,"Diego")+SUMIFS('S5'!$I$6:$I$20,'S5'!$B$6:$B$20,$A10,'S5'!$E$6:$E$20,"Ambos")+SUMIFS('S6'!$I$6:$I$17,'S6'!$B$6:$B$17,$A10,'S6'!$E$6:$E$17,"Diego")+SUMIFS('S6'!$I$6:$I$17,'S6'!$B$6:$B$17,$A10,'S6'!$E$6:$E$17,"Ambos")+SUMIFS('S7'!$I$6:$I$19,'S7'!$B$6:$B$19,$A10,'S7'!$E$6:$E$19,"Diego")+SUMIFS('S7'!$I$6:$I$19,'S7'!$B$6:$B$19,$A10,'S7'!$E$6:$E$19,"Ambos")+SUMIFS('S8'!$I$6:$I$23,'S8'!$B$6:$B$23,$A10,'S8'!$E$6:$E$23,"Diego")+SUMIFS('S8'!$I$6:$I$23,'S8'!$B$6:$B$23,$A10,'S8'!$E$6:$E$23,"Ambos")+SUMIFS('S9'!$I$6:$I$15,'S9'!$B$6:$B$15,$A10,'S9'!$E$6:$E$15,"Diego")+SUMIFS('S9'!$I$6:$I$15,'S9'!$B$6:$B$15,$A10,'S9'!$E$6:$E$15,"Ambos")+SUMIFS('S10'!$I$6:$I$13,'S10'!$B$6:$B$13,$A10,'S10'!$E$6:$E$13,"Diego")+SUMIFS('S10'!$I$6:$I$13,'S10'!$B$6:$B$13,$A10,'S10'!$E$6:$E$13,"Ambos")+SUMIFS('Holgura'!$I$6:$I$11,'Holgura'!$B$6:$B$11,$A10,'Holgura'!$E$6:$E$11,"Diego")+SUMIFS('Holgura'!$I$6:$I$11,'Holgura'!$B$6:$B$11,$A10,'Holgura'!$E$6:$E$11,"Ambos")+SUMIFS('Entrega'!$I$6:$I$9,'Entrega'!$B$6:$B$9,$A10,'Entrega'!$E$6:$E$9,"Diego")+SUMIFS('Entrega'!$I$6:$I$9,'Entrega'!$B$6:$B$9,$A10,'Entrega'!$E$6:$E$9,"Ambos")+SUMIFS('Defensa'!$I$6:$I$10,'Defensa'!$B$6:$B$10,$A10,'Defensa'!$E$6:$E$10,"Diego")+SUMIFS('Defensa'!$I$6:$I$10,'Defensa'!$B$6:$B$10,$A10,'Defensa'!$E$6:$E$10,"Ambos") | F10: =COUNTIFS('S1'!$B$6:$B$32,$A10,'S1'!$E$6:$E$32,"Víctor")+COUNTIFS('S1'!$B$6:$B$32,$A10,'S1'!$E$6:$E$32,"Ambos")+COUNTIFS('S2'!$B$6:$B$23,$A10,'S2'!$E$6:$E$23,"Víctor")+COUNTIFS('S2'!$B$6:$B$23,$A10,'S2'!$E$6:$E$23,"Ambos")+COUNTIFS('S3'!$B$6:$B$24,$A10,'S3'!$E$6:$E$24,"Víctor")+COUNTIFS('S3'!$B$6:$B$24,$A10,'S3'!$E$6:$E$24,"Ambos")+COUNTIFS('S4'!$B$6:$B$22,$A10,'S4'!$E$6:$E$22,"Víctor")+COUNTIFS('S4'!$B$6:$B$22,$A10,'S4'!$E$6:$E$22,"Ambos")+COUNTIFS('S5'!$B$6:$B$20,$A10,'S5'!$E$6:$E$20,"Víctor")+COUNTIFS('S5'!$B$6:$B$20,$A10,'S5'!$E$6:$E$20,"Ambos")+COUNTIFS('S6'!$B$6:$B$17,$A10,'S6'!$E$6:$E$17,"Víctor")+COUNTIFS('S6'!$B$6:$B$17,$A10,'S6'!$E$6:$E$17,"Ambos")+COUNTIFS('S7'!$B$6:$B$19,$A10,'S7'!$E$6:$E$19,"Víctor")+COUNTIFS('S7'!$B$6:$B$19,$A10,'S7'!$E$6:$E$19,"Ambos")+COUNTIFS('S8'!$B$6:$B$23,$A10,'S8'!$E$6:$E$23,"Víctor")+COUNTIFS('S8'!$B$6:$B$23,$A10,'S8'!$E$6:$E$23,"Ambos")+COUNTIFS('S9'!$B$6:$B$15,$A10,'S9'!$E$6:$E$15,"Víctor")+COUNTIFS('S9'!$B$6:$B$15,$A10,'S9'!$E$6:$E$15,"Ambos")+COUNTIFS('S10'!$B$6:$B$13,$A10,'S10'!$E$6:$E$13,"Víctor")+COUNTIFS('S10'!$B$6:$B$13,$A10,'S10'!$E$6:$E$13,"Ambos")+COUNTIFS('Holgura'!$B$6:$B$11,$A10,'Holgura'!$E$6:$E$11,"Víctor")+COUNTIFS('Holgura'!$B$6:$B$11,$A10,'Holgura'!$E$6:$E$11,"Ambos")+COUNTIFS('Entrega'!$B$6:$B$9,$A10,'Entrega'!$E$6:$E$9,"Víctor")+COUNTIFS('Entrega'!$B$6:$B$9,$A10,'Entrega'!$E$6:$E$9,"Ambos")+COUNTIFS('Defensa'!$B$6:$B$10,$A10,'Defensa'!$E$6:$E$10,"Víctor")+COUNTIFS('Defensa'!$B$6:$B$10,$A10,'Defensa'!$E$6:$E$10,"Ambos") | G10: =COUNTIFS('S1'!$B$6:$B$32,$A10,'S1'!$E$6:$E$32,"Diego")+COUNTIFS('S1'!$B$6:$B$32,$A10,'S1'!$E$6:$E$32,"Ambos")+COUNTIFS('S2'!$B$6:$B$23,$A10,'S2'!$E$6:$E$23,"Diego")+COUNTIFS('S2'!$B$6:$B$23,$A10,'S2'!$E$6:$E$23,"Ambos")+COUNTIFS('S3'!$B$6:$B$24,$A10,'S3'!$E$6:$E$24,"Diego")+COUNTIFS('S3'!$B$6:$B$24,$A10,'S3'!$E$6:$E$24,"Ambos")+COUNTIFS('S4'!$B$6:$B$22,$A10,'S4'!$E$6:$E$22,"Diego")+COUNTIFS('S4'!$B$6:$B$22,$A10,'S4'!$E$6:$E$22,"Ambos")+COUNTIFS('S5'!$B$6:$B$20,$A10,'S5'!$E$6:$E$20,"Diego")+COUNTIFS('S5'!$B$6:$B$20,$A10,'S5'!$E$6:$E$20,"Ambos")+COUNTIFS('S6'!$B$6:$B$17,$A10,'S6'!$E$6:$E$17,"Diego")+COUNTIFS('S6'!$B$6:$B$17,$A10,'S6'!$E$6:$E$17,"Ambos")+COUNTIFS('S7'!$B$6:$B$19,$A10,'S7'!$E$6:$E$19,"Diego")+COUNTIFS('S7'!$B$6:$B$19,$A10,'S7'!$E$6:$E$19,"Ambos")+COUNTIFS('S8'!$B$6:$B$23,$A10,'S8'!$E$6:$E$23,"Diego")+COUNTIFS('S8'!$B$6:$B$23,$A10,'S8'!$E$6:$E$23,"Ambos")+COUNTIFS('S9'!$B$6:$B$15,$A10,'S9'!$E$6:$E$15,"Diego")+COUNTIFS('S9'!$B$6:$B$15,$A10,'S9'!$E$6:$E$15,"Ambos")+COUNTIFS('S10'!$B$6:$B$13,$A10,'S10'!$E$6:$E$13,"Diego")+COUNTIFS('S10'!$B$6:$B$13,$A10,'S10'!$E$6:$E$13,"Ambos")+COUNTIFS('Holgura'!$B$6:$B$11,$A10,'Holgura'!$E$6:$E$11,"Diego")+COUNTIFS('Holgura'!$B$6:$B$11,$A10,'Holgura'!$E$6:$E$11,"Ambos")+COUNTIFS('Entrega'!$B$6:$B$9,$A10,'Entrega'!$E$6:$E$9,"Diego")+COUNTIFS('Entrega'!$B$6:$B$9,$A10,'Entrega'!$E$6:$E$9,"Ambos")+COUNTIFS('Defensa'!$B$6:$B$10,$A10,'Defensa'!$E$6:$E$10,"Diego")+COUNTIFS('Defensa'!$B$6:$B$10,$A10,'Defensa'!$E$6:$E$10,"Ambos")
A11: 46313 | B11: =A11 | C11: =IF(WEEKDAY(A11,2)>5,4,2) | D11: =SUMIFS('S1'!$I$6:$I$32,'S1'!$B$6:$B$32,$A11,'S1'!$E$6:$E$32,"Víctor")+SUMIFS('S1'!$I$6:$I$32,'S1'!$B$6:$B$32,$A11,'S1'!$E$6:$E$32,"Ambos")+SUMIFS('S2'!$I$6:$I$23,'S2'!$B$6:$B$23,$A11,'S2'!$E$6:$E$23,"Víctor")+SUMIFS('S2'!$I$6:$I$23,'S2'!$B$6:$B$23,$A11,'S2'!$E$6:$E$23,"Ambos")+SUMIFS('S3'!$I$6:$I$24,'S3'!$B$6:$B$24,$A11,'S3'!$E$6:$E$24,"Víctor")+SUMIFS('S3'!$I$6:$I$24,'S3'!$B$6:$B$24,$A11,'S3'!$E$6:$E$24,"Ambos")+SUMIFS('S4'!$I$6:$I$22,'S4'!$B$6:$B$22,$A11,'S4'!$E$6:$E$22,"Víctor")+SUMIFS('S4'!$I$6:$I$22,'S4'!$B$6:$B$22,$A11,'S4'!$E$6:$E$22,"Ambos")+SUMIFS('S5'!$I$6:$I$20,'S5'!$B$6:$B$20,$A11,'S5'!$E$6:$E$20,"Víctor")+SUMIFS('S5'!$I$6:$I$20,'S5'!$B$6:$B$20,$A11,'S5'!$E$6:$E$20,"Ambos")+SUMIFS('S6'!$I$6:$I$17,'S6'!$B$6:$B$17,$A11,'S6'!$E$6:$E$17,"Víctor")+SUMIFS('S6'!$I$6:$I$17,'S6'!$B$6:$B$17,$A11,'S6'!$E$6:$E$17,"Ambos")+SUMIFS('S7'!$I$6:$I$19,'S7'!$B$6:$B$19,$A11,'S7'!$E$6:$E$19,"Víctor")+SUMIFS('S7'!$I$6:$I$19,'S7'!$B$6:$B$19,$A11,'S7'!$E$6:$E$19,"Ambos")+SUMIFS('S8'!$I$6:$I$23,'S8'!$B$6:$B$23,$A11,'S8'!$E$6:$E$23,"Víctor")+SUMIFS('S8'!$I$6:$I$23,'S8'!$B$6:$B$23,$A11,'S8'!$E$6:$E$23,"Ambos")+SUMIFS('S9'!$I$6:$I$15,'S9'!$B$6:$B$15,$A11,'S9'!$E$6:$E$15,"Víctor")+SUMIFS('S9'!$I$6:$I$15,'S9'!$B$6:$B$15,$A11,'S9'!$E$6:$E$15,"Ambos")+SUMIFS('S10'!$I$6:$I$13,'S10'!$B$6:$B$13,$A11,'S10'!$E$6:$E$13,"Víctor")+SUMIFS('S10'!$I$6:$I$13,'S10'!$B$6:$B$13,$A11,'S10'!$E$6:$E$13,"Ambos")+SUMIFS('Holgura'!$I$6:$I$11,'Holgura'!$B$6:$B$11,$A11,'Holgura'!$E$6:$E$11,"Víctor")+SUMIFS('Holgura'!$I$6:$I$11,'Holgura'!$B$6:$B$11,$A11,'Holgura'!$E$6:$E$11,"Ambos")+SUMIFS('Entrega'!$I$6:$I$9,'Entrega'!$B$6:$B$9,$A11,'Entrega'!$E$6:$E$9,"Víctor")+SUMIFS('Entrega'!$I$6:$I$9,'Entrega'!$B$6:$B$9,$A11,'Entrega'!$E$6:$E$9,"Ambos")+SUMIFS('Defensa'!$I$6:$I$10,'Defensa'!$B$6:$B$10,$A11,'Defensa'!$E$6:$E$10,"Víctor")+SUMIFS('Defensa'!$I$6:$I$10,'Defensa'!$B$6:$B$10,$A11,'Defensa'!$E$6:$E$10,"Ambos") | E11: =SUMIFS('S1'!$I$6:$I$32,'S1'!$B$6:$B$32,$A11,'S1'!$E$6:$E$32,"Diego")+SUMIFS('S1'!$I$6:$I$32,'S1'!$B$6:$B$32,$A11,'S1'!$E$6:$E$32,"Ambos")+SUMIFS('S2'!$I$6:$I$23,'S2'!$B$6:$B$23,$A11,'S2'!$E$6:$E$23,"Diego")+SUMIFS('S2'!$I$6:$I$23,'S2'!$B$6:$B$23,$A11,'S2'!$E$6:$E$23,"Ambos")+SUMIFS('S3'!$I$6:$I$24,'S3'!$B$6:$B$24,$A11,'S3'!$E$6:$E$24,"Diego")+SUMIFS('S3'!$I$6:$I$24,'S3'!$B$6:$B$24,$A11,'S3'!$E$6:$E$24,"Ambos")+SUMIFS('S4'!$I$6:$I$22,'S4'!$B$6:$B$22,$A11,'S4'!$E$6:$E$22,"Diego")+SUMIFS('S4'!$I$6:$I$22,'S4'!$B$6:$B$22,$A11,'S4'!$E$6:$E$22,"Ambos")+SUMIFS('S5'!$I$6:$I$20,'S5'!$B$6:$B$20,$A11,'S5'!$E$6:$E$20,"Diego")+SUMIFS('S5'!$I$6:$I$20,'S5'!$B$6:$B$20,$A11,'S5'!$E$6:$E$20,"Ambos")+SUMIFS('S6'!$I$6:$I$17,'S6'!$B$6:$B$17,$A11,'S6'!$E$6:$E$17,"Diego")+SUMIFS('S6'!$I$6:$I$17,'S6'!$B$6:$B$17,$A11,'S6'!$E$6:$E$17,"Ambos")+SUMIFS('S7'!$I$6:$I$19,'S7'!$B$6:$B$19,$A11,'S7'!$E$6:$E$19,"Diego")+SUMIFS('S7'!$I$6:$I$19,'S7'!$B$6:$B$19,$A11,'S7'!$E$6:$E$19,"Ambos")+SUMIFS('S8'!$I$6:$I$23,'S8'!$B$6:$B$23,$A11,'S8'!$E$6:$E$23,"Diego")+SUMIFS('S8'!$I$6:$I$23,'S8'!$B$6:$B$23,$A11,'S8'!$E$6:$E$23,"Ambos")+SUMIFS('S9'!$I$6:$I$15,'S9'!$B$6:$B$15,$A11,'S9'!$E$6:$E$15,"Diego")+SUMIFS('S9'!$I$6:$I$15,'S9'!$B$6:$B$15,$A11,'S9'!$E$6:$E$15,"Ambos")+SUMIFS('S10'!$I$6:$I$13,'S10'!$B$6:$B$13,$A11,'S10'!$E$6:$E$13,"Diego")+SUMIFS('S10'!$I$6:$I$13,'S10'!$B$6:$B$13,$A11,'S10'!$E$6:$E$13,"Ambos")+SUMIFS('Holgura'!$I$6:$I$11,'Holgura'!$B$6:$B$11,$A11,'Holgura'!$E$6:$E$11,"Diego")+SUMIFS('Holgura'!$I$6:$I$11,'Holgura'!$B$6:$B$11,$A11,'Holgura'!$E$6:$E$11,"Ambos")+SUMIFS('Entrega'!$I$6:$I$9,'Entrega'!$B$6:$B$9,$A11,'Entrega'!$E$6:$E$9,"Diego")+SUMIFS('Entrega'!$I$6:$I$9,'Entrega'!$B$6:$B$9,$A11,'Entrega'!$E$6:$E$9,"Ambos")+SUMIFS('Defensa'!$I$6:$I$10,'Defensa'!$B$6:$B$10,$A11,'Defensa'!$E$6:$E$10,"Diego")+SUMIFS('Defensa'!$I$6:$I$10,'Defensa'!$B$6:$B$10,$A11,'Defensa'!$E$6:$E$10,"Ambos") | F11: =COUNTIFS('S1'!$B$6:$B$32,$A11,'S1'!$E$6:$E$32,"Víctor")+COUNTIFS('S1'!$B$6:$B$32,$A11,'S1'!$E$6:$E$32,"Ambos")+COUNTIFS('S2'!$B$6:$B$23,$A11,'S2'!$E$6:$E$23,"Víctor")+COUNTIFS('S2'!$B$6:$B$23,$A11,'S2'!$E$6:$E$23,"Ambos")+COUNTIFS('S3'!$B$6:$B$24,$A11,'S3'!$E$6:$E$24,"Víctor")+COUNTIFS('S3'!$B$6:$B$24,$A11,'S3'!$E$6:$E$24,"Ambos")+COUNTIFS('S4'!$B$6:$B$22,$A11,'S4'!$E$6:$E$22,"Víctor")+COUNTIFS('S4'!$B$6:$B$22,$A11,'S4'!$E$6:$E$22,"Ambos")+COUNTIFS('S5'!$B$6:$B$20,$A11,'S5'!$E$6:$E$20,"Víctor")+COUNTIFS('S5'!$B$6:$B$20,$A11,'S5'!$E$6:$E$20,"Ambos")+COUNTIFS('S6'!$B$6:$B$17,$A11,'S6'!$E$6:$E$17,"Víctor")+COUNTIFS('S6'!$B$6:$B$17,$A11,'S6'!$E$6:$E$17,"Ambos")+COUNTIFS('S7'!$B$6:$B$19,$A11,'S7'!$E$6:$E$19,"Víctor")+COUNTIFS('S7'!$B$6:$B$19,$A11,'S7'!$E$6:$E$19,"Ambos")+COUNTIFS('S8'!$B$6:$B$23,$A11,'S8'!$E$6:$E$23,"Víctor")+COUNTIFS('S8'!$B$6:$B$23,$A11,'S8'!$E$6:$E$23,"Ambos")+COUNTIFS('S9'!$B$6:$B$15,$A11,'S9'!$E$6:$E$15,"Víctor")+COUNTIFS('S9'!$B$6:$B$15,$A11,'S9'!$E$6:$E$15,"Ambos")+COUNTIFS('S10'!$B$6:$B$13,$A11,'S10'!$E$6:$E$13,"Víctor")+COUNTIFS('S10'!$B$6:$B$13,$A11,'S10'!$E$6:$E$13,"Ambos")+COUNTIFS('Holgura'!$B$6:$B$11,$A11,'Holgura'!$E$6:$E$11,"Víctor")+COUNTIFS('Holgura'!$B$6:$B$11,$A11,'Holgura'!$E$6:$E$11,"Ambos")+COUNTIFS('Entrega'!$B$6:$B$9,$A11,'Entrega'!$E$6:$E$9,"Víctor")+COUNTIFS('Entrega'!$B$6:$B$9,$A11,'Entrega'!$E$6:$E$9,"Ambos")+COUNTIFS('Defensa'!$B$6:$B$10,$A11,'Defensa'!$E$6:$E$10,"Víctor")+COUNTIFS('Defensa'!$B$6:$B$10,$A11,'Defensa'!$E$6:$E$10,"Ambos") | G11: =COUNTIFS('S1'!$B$6:$B$32,$A11,'S1'!$E$6:$E$32,"Diego")+COUNTIFS('S1'!$B$6:$B$32,$A11,'S1'!$E$6:$E$32,"Ambos")+COUNTIFS('S2'!$B$6:$B$23,$A11,'S2'!$E$6:$E$23,"Diego")+COUNTIFS('S2'!$B$6:$B$23,$A11,'S2'!$E$6:$E$23,"Ambos")+COUNTIFS('S3'!$B$6:$B$24,$A11,'S3'!$E$6:$E$24,"Diego")+COUNTIFS('S3'!$B$6:$B$24,$A11,'S3'!$E$6:$E$24,"Ambos")+COUNTIFS('S4'!$B$6:$B$22,$A11,'S4'!$E$6:$E$22,"Diego")+COUNTIFS('S4'!$B$6:$B$22,$A11,'S4'!$E$6:$E$22,"Ambos")+COUNTIFS('S5'!$B$6:$B$20,$A11,'S5'!$E$6:$E$20,"Diego")+COUNTIFS('S5'!$B$6:$B$20,$A11,'S5'!$E$6:$E$20,"Ambos")+COUNTIFS('S6'!$B$6:$B$17,$A11,'S6'!$E$6:$E$17,"Diego")+COUNTIFS('S6'!$B$6:$B$17,$A11,'S6'!$E$6:$E$17,"Ambos")+COUNTIFS('S7'!$B$6:$B$19,$A11,'S7'!$E$6:$E$19,"Diego")+COUNTIFS('S7'!$B$6:$B$19,$A11,'S7'!$E$6:$E$19,"Ambos")+COUNTIFS('S8'!$B$6:$B$23,$A11,'S8'!$E$6:$E$23,"Diego")+COUNTIFS('S8'!$B$6:$B$23,$A11,'S8'!$E$6:$E$23,"Ambos")+COUNTIFS('S9'!$B$6:$B$15,$A11,'S9'!$E$6:$E$15,"Diego")+COUNTIFS('S9'!$B$6:$B$15,$A11,'S9'!$E$6:$E$15,"Ambos")+COUNTIFS('S10'!$B$6:$B$13,$A11,'S10'!$E$6:$E$13,"Diego")+COUNTIFS('S10'!$B$6:$B$13,$A11,'S10'!$E$6:$E$13,"Ambos")+COUNTIFS('Holgura'!$B$6:$B$11,$A11,'Holgura'!$E$6:$E$11,"Diego")+COUNTIFS('Holgura'!$B$6:$B$11,$A11,'Holgura'!$E$6:$E$11,"Ambos")+COUNTIFS('Entrega'!$B$6:$B$9,$A11,'Entrega'!$E$6:$E$9,"Diego")+COUNTIFS('Entrega'!$B$6:$B$9,$A11,'Entrega'!$E$6:$E$9,"Ambos")+COUNTIFS('Defensa'!$B$6:$B$10,$A11,'Defensa'!$E$6:$E$10,"Diego")+COUNTIFS('Defensa'!$B$6:$B$10,$A11,'Defensa'!$E$6:$E$10,"Ambos")
A12: 46314 | B12: =A12 | C12: =IF(WEEKDAY(A12,2)>5,4,2) | D12: =SUMIFS('S1'!$I$6:$I$32,'S1'!$B$6:$B$32,$A12,'S1'!$E$6:$E$32,"Víctor")+SUMIFS('S1'!$I$6:$I$32,'S1'!$B$6:$B$32,$A12,'S1'!$E$6:$E$32,"Ambos")+SUMIFS('S2'!$I$6:$I$23,'S2'!$B$6:$B$23,$A12,'S2'!$E$6:$E$23,"Víctor")+SUMIFS('S2'!$I$6:$I$23,'S2'!$B$6:$B$23,$A12,'S2'!$E$6:$E$23,"Ambos")+SUMIFS('S3'!$I$6:$I$24,'S3'!$B$6:$B$24,$A12,'S3'!$E$6:$E$24,"Víctor")+SUMIFS('S3'!$I$6:$I$24,'S3'!$B$6:$B$24,$A12,'S3'!$E$6:$E$24,"Ambos")+SUMIFS('S4'!$I$6:$I$22,'S4'!$B$6:$B$22,$A12,'S4'!$E$6:$E$22,"Víctor")+SUMIFS('S4'!$I$6:$I$22,'S4'!$B$6:$B$22,$A12,'S4'!$E$6:$E$22,"Ambos")+SUMIFS('S5'!$I$6:$I$20,'S5'!$B$6:$B$20,$A12,'S5'!$E$6:$E$20,"Víctor")+SUMIFS('S5'!$I$6:$I$20,'S5'!$B$6:$B$20,$A12,'S5'!$E$6:$E$20,"Ambos")+SUMIFS('S6'!$I$6:$I$17,'S6'!$B$6:$B$17,$A12,'S6'!$E$6:$E$17,"Víctor")+SUMIFS('S6'!$I$6:$I$17,'S6'!$B$6:$B$17,$A12,'S6'!$E$6:$E$17,"Ambos")+SUMIFS('S7'!$I$6:$I$19,'S7'!$B$6:$B$19,$A12,'S7'!$E$6:$E$19,"Víctor")+SUMIFS('S7'!$I$6:$I$19,'S7'!$B$6:$B$19,$A12,'S7'!$E$6:$E$19,"Ambos")+SUMIFS('S8'!$I$6:$I$23,'S8'!$B$6:$B$23,$A12,'S8'!$E$6:$E$23,"Víctor")+SUMIFS('S8'!$I$6:$I$23,'S8'!$B$6:$B$23,$A12,'S8'!$E$6:$E$23,"Ambos")+SUMIFS('S9'!$I$6:$I$15,'S9'!$B$6:$B$15,$A12,'S9'!$E$6:$E$15,"Víctor")+SUMIFS('S9'!$I$6:$I$15,'S9'!$B$6:$B$15,$A12,'S9'!$E$6:$E$15,"Ambos")+SUMIFS('S10'!$I$6:$I$13,'S10'!$B$6:$B$13,$A12,'S10'!$E$6:$E$13,"Víctor")+SUMIFS('S10'!$I$6:$I$13,'S10'!$B$6:$B$13,$A12,'S10'!$E$6:$E$13,"Ambos")+SUMIFS('Holgura'!$I$6:$I$11,'Holgura'!$B$6:$B$11,$A12,'Holgura'!$E$6:$E$11,"Víctor")+SUMIFS('Holgura'!$I$6:$I$11,'Holgura'!$B$6:$B$11,$A12,'Holgura'!$E$6:$E$11,"Ambos")+SUMIFS('Entrega'!$I$6:$I$9,'Entrega'!$B$6:$B$9,$A12,'Entrega'!$E$6:$E$9,"Víctor")+SUMIFS('Entrega'!$I$6:$I$9,'Entrega'!$B$6:$B$9,$A12,'Entrega'!$E$6:$E$9,"Ambos")+SUMIFS('Defensa'!$I$6:$I$10,'Defensa'!$B$6:$B$10,$A12,'Defensa'!$E$6:$E$10,"Víctor")+SUMIFS('Defensa'!$I$6:$I$10,'Defensa'!$B$6:$B$10,$A12,'Defensa'!$E$6:$E$10,"Ambos") | E12: =SUMIFS('S1'!$I$6:$I$32,'S1'!$B$6:$B$32,$A12,'S1'!$E$6:$E$32,"Diego")+SUMIFS('S1'!$I$6:$I$32,'S1'!$B$6:$B$32,$A12,'S1'!$E$6:$E$32,"Ambos")+SUMIFS('S2'!$I$6:$I$23,'S2'!$B$6:$B$23,$A12,'S2'!$E$6:$E$23,"Diego")+SUMIFS('S2'!$I$6:$I$23,'S2'!$B$6:$B$23,$A12,'S2'!$E$6:$E$23,"Ambos")+SUMIFS('S3'!$I$6:$I$24,'S3'!$B$6:$B$24,$A12,'S3'!$E$6:$E$24,"Diego")+SUMIFS('S3'!$I$6:$I$24,'S3'!$B$6:$B$24,$A12,'S3'!$E$6:$E$24,"Ambos")+SUMIFS('S4'!$I$6:$I$22,'S4'!$B$6:$B$22,$A12,'S4'!$E$6:$E$22,"Diego")+SUMIFS('S4'!$I$6:$I$22,'S4'!$B$6:$B$22,$A12,'S4'!$E$6:$E$22,"Ambos")+SUMIFS('S5'!$I$6:$I$20,'S5'!$B$6:$B$20,$A12,'S5'!$E$6:$E$20,"Diego")+SUMIFS('S5'!$I$6:$I$20,'S5'!$B$6:$B$20,$A12,'S5'!$E$6:$E$20,"Ambos")+SUMIFS('S6'!$I$6:$I$17,'S6'!$B$6:$B$17,$A12,'S6'!$E$6:$E$17,"Diego")+SUMIFS('S6'!$I$6:$I$17,'S6'!$B$6:$B$17,$A12,'S6'!$E$6:$E$17,"Ambos")+SUMIFS('S7'!$I$6:$I$19,'S7'!$B$6:$B$19,$A12,'S7'!$E$6:$E$19,"Diego")+SUMIFS('S7'!$I$6:$I$19,'S7'!$B$6:$B$19,$A12,'S7'!$E$6:$E$19,"Ambos")+SUMIFS('S8'!$I$6:$I$23,'S8'!$B$6:$B$23,$A12,'S8'!$E$6:$E$23,"Diego")+SUMIFS('S8'!$I$6:$I$23,'S8'!$B$6:$B$23,$A12,'S8'!$E$6:$E$23,"Ambos")+SUMIFS('S9'!$I$6:$I$15,'S9'!$B$6:$B$15,$A12,'S9'!$E$6:$E$15,"Diego")+SUMIFS('S9'!$I$6:$I$15,'S9'!$B$6:$B$15,$A12,'S9'!$E$6:$E$15,"Ambos")+SUMIFS('S10'!$I$6:$I$13,'S10'!$B$6:$B$13,$A12,'S10'!$E$6:$E$13,"Diego")+SUMIFS('S10'!$I$6:$I$13,'S10'!$B$6:$B$13,$A12,'S10'!$E$6:$E$13,"Ambos")+SUMIFS('Holgura'!$I$6:$I$11,'Holgura'!$B$6:$B$11,$A12,'Holgura'!$E$6:$E$11,"Diego")+SUMIFS('Holgura'!$I$6:$I$11,'Holgura'!$B$6:$B$11,$A12,'Holgura'!$E$6:$E$11,"Ambos")+SUMIFS('Entrega'!$I$6:$I$9,'Entrega'!$B$6:$B$9,$A12,'Entrega'!$E$6:$E$9,"Diego")+SUMIFS('Entrega'!$I$6:$I$9,'Entrega'!$B$6:$B$9,$A12,'Entrega'!$E$6:$E$9,"Ambos")+SUMIFS('Defensa'!$I$6:$I$10,'Defensa'!$B$6:$B$10,$A12,'Defensa'!$E$6:$E$10,"Diego")+SUMIFS('Defensa'!$I$6:$I$10,'Defensa'!$B$6:$B$10,$A12,'Defensa'!$E$6:$E$10,"Ambos") | F12: =COUNTIFS('S1'!$B$6:$B$32,$A12,'S1'!$E$6:$E$32,"Víctor")+COUNTIFS('S1'!$B$6:$B$32,$A12,'S1'!$E$6:$E$32,"Ambos")+COUNTIFS('S2'!$B$6:$B$23,$A12,'S2'!$E$6:$E$23,"Víctor")+COUNTIFS('S2'!$B$6:$B$23,$A12,'S2'!$E$6:$E$23,"Ambos")+COUNTIFS('S3'!$B$6:$B$24,$A12,'S3'!$E$6:$E$24,"Víctor")+COUNTIFS('S3'!$B$6:$B$24,$A12,'S3'!$E$6:$E$24,"Ambos")+COUNTIFS('S4'!$B$6:$B$22,$A12,'S4'!$E$6:$E$22,"Víctor")+COUNTIFS('S4'!$B$6:$B$22,$A12,'S4'!$E$6:$E$22,"Ambos")+COUNTIFS('S5'!$B$6:$B$20,$A12,'S5'!$E$6:$E$20,"Víctor")+COUNTIFS('S5'!$B$6:$B$20,$A12,'S5'!$E$6:$E$20,"Ambos")+COUNTIFS('S6'!$B$6:$B$17,$A12,'S6'!$E$6:$E$17,"Víctor")+COUNTIFS('S6'!$B$6:$B$17,$A12,'S6'!$E$6:$E$17,"Ambos")+COUNTIFS('S7'!$B$6:$B$19,$A12,'S7'!$E$6:$E$19,"Víctor")+COUNTIFS('S7'!$B$6:$B$19,$A12,'S7'!$E$6:$E$19,"Ambos")+COUNTIFS('S8'!$B$6:$B$23,$A12,'S8'!$E$6:$E$23,"Víctor")+COUNTIFS('S8'!$B$6:$B$23,$A12,'S8'!$E$6:$E$23,"Ambos")+COUNTIFS('S9'!$B$6:$B$15,$A12,'S9'!$E$6:$E$15,"Víctor")+COUNTIFS('S9'!$B$6:$B$15,$A12,'S9'!$E$6:$E$15,"Ambos")+COUNTIFS('S10'!$B$6:$B$13,$A12,'S10'!$E$6:$E$13,"Víctor")+COUNTIFS('S10'!$B$6:$B$13,$A12,'S10'!$E$6:$E$13,"Ambos")+COUNTIFS('Holgura'!$B$6:$B$11,$A12,'Holgura'!$E$6:$E$11,"Víctor")+COUNTIFS('Holgura'!$B$6:$B$11,$A12,'Holgura'!$E$6:$E$11,"Ambos")+COUNTIFS('Entrega'!$B$6:$B$9,$A12,'Entrega'!$E$6:$E$9,"Víctor")+COUNTIFS('Entrega'!$B$6:$B$9,$A12,'Entrega'!$E$6:$E$9,"Ambos")+COUNTIFS('Defensa'!$B$6:$B$10,$A12,'Defensa'!$E$6:$E$10,"Víctor")+COUNTIFS('Defensa'!$B$6:$B$10,$A12,'Defensa'!$E$6:$E$10,"Ambos") | G12: =COUNTIFS('S1'!$B$6:$B$32,$A12,'S1'!$E$6:$E$32,"Diego")+COUNTIFS('S1'!$B$6:$B$32,$A12,'S1'!$E$6:$E$32,"Ambos")+COUNTIFS('S2'!$B$6:$B$23,$A12,'S2'!$E$6:$E$23,"Diego")+COUNTIFS('S2'!$B$6:$B$23,$A12,'S2'!$E$6:$E$23,"Ambos")+COUNTIFS('S3'!$B$6:$B$24,$A12,'S3'!$E$6:$E$24,"Diego")+COUNTIFS('S3'!$B$6:$B$24,$A12,'S3'!$E$6:$E$24,"Ambos")+COUNTIFS('S4'!$B$6:$B$22,$A12,'S4'!$E$6:$E$22,"Diego")+COUNTIFS('S4'!$B$6:$B$22,$A12,'S4'!$E$6:$E$22,"Ambos")+COUNTIFS('S5'!$B$6:$B$20,$A12,'S5'!$E$6:$E$20,"Diego")+COUNTIFS('S5'!$B$6:$B$20,$A12,'S5'!$E$6:$E$20,"Ambos")+COUNTIFS('S6'!$B$6:$B$17,$A12,'S6'!$E$6:$E$17,"Diego")+COUNTIFS('S6'!$B$6:$B$17,$A12,'S6'!$E$6:$E$17,"Ambos")+COUNTIFS('S7'!$B$6:$B$19,$A12,'S7'!$E$6:$E$19,"Diego")+COUNTIFS('S7'!$B$6:$B$19,$A12,'S7'!$E$6:$E$19,"Ambos")+COUNTIFS('S8'!$B$6:$B$23,$A12,'S8'!$E$6:$E$23,"Diego")+COUNTIFS('S8'!$B$6:$B$23,$A12,'S8'!$E$6:$E$23,"Ambos")+COUNTIFS('S9'!$B$6:$B$15,$A12,'S9'!$E$6:$E$15,"Diego")+COUNTIFS('S9'!$B$6:$B$15,$A12,'S9'!$E$6:$E$15,"Ambos")+COUNTIFS('S10'!$B$6:$B$13,$A12,'S10'!$E$6:$E$13,"Diego")+COUNTIFS('S10'!$B$6:$B$13,$A12,'S10'!$E$6:$E$13,"Ambos")+COUNTIFS('Holgura'!$B$6:$B$11,$A12,'Holgura'!$E$6:$E$11,"Diego")+COUNTIFS('Holgura'!$B$6:$B$11,$A12,'Holgura'!$E$6:$E$11,"Ambos")+COUNTIFS('Entrega'!$B$6:$B$9,$A12,'Entrega'!$E$6:$E$9,"Diego")+COUNTIFS('Entrega'!$B$6:$B$9,$A12,'Entrega'!$E$6:$E$9,"Ambos")+COUNTIFS('Defensa'!$B$6:$B$10,$A12,'Defensa'!$E$6:$E$10,"Diego")+COUNTIFS('Defensa'!$B$6:$B$10,$A12,'Defensa'!$E$6:$E$10,"Ambos")
A13: 46315 | B13: =A13 | C13: =IF(WEEKDAY(A13,2)>5,4,2) | D13: =SUMIFS('S1'!$I$6:$I$32,'S1'!$B$6:$B$32,$A13,'S1'!$E$6:$E$32,"Víctor")+SUMIFS('S1'!$I$6:$I$32,'S1'!$B$6:$B$32,$A13,'S1'!$E$6:$E$32,"Ambos")+SUMIFS('S2'!$I$6:$I$23,'S2'!$B$6:$B$23,$A13,'S2'!$E$6:$E$23,"Víctor")+SUMIFS('S2'!$I$6:$I$23,'S2'!$B$6:$B$23,$A13,'S2'!$E$6:$E$23,"Ambos")+SUMIFS('S3'!$I$6:$I$24,'S3'!$B$6:$B$24,$A13,'S3'!$E$6:$E$24,"Víctor")+SUMIFS('S3'!$I$6:$I$24,'S3'!$B$6:$B$24,$A13,'S3'!$E$6:$E$24,"Ambos")+SUMIFS('S4'!$I$6:$I$22,'S4'!$B$6:$B$22,$A13,'S4'!$E$6:$E$22,"Víctor")+SUMIFS('S4'!$I$6:$I$22,'S4'!$B$6:$B$22,$A13,'S4'!$E$6:$E$22,"Ambos")+SUMIFS('S5'!$I$6:$I$20,'S5'!$B$6:$B$20,$A13,'S5'!$E$6:$E$20,"Víctor")+SUMIFS('S5'!$I$6:$I$20,'S5'!$B$6:$B$20,$A13,'S5'!$E$6:$E$20,"Ambos")+SUMIFS('S6'!$I$6:$I$17,'S6'!$B$6:$B$17,$A13,'S6'!$E$6:$E$17,"Víctor")+SUMIFS('S6'!$I$6:$I$17,'S6'!$B$6:$B$17,$A13,'S6'!$E$6:$E$17,"Ambos")+SUMIFS('S7'!$I$6:$I$19,'S7'!$B$6:$B$19,$A13,'S7'!$E$6:$E$19,"Víctor")+SUMIFS('S7'!$I$6:$I$19,'S7'!$B$6:$B$19,$A13,'S7'!$E$6:$E$19,"Ambos")+SUMIFS('S8'!$I$6:$I$23,'S8'!$B$6:$B$23,$A13,'S8'!$E$6:$E$23,"Víctor")+SUMIFS('S8'!$I$6:$I$23,'S8'!$B$6:$B$23,$A13,'S8'!$E$6:$E$23,"Ambos")+SUMIFS('S9'!$I$6:$I$15,'S9'!$B$6:$B$15,$A13,'S9'!$E$6:$E$15,"Víctor")+SUMIFS('S9'!$I$6:$I$15,'S9'!$B$6:$B$15,$A13,'S9'!$E$6:$E$15,"Ambos")+SUMIFS('S10'!$I$6:$I$13,'S10'!$B$6:$B$13,$A13,'S10'!$E$6:$E$13,"Víctor")+SUMIFS('S10'!$I$6:$I$13,'S10'!$B$6:$B$13,$A13,'S10'!$E$6:$E$13,"Ambos")+SUMIFS('Holgura'!$I$6:$I$11,'Holgura'!$B$6:$B$11,$A13,'Holgura'!$E$6:$E$11,"Víctor")+SUMIFS('Holgura'!$I$6:$I$11,'Holgura'!$B$6:$B$11,$A13,'Holgura'!$E$6:$E$11,"Ambos")+SUMIFS('Entrega'!$I$6:$I$9,'Entrega'!$B$6:$B$9,$A13,'Entrega'!$E$6:$E$9,"Víctor")+SUMIFS('Entrega'!$I$6:$I$9,'Entrega'!$B$6:$B$9,$A13,'Entrega'!$E$6:$E$9,"Ambos")+SUMIFS('Defensa'!$I$6:$I$10,'Defensa'!$B$6:$B$10,$A13,'Defensa'!$E$6:$E$10,"Víctor")+SUMIFS('Defensa'!$I$6:$I$10,'Defensa'!$B$6:$B$10,$A13,'Defensa'!$E$6:$E$10,"Ambos") | E13: =SUMIFS('S1'!$I$6:$I$32,'S1'!$B$6:$B$32,$A13,'S1'!$E$6:$E$32,"Diego")+SUMIFS('S1'!$I$6:$I$32,'S1'!$B$6:$B$32,$A13,'S1'!$E$6:$E$32,"Ambos")+SUMIFS('S2'!$I$6:$I$23,'S2'!$B$6:$B$23,$A13,'S2'!$E$6:$E$23,"Diego")+SUMIFS('S2'!$I$6:$I$23,'S2'!$B$6:$B$23,$A13,'S2'!$E$6:$E$23,"Ambos")+SUMIFS('S3'!$I$6:$I$24,'S3'!$B$6:$B$24,$A13,'S3'!$E$6:$E$24,"Diego")+SUMIFS('S3'!$I$6:$I$24,'S3'!$B$6:$B$24,$A13,'S3'!$E$6:$E$24,"Ambos")+SUMIFS('S4'!$I$6:$I$22,'S4'!$B$6:$B$22,$A13,'S4'!$E$6:$E$22,"Diego")+SUMIFS('S4'!$I$6:$I$22,'S4'!$B$6:$B$22,$A13,'S4'!$E$6:$E$22,"Ambos")+SUMIFS('S5'!$I$6:$I$20,'S5'!$B$6:$B$20,$A13,'S5'!$E$6:$E$20,"Diego")+SUMIFS('S5'!$I$6:$I$20,'S5'!$B$6:$B$20,$A13,'S5'!$E$6:$E$20,"Ambos")+SUMIFS('S6'!$I$6:$I$17,'S6'!$B$6:$B$17,$A13,'S6'!$E$6:$E$17,"Diego")+SUMIFS('S6'!$I$6:$I$17,'S6'!$B$6:$B$17,$A13,'S6'!$E$6:$E$17,"Ambos")+SUMIFS('S7'!$I$6:$I$19,'S7'!$B$6:$B$19,$A13,'S7'!$E$6:$E$19,"Diego")+SUMIFS('S7'!$I$6:$I$19,'S7'!$B$6:$B$19,$A13,'S7'!$E$6:$E$19,"Ambos")+SUMIFS('S8'!$I$6:$I$23,'S8'!$B$6:$B$23,$A13,'S8'!$E$6:$E$23,"Diego")+SUMIFS('S8'!$I$6:$I$23,'S8'!$B$6:$B$23,$A13,'S8'!$E$6:$E$23,"Ambos")+SUMIFS('S9'!$I$6:$I$15,'S9'!$B$6:$B$15,$A13,'S9'!$E$6:$E$15,"Diego")+SUMIFS('S9'!$I$6:$I$15,'S9'!$B$6:$B$15,$A13,'S9'!$E$6:$E$15,"Ambos")+SUMIFS('S10'!$I$6:$I$13,'S10'!$B$6:$B$13,$A13,'S10'!$E$6:$E$13,"Diego")+SUMIFS('S10'!$I$6:$I$13,'S10'!$B$6:$B$13,$A13,'S10'!$E$6:$E$13,"Ambos")+SUMIFS('Holgura'!$I$6:$I$11,'Holgura'!$B$6:$B$11,$A13,'Holgura'!$E$6:$E$11,"Diego")+SUMIFS('Holgura'!$I$6:$I$11,'Holgura'!$B$6:$B$11,$A13,'Holgura'!$E$6:$E$11,"Ambos")+SUMIFS('Entrega'!$I$6:$I$9,'Entrega'!$B$6:$B$9,$A13,'Entrega'!$E$6:$E$9,"Diego")+SUMIFS('Entrega'!$I$6:$I$9,'Entrega'!$B$6:$B$9,$A13,'Entrega'!$E$6:$E$9,"Ambos")+SUMIFS('Defensa'!$I$6:$I$10,'Defensa'!$B$6:$B$10,$A13,'Defensa'!$E$6:$E$10,"Diego")+SUMIFS('Defensa'!$I$6:$I$10,'Defensa'!$B$6:$B$10,$A13,'Defensa'!$E$6:$E$10,"Ambos") | F13: =COUNTIFS('S1'!$B$6:$B$32,$A13,'S1'!$E$6:$E$32,"Víctor")+COUNTIFS('S1'!$B$6:$B$32,$A13,'S1'!$E$6:$E$32,"Ambos")+COUNTIFS('S2'!$B$6:$B$23,$A13,'S2'!$E$6:$E$23,"Víctor")+COUNTIFS('S2'!$B$6:$B$23,$A13,'S2'!$E$6:$E$23,"Ambos")+COUNTIFS('S3'!$B$6:$B$24,$A13,'S3'!$E$6:$E$24,"Víctor")+COUNTIFS('S3'!$B$6:$B$24,$A13,'S3'!$E$6:$E$24,"Ambos")+COUNTIFS('S4'!$B$6:$B$22,$A13,'S4'!$E$6:$E$22,"Víctor")+COUNTIFS('S4'!$B$6:$B$22,$A13,'S4'!$E$6:$E$22,"Ambos")+COUNTIFS('S5'!$B$6:$B$20,$A13,'S5'!$E$6:$E$20,"Víctor")+COUNTIFS('S5'!$B$6:$B$20,$A13,'S5'!$E$6:$E$20,"Ambos")+COUNTIFS('S6'!$B$6:$B$17,$A13,'S6'!$E$6:$E$17,"Víctor")+COUNTIFS('S6'!$B$6:$B$17,$A13,'S6'!$E$6:$E$17,"Ambos")+COUNTIFS('S7'!$B$6:$B$19,$A13,'S7'!$E$6:$E$19,"Víctor")+COUNTIFS('S7'!$B$6:$B$19,$A13,'S7'!$E$6:$E$19,"Ambos")+COUNTIFS('S8'!$B$6:$B$23,$A13,'S8'!$E$6:$E$23,"Víctor")+COUNTIFS('S8'!$B$6:$B$23,$A13,'S8'!$E$6:$E$23,"Ambos")+COUNTIFS('S9'!$B$6:$B$15,$A13,'S9'!$E$6:$E$15,"Víctor")+COUNTIFS('S9'!$B$6:$B$15,$A13,'S9'!$E$6:$E$15,"Ambos")+COUNTIFS('S10'!$B$6:$B$13,$A13,'S10'!$E$6:$E$13,"Víctor")+COUNTIFS('S10'!$B$6:$B$13,$A13,'S10'!$E$6:$E$13,"Ambos")+COUNTIFS('Holgura'!$B$6:$B$11,$A13,'Holgura'!$E$6:$E$11,"Víctor")+COUNTIFS('Holgura'!$B$6:$B$11,$A13,'Holgura'!$E$6:$E$11,"Ambos")+COUNTIFS('Entrega'!$B$6:$B$9,$A13,'Entrega'!$E$6:$E$9,"Víctor")+COUNTIFS('Entrega'!$B$6:$B$9,$A13,'Entrega'!$E$6:$E$9,"Ambos")+COUNTIFS('Defensa'!$B$6:$B$10,$A13,'Defensa'!$E$6:$E$10,"Víctor")+COUNTIFS('Defensa'!$B$6:$B$10,$A13,'Defensa'!$E$6:$E$10,"Ambos") | G13: =COUNTIFS('S1'!$B$6:$B$32,$A13,'S1'!$E$6:$E$32,"Diego")+COUNTIFS('S1'!$B$6:$B$32,$A13,'S1'!$E$6:$E$32,"Ambos")+COUNTIFS('S2'!$B$6:$B$23,$A13,'S2'!$E$6:$E$23,"Diego")+COUNTIFS('S2'!$B$6:$B$23,$A13,'S2'!$E$6:$E$23,"Ambos")+COUNTIFS('S3'!$B$6:$B$24,$A13,'S3'!$E$6:$E$24,"Diego")+COUNTIFS('S3'!$B$6:$B$24,$A13,'S3'!$E$6:$E$24,"Ambos")+COUNTIFS('S4'!$B$6:$B$22,$A13,'S4'!$E$6:$E$22,"Diego")+COUNTIFS('S4'!$B$6:$B$22,$A13,'S4'!$E$6:$E$22,"Ambos")+COUNTIFS('S5'!$B$6:$B$20,$A13,'S5'!$E$6:$E$20,"Diego")+COUNTIFS('S5'!$B$6:$B$20,$A13,'S5'!$E$6:$E$20,"Ambos")+COUNTIFS('S6'!$B$6:$B$17,$A13,'S6'!$E$6:$E$17,"Diego")+COUNTIFS('S6'!$B$6:$B$17,$A13,'S6'!$E$6:$E$17,"Ambos")+COUNTIFS('S7'!$B$6:$B$19,$A13,'S7'!$E$6:$E$19,"Diego")+COUNTIFS('S7'!$B$6:$B$19,$A13,'S7'!$E$6:$E$19,"Ambos")+COUNTIFS('S8'!$B$6:$B$23,$A13,'S8'!$E$6:$E$23,"Diego")+COUNTIFS('S8'!$B$6:$B$23,$A13,'S8'!$E$6:$E$23,"Ambos")+COUNTIFS('S9'!$B$6:$B$15,$A13,'S9'!$E$6:$E$15,"Diego")+COUNTIFS('S9'!$B$6:$B$15,$A13,'S9'!$E$6:$E$15,"Ambos")+COUNTIFS('S10'!$B$6:$B$13,$A13,'S10'!$E$6:$E$13,"Diego")+COUNTIFS('S10'!$B$6:$B$13,$A13,'S10'!$E$6:$E$13,"Ambos")+COUNTIFS('Holgura'!$B$6:$B$11,$A13,'Holgura'!$E$6:$E$11,"Diego")+COUNTIFS('Holgura'!$B$6:$B$11,$A13,'Holgura'!$E$6:$E$11,"Ambos")+COUNTIFS('Entrega'!$B$6:$B$9,$A13,'Entrega'!$E$6:$E$9,"Diego")+COUNTIFS('Entrega'!$B$6:$B$9,$A13,'Entrega'!$E$6:$E$9,"Ambos")+COUNTIFS('Defensa'!$B$6:$B$10,$A13,'Defensa'!$E$6:$E$10,"Diego")+COUNTIFS('Defensa'!$B$6:$B$10,$A13,'Defensa'!$E$6:$E$10,"Ambos")
A14: 46316 | B14: =A14 | C14: =IF(WEEKDAY(A14,2)>5,4,2) | D14: =SUMIFS('S1'!$I$6:$I$32,'S1'!$B$6:$B$32,$A14,'S1'!$E$6:$E$32,"Víctor")+SUMIFS('S1'!$I$6:$I$32,'S1'!$B$6:$B$32,$A14,'S1'!$E$6:$E$32,"Ambos")+SUMIFS('S2'!$I$6:$I$23,'S2'!$B$6:$B$23,$A14,'S2'!$E$6:$E$23,"Víctor")+SUMIFS('S2'!$I$6:$I$23,'S2'!$B$6:$B$23,$A14,'S2'!$E$6:$E$23,"Ambos")+SUMIFS('S3'!$I$6:$I$24,'S3'!$B$6:$B$24,$A14,'S3'!$E$6:$E$24,"Víctor")+SUMIFS('S3'!$I$6:$I$24,'S3'!$B$6:$B$24,$A14,'S3'!$E$6:$E$24,"Ambos")+SUMIFS('S4'!$I$6:$I$22,'S4'!$B$6:$B$22,$A14,'S4'!$E$6:$E$22,"Víctor")+SUMIFS('S4'!$I$6:$I$22,'S4'!$B$6:$B$22,$A14,'S4'!$E$6:$E$22,"Ambos")+SUMIFS('S5'!$I$6:$I$20,'S5'!$B$6:$B$20,$A14,'S5'!$E$6:$E$20,"Víctor")+SUMIFS('S5'!$I$6:$I$20,'S5'!$B$6:$B$20,$A14,'S5'!$E$6:$E$20,"Ambos")+SUMIFS('S6'!$I$6:$I$17,'S6'!$B$6:$B$17,$A14,'S6'!$E$6:$E$17,"Víctor")+SUMIFS('S6'!$I$6:$I$17,'S6'!$B$6:$B$17,$A14,'S6'!$E$6:$E$17,"Ambos")+SUMIFS('S7'!$I$6:$I$19,'S7'!$B$6:$B$19,$A14,'S7'!$E$6:$E$19,"Víctor")+SUMIFS('S7'!$I$6:$I$19,'S7'!$B$6:$B$19,$A14,'S7'!$E$6:$E$19,"Ambos")+SUMIFS('S8'!$I$6:$I$23,'S8'!$B$6:$B$23,$A14,'S8'!$E$6:$E$23,"Víctor")+SUMIFS('S8'!$I$6:$I$23,'S8'!$B$6:$B$23,$A14,'S8'!$E$6:$E$23,"Ambos")+SUMIFS('S9'!$I$6:$I$15,'S9'!$B$6:$B$15,$A14,'S9'!$E$6:$E$15,"Víctor")+SUMIFS('S9'!$I$6:$I$15,'S9'!$B$6:$B$15,$A14,'S9'!$E$6:$E$15,"Ambos")+SUMIFS('S10'!$I$6:$I$13,'S10'!$B$6:$B$13,$A14,'S10'!$E$6:$E$13,"Víctor")+SUMIFS('S10'!$I$6:$I$13,'S10'!$B$6:$B$13,$A14,'S10'!$E$6:$E$13,"Ambos")+SUMIFS('Holgura'!$I$6:$I$11,'Holgura'!$B$6:$B$11,$A14,'Holgura'!$E$6:$E$11,"Víctor")+SUMIFS('Holgura'!$I$6:$I$11,'Holgura'!$B$6:$B$11,$A14,'Holgura'!$E$6:$E$11,"Ambos")+SUMIFS('Entrega'!$I$6:$I$9,'Entrega'!$B$6:$B$9,$A14,'Entrega'!$E$6:$E$9,"Víctor")+SUMIFS('Entrega'!$I$6:$I$9,'Entrega'!$B$6:$B$9,$A14,'Entrega'!$E$6:$E$9,"Ambos")+SUMIFS('Defensa'!$I$6:$I$10,'Defensa'!$B$6:$B$10,$A14,'Defensa'!$E$6:$E$10,"Víctor")+SUMIFS('Defensa'!$I$6:$I$10,'Defensa'!$B$6:$B$10,$A14,'Defensa'!$E$6:$E$10,"Ambos") | E14: =SUMIFS('S1'!$I$6:$I$32,'S1'!$B$6:$B$32,$A14,'S1'!$E$6:$E$32,"Diego")+SUMIFS('S1'!$I$6:$I$32,'S1'!$B$6:$B$32,$A14,'S1'!$E$6:$E$32,"Ambos")+SUMIFS('S2'!$I$6:$I$23,'S2'!$B$6:$B$23,$A14,'S2'!$E$6:$E$23,"Diego")+SUMIFS('S2'!$I$6:$I$23,'S2'!$B$6:$B$23,$A14,'S2'!$E$6:$E$23,"Ambos")+SUMIFS('S3'!$I$6:$I$24,'S3'!$B$6:$B$24,$A14,'S3'!$E$6:$E$24,"Diego")+SUMIFS('S3'!$I$6:$I$24,'S3'!$B$6:$B$24,$A14,'S3'!$E$6:$E$24,"Ambos")+SUMIFS('S4'!$I$6:$I$22,'S4'!$B$6:$B$22,$A14,'S4'!$E$6:$E$22,"Diego")+SUMIFS('S4'!$I$6:$I$22,'S4'!$B$6:$B$22,$A14,'S4'!$E$6:$E$22,"Ambos")+SUMIFS('S5'!$I$6:$I$20,'S5'!$B$6:$B$20,$A14,'S5'!$E$6:$E$20,"Diego")+SUMIFS('S5'!$I$6:$I$20,'S5'!$B$6:$B$20,$A14,'S5'!$E$6:$E$20,"Ambos")+SUMIFS('S6'!$I$6:$I$17,'S6'!$B$6:$B$17,$A14,'S6'!$E$6:$E$17,"Diego")+SUMIFS('S6'!$I$6:$I$17,'S6'!$B$6:$B$17,$A14,'S6'!$E$6:$E$17,"Ambos")+SUMIFS('S7'!$I$6:$I$19,'S7'!$B$6:$B$19,$A14,'S7'!$E$6:$E$19,"Diego")+SUMIFS('S7'!$I$6:$I$19,'S7'!$B$6:$B$19,$A14,'S7'!$E$6:$E$19,"Ambos")+SUMIFS('S8'!$I$6:$I$23,'S8'!$B$6:$B$23,$A14,'S8'!$E$6:$E$23,"Diego")+SUMIFS('S8'!$I$6:$I$23,'S8'!$B$6:$B$23,$A14,'S8'!$E$6:$E$23,"Ambos")+SUMIFS('S9'!$I$6:$I$15,'S9'!$B$6:$B$15,$A14,'S9'!$E$6:$E$15,"Diego")+SUMIFS('S9'!$I$6:$I$15,'S9'!$B$6:$B$15,$A14,'S9'!$E$6:$E$15,"Ambos")+SUMIFS('S10'!$I$6:$I$13,'S10'!$B$6:$B$13,$A14,'S10'!$E$6:$E$13,"Diego")+SUMIFS('S10'!$I$6:$I$13,'S10'!$B$6:$B$13,$A14,'S10'!$E$6:$E$13,"Ambos")+SUMIFS('Holgura'!$I$6:$I$11,'Holgura'!$B$6:$B$11,$A14,'Holgura'!$E$6:$E$11,"Diego")+SUMIFS('Holgura'!$I$6:$I$11,'Holgura'!$B$6:$B$11,$A14,'Holgura'!$E$6:$E$11,"Ambos")+SUMIFS('Entrega'!$I$6:$I$9,'Entrega'!$B$6:$B$9,$A14,'Entrega'!$E$6:$E$9,"Diego")+SUMIFS('Entrega'!$I$6:$I$9,'Entrega'!$B$6:$B$9,$A14,'Entrega'!$E$6:$E$9,"Ambos")+SUMIFS('Defensa'!$I$6:$I$10,'Defensa'!$B$6:$B$10,$A14,'Defensa'!$E$6:$E$10,"Diego")+SUMIFS('Defensa'!$I$6:$I$10,'Defensa'!$B$6:$B$10,$A14,'Defensa'!$E$6:$E$10,"Ambos") | F14: =COUNTIFS('S1'!$B$6:$B$32,$A14,'S1'!$E$6:$E$32,"Víctor")+COUNTIFS('S1'!$B$6:$B$32,$A14,'S1'!$E$6:$E$32,"Ambos")+COUNTIFS('S2'!$B$6:$B$23,$A14,'S2'!$E$6:$E$23,"Víctor")+COUNTIFS('S2'!$B$6:$B$23,$A14,'S2'!$E$6:$E$23,"Ambos")+COUNTIFS('S3'!$B$6:$B$24,$A14,'S3'!$E$6:$E$24,"Víctor")+COUNTIFS('S3'!$B$6:$B$24,$A14,'S3'!$E$6:$E$24,"Ambos")+COUNTIFS('S4'!$B$6:$B$22,$A14,'S4'!$E$6:$E$22,"Víctor")+COUNTIFS('S4'!$B$6:$B$22,$A14,'S4'!$E$6:$E$22,"Ambos")+COUNTIFS('S5'!$B$6:$B$20,$A14,'S5'!$E$6:$E$20,"Víctor")+COUNTIFS('S5'!$B$6:$B$20,$A14,'S5'!$E$6:$E$20,"Ambos")+COUNTIFS('S6'!$B$6:$B$17,$A14,'S6'!$E$6:$E$17,"Víctor")+COUNTIFS('S6'!$B$6:$B$17,$A14,'S6'!$E$6:$E$17,"Ambos")+COUNTIFS('S7'!$B$6:$B$19,$A14,'S7'!$E$6:$E$19,"Víctor")+COUNTIFS('S7'!$B$6:$B$19,$A14,'S7'!$E$6:$E$19,"Ambos")+COUNTIFS('S8'!$B$6:$B$23,$A14,'S8'!$E$6:$E$23,"Víctor")+COUNTIFS('S8'!$B$6:$B$23,$A14,'S8'!$E$6:$E$23,"Ambos")+COUNTIFS('S9'!$B$6:$B$15,$A14,'S9'!$E$6:$E$15,"Víctor")+COUNTIFS('S9'!$B$6:$B$15,$A14,'S9'!$E$6:$E$15,"Ambos")+COUNTIFS('S10'!$B$6:$B$13,$A14,'S10'!$E$6:$E$13,"Víctor")+COUNTIFS('S10'!$B$6:$B$13,$A14,'S10'!$E$6:$E$13,"Ambos")+COUNTIFS('Holgura'!$B$6:$B$11,$A14,'Holgura'!$E$6:$E$11,"Víctor")+COUNTIFS('Holgura'!$B$6:$B$11,$A14,'Holgura'!$E$6:$E$11,"Ambos")+COUNTIFS('Entrega'!$B$6:$B$9,$A14,'Entrega'!$E$6:$E$9,"Víctor")+COUNTIFS('Entrega'!$B$6:$B$9,$A14,'Entrega'!$E$6:$E$9,"Ambos")+COUNTIFS('Defensa'!$B$6:$B$10,$A14,'Defensa'!$E$6:$E$10,"Víctor")+COUNTIFS('Defensa'!$B$6:$B$10,$A14,'Defensa'!$E$6:$E$10,"Ambos") | G14: =COUNTIFS('S1'!$B$6:$B$32,$A14,'S1'!$E$6:$E$32,"Diego")+COUNTIFS('S1'!$B$6:$B$32,$A14,'S1'!$E$6:$E$32,"Ambos")+COUNTIFS('S2'!$B$6:$B$23,$A14,'S2'!$E$6:$E$23,"Diego")+COUNTIFS('S2'!$B$6:$B$23,$A14,'S2'!$E$6:$E$23,"Ambos")+COUNTIFS('S3'!$B$6:$B$24,$A14,'S3'!$E$6:$E$24,"Diego")+COUNTIFS('S3'!$B$6:$B$24,$A14,'S3'!$E$6:$E$24,"Ambos")+COUNTIFS('S4'!$B$6:$B$22,$A14,'S4'!$E$6:$E$22,"Diego")+COUNTIFS('S4'!$B$6:$B$22,$A14,'S4'!$E$6:$E$22,"Ambos")+COUNTIFS('S5'!$B$6:$B$20,$A14,'S5'!$E$6:$E$20,"Diego")+COUNTIFS('S5'!$B$6:$B$20,$A14,'S5'!$E$6:$E$20,"Ambos")+COUNTIFS('S6'!$B$6:$B$17,$A14,'S6'!$E$6:$E$17,"Diego")+COUNTIFS('S6'!$B$6:$B$17,$A14,'S6'!$E$6:$E$17,"Ambos")+COUNTIFS('S7'!$B$6:$B$19,$A14,'S7'!$E$6:$E$19,"Diego")+COUNTIFS('S7'!$B$6:$B$19,$A14,'S7'!$E$6:$E$19,"Ambos")+COUNTIFS('S8'!$B$6:$B$23,$A14,'S8'!$E$6:$E$23,"Diego")+COUNTIFS('S8'!$B$6:$B$23,$A14,'S8'!$E$6:$E$23,"Ambos")+COUNTIFS('S9'!$B$6:$B$15,$A14,'S9'!$E$6:$E$15,"Diego")+COUNTIFS('S9'!$B$6:$B$15,$A14,'S9'!$E$6:$E$15,"Ambos")+COUNTIFS('S10'!$B$6:$B$13,$A14,'S10'!$E$6:$E$13,"Diego")+COUNTIFS('S10'!$B$6:$B$13,$A14,'S10'!$E$6:$E$13,"Ambos")+COUNTIFS('Holgura'!$B$6:$B$11,$A14,'Holgura'!$E$6:$E$11,"Diego")+COUNTIFS('Holgura'!$B$6:$B$11,$A14,'Holgura'!$E$6:$E$11,"Ambos")+COUNTIFS('Entrega'!$B$6:$B$9,$A14,'Entrega'!$E$6:$E$9,"Diego")+COUNTIFS('Entrega'!$B$6:$B$9,$A14,'Entrega'!$E$6:$E$9,"Ambos")+COUNTIFS('Defensa'!$B$6:$B$10,$A14,'Defensa'!$E$6:$E$10,"Diego")+COUNTIFS('Defensa'!$B$6:$B$10,$A14,'Defensa'!$E$6:$E$10,"Ambos")
A15: 46317 | B15: =A15 | C15: =IF(WEEKDAY(A15,2)>5,4,2) | D15: =SUMIFS('S1'!$I$6:$I$32,'S1'!$B$6:$B$32,$A15,'S1'!$E$6:$E$32,"Víctor")+SUMIFS('S1'!$I$6:$I$32,'S1'!$B$6:$B$32,$A15,'S1'!$E$6:$E$32,"Ambos")+SUMIFS('S2'!$I$6:$I$23,'S2'!$B$6:$B$23,$A15,'S2'!$E$6:$E$23,"Víctor")+SUMIFS('S2'!$I$6:$I$23,'S2'!$B$6:$B$23,$A15,'S2'!$E$6:$E$23,"Ambos")+SUMIFS('S3'!$I$6:$I$24,'S3'!$B$6:$B$24,$A15,'S3'!$E$6:$E$24,"Víctor")+SUMIFS('S3'!$I$6:$I$24,'S3'!$B$6:$B$24,$A15,'S3'!$E$6:$E$24,"Ambos")+SUMIFS('S4'!$I$6:$I$22,'S4'!$B$6:$B$22,$A15,'S4'!$E$6:$E$22,"Víctor")+SUMIFS('S4'!$I$6:$I$22,'S4'!$B$6:$B$22,$A15,'S4'!$E$6:$E$22,"Ambos")+SUMIFS('S5'!$I$6:$I$20,'S5'!$B$6:$B$20,$A15,'S5'!$E$6:$E$20,"Víctor")+SUMIFS('S5'!$I$6:$I$20,'S5'!$B$6:$B$20,$A15,'S5'!$E$6:$E$20,"Ambos")+SUMIFS('S6'!$I$6:$I$17,'S6'!$B$6:$B$17,$A15,'S6'!$E$6:$E$17,"Víctor")+SUMIFS('S6'!$I$6:$I$17,'S6'!$B$6:$B$17,$A15,'S6'!$E$6:$E$17,"Ambos")+SUMIFS('S7'!$I$6:$I$19,'S7'!$B$6:$B$19,$A15,'S7'!$E$6:$E$19,"Víctor")+SUMIFS('S7'!$I$6:$I$19,'S7'!$B$6:$B$19,$A15,'S7'!$E$6:$E$19,"Ambos")+SUMIFS('S8'!$I$6:$I$23,'S8'!$B$6:$B$23,$A15,'S8'!$E$6:$E$23,"Víctor")+SUMIFS('S8'!$I$6:$I$23,'S8'!$B$6:$B$23,$A15,'S8'!$E$6:$E$23,"Ambos")+SUMIFS('S9'!$I$6:$I$15,'S9'!$B$6:$B$15,$A15,'S9'!$E$6:$E$15,"Víctor")+SUMIFS('S9'!$I$6:$I$15,'S9'!$B$6:$B$15,$A15,'S9'!$E$6:$E$15,"Ambos")+SUMIFS('S10'!$I$6:$I$13,'S10'!$B$6:$B$13,$A15,'S10'!$E$6:$E$13,"Víctor")+SUMIFS('S10'!$I$6:$I$13,'S10'!$B$6:$B$13,$A15,'S10'!$E$6:$E$13,"Ambos")+SUMIFS('Holgura'!$I$6:$I$11,'Holgura'!$B$6:$B$11,$A15,'Holgura'!$E$6:$E$11,"Víctor")+SUMIFS('Holgura'!$I$6:$I$11,'Holgura'!$B$6:$B$11,$A15,'Holgura'!$E$6:$E$11,"Ambos")+SUMIFS('Entrega'!$I$6:$I$9,'Entrega'!$B$6:$B$9,$A15,'Entrega'!$E$6:$E$9,"Víctor")+SUMIFS('Entrega'!$I$6:$I$9,'Entrega'!$B$6:$B$9,$A15,'Entrega'!$E$6:$E$9,"Ambos")+SUMIFS('Defensa'!$I$6:$I$10,'Defensa'!$B$6:$B$10,$A15,'Defensa'!$E$6:$E$10,"Víctor")+SUMIFS('Defensa'!$I$6:$I$10,'Defensa'!$B$6:$B$10,$A15,'Defensa'!$E$6:$E$10,"Ambos") | E15: =SUMIFS('S1'!$I$6:$I$32,'S1'!$B$6:$B$32,$A15,'S1'!$E$6:$E$32,"Diego")+SUMIFS('S1'!$I$6:$I$32,'S1'!$B$6:$B$32,$A15,'S1'!$E$6:$E$32,"Ambos")+SUMIFS('S2'!$I$6:$I$23,'S2'!$B$6:$B$23,$A15,'S2'!$E$6:$E$23,"Diego")+SUMIFS('S2'!$I$6:$I$23,'S2'!$B$6:$B$23,$A15,'S2'!$E$6:$E$23,"Ambos")+SUMIFS('S3'!$I$6:$I$24,'S3'!$B$6:$B$24,$A15,'S3'!$E$6:$E$24,"Diego")+SUMIFS('S3'!$I$6:$I$24,'S3'!$B$6:$B$24,$A15,'S3'!$E$6:$E$24,"Ambos")+SUMIFS('S4'!$I$6:$I$22,'S4'!$B$6:$B$22,$A15,'S4'!$E$6:$E$22,"Diego")+SUMIFS('S4'!$I$6:$I$22,'S4'!$B$6:$B$22,$A15,'S4'!$E$6:$E$22,"Ambos")+SUMIFS('S5'!$I$6:$I$20,'S5'!$B$6:$B$20,$A15,'S5'!$E$6:$E$20,"Diego")+SUMIFS('S5'!$I$6:$I$20,'S5'!$B$6:$B$20,$A15,'S5'!$E$6:$E$20,"Ambos")+SUMIFS('S6'!$I$6:$I$17,'S6'!$B$6:$B$17,$A15,'S6'!$E$6:$E$17,"Diego")+SUMIFS('S6'!$I$6:$I$17,'S6'!$B$6:$B$17,$A15,'S6'!$E$6:$E$17,"Ambos")+SUMIFS('S7'!$I$6:$I$19,'S7'!$B$6:$B$19,$A15,'S7'!$E$6:$E$19,"Diego")+SUMIFS('S7'!$I$6:$I$19,'S7'!$B$6:$B$19,$A15,'S7'!$E$6:$E$19,"Ambos")+SUMIFS('S8'!$I$6:$I$23,'S8'!$B$6:$B$23,$A15,'S8'!$E$6:$E$23,"Diego")+SUMIFS('S8'!$I$6:$I$23,'S8'!$B$6:$B$23,$A15,'S8'!$E$6:$E$23,"Ambos")+SUMIFS('S9'!$I$6:$I$15,'S9'!$B$6:$B$15,$A15,'S9'!$E$6:$E$15,"Diego")+SUMIFS('S9'!$I$6:$I$15,'S9'!$B$6:$B$15,$A15,'S9'!$E$6:$E$15,"Ambos")+SUMIFS('S10'!$I$6:$I$13,'S10'!$B$6:$B$13,$A15,'S10'!$E$6:$E$13,"Diego")+SUMIFS('S10'!$I$6:$I$13,'S10'!$B$6:$B$13,$A15,'S10'!$E$6:$E$13,"Ambos")+SUMIFS('Holgura'!$I$6:$I$11,'Holgura'!$B$6:$B$11,$A15,'Holgura'!$E$6:$E$11,"Diego")+SUMIFS('Holgura'!$I$6:$I$11,'Holgura'!$B$6:$B$11,$A15,'Holgura'!$E$6:$E$11,"Ambos")+SUMIFS('Entrega'!$I$6:$I$9,'Entrega'!$B$6:$B$9,$A15,'Entrega'!$E$6:$E$9,"Diego")+SUMIFS('Entrega'!$I$6:$I$9,'Entrega'!$B$6:$B$9,$A15,'Entrega'!$E$6:$E$9,"Ambos")+SUMIFS('Defensa'!$I$6:$I$10,'Defensa'!$B$6:$B$10,$A15,'Defensa'!$E$6:$E$10,"Diego")+SUMIFS('Defensa'!$I$6:$I$10,'Defensa'!$B$6:$B$10,$A15,'Defensa'!$E$6:$E$10,"Ambos") | F15: =COUNTIFS('S1'!$B$6:$B$32,$A15,'S1'!$E$6:$E$32,"Víctor")+COUNTIFS('S1'!$B$6:$B$32,$A15,'S1'!$E$6:$E$32,"Ambos")+COUNTIFS('S2'!$B$6:$B$23,$A15,'S2'!$E$6:$E$23,"Víctor")+COUNTIFS('S2'!$B$6:$B$23,$A15,'S2'!$E$6:$E$23,"Ambos")+COUNTIFS('S3'!$B$6:$B$24,$A15,'S3'!$E$6:$E$24,"Víctor")+COUNTIFS('S3'!$B$6:$B$24,$A15,'S3'!$E$6:$E$24,"Ambos")+COUNTIFS('S4'!$B$6:$B$22,$A15,'S4'!$E$6:$E$22,"Víctor")+COUNTIFS('S4'!$B$6:$B$22,$A15,'S4'!$E$6:$E$22,"Ambos")+COUNTIFS('S5'!$B$6:$B$20,$A15,'S5'!$E$6:$E$20,"Víctor")+COUNTIFS('S5'!$B$6:$B$20,$A15,'S5'!$E$6:$E$20,"Ambos")+COUNTIFS('S6'!$B$6:$B$17,$A15,'S6'!$E$6:$E$17,"Víctor")+COUNTIFS('S6'!$B$6:$B$17,$A15,'S6'!$E$6:$E$17,"Ambos")+COUNTIFS('S7'!$B$6:$B$19,$A15,'S7'!$E$6:$E$19,"Víctor")+COUNTIFS('S7'!$B$6:$B$19,$A15,'S7'!$E$6:$E$19,"Ambos")+COUNTIFS('S8'!$B$6:$B$23,$A15,'S8'!$E$6:$E$23,"Víctor")+COUNTIFS('S8'!$B$6:$B$23,$A15,'S8'!$E$6:$E$23,"Ambos")+COUNTIFS('S9'!$B$6:$B$15,$A15,'S9'!$E$6:$E$15,"Víctor")+COUNTIFS('S9'!$B$6:$B$15,$A15,'S9'!$E$6:$E$15,"Ambos")+COUNTIFS('S10'!$B$6:$B$13,$A15,'S10'!$E$6:$E$13,"Víctor")+COUNTIFS('S10'!$B$6:$B$13,$A15,'S10'!$E$6:$E$13,"Ambos")+COUNTIFS('Holgura'!$B$6:$B$11,$A15,'Holgura'!$E$6:$E$11,"Víctor")+COUNTIFS('Holgura'!$B$6:$B$11,$A15,'Holgura'!$E$6:$E$11,"Ambos")+COUNTIFS('Entrega'!$B$6:$B$9,$A15,'Entrega'!$E$6:$E$9,"Víctor")+COUNTIFS('Entrega'!$B$6:$B$9,$A15,'Entrega'!$E$6:$E$9,"Ambos")+COUNTIFS('Defensa'!$B$6:$B$10,$A15,'Defensa'!$E$6:$E$10,"Víctor")+COUNTIFS('Defensa'!$B$6:$B$10,$A15,'Defensa'!$E$6:$E$10,"Ambos") | G15: =COUNTIFS('S1'!$B$6:$B$32,$A15,'S1'!$E$6:$E$32,"Diego")+COUNTIFS('S1'!$B$6:$B$32,$A15,'S1'!$E$6:$E$32,"Ambos")+COUNTIFS('S2'!$B$6:$B$23,$A15,'S2'!$E$6:$E$23,"Diego")+COUNTIFS('S2'!$B$6:$B$23,$A15,'S2'!$E$6:$E$23,"Ambos")+COUNTIFS('S3'!$B$6:$B$24,$A15,'S3'!$E$6:$E$24,"Diego")+COUNTIFS('S3'!$B$6:$B$24,$A15,'S3'!$E$6:$E$24,"Ambos")+COUNTIFS('S4'!$B$6:$B$22,$A15,'S4'!$E$6:$E$22,"Diego")+COUNTIFS('S4'!$B$6:$B$22,$A15,'S4'!$E$6:$E$22,"Ambos")+COUNTIFS('S5'!$B$6:$B$20,$A15,'S5'!$E$6:$E$20,"Diego")+COUNTIFS('S5'!$B$6:$B$20,$A15,'S5'!$E$6:$E$20,"Ambos")+COUNTIFS('S6'!$B$6:$B$17,$A15,'S6'!$E$6:$E$17,"Diego")+COUNTIFS('S6'!$B$6:$B$17,$A15,'S6'!$E$6:$E$17,"Ambos")+COUNTIFS('S7'!$B$6:$B$19,$A15,'S7'!$E$6:$E$19,"Diego")+COUNTIFS('S7'!$B$6:$B$19,$A15,'S7'!$E$6:$E$19,"Ambos")+COUNTIFS('S8'!$B$6:$B$23,$A15,'S8'!$E$6:$E$23,"Diego")+COUNTIFS('S8'!$B$6:$B$23,$A15,'S8'!$E$6:$E$23,"Ambos")+COUNTIFS('S9'!$B$6:$B$15,$A15,'S9'!$E$6:$E$15,"Diego")+COUNTIFS('S9'!$B$6:$B$15,$A15,'S9'!$E$6:$E$15,"Ambos")+COUNTIFS('S10'!$B$6:$B$13,$A15,'S10'!$E$6:$E$13,"Diego")+COUNTIFS('S10'!$B$6:$B$13,$A15,'S10'!$E$6:$E$13,"Ambos")+COUNTIFS('Holgura'!$B$6:$B$11,$A15,'Holgura'!$E$6:$E$11,"Diego")+COUNTIFS('Holgura'!$B$6:$B$11,$A15,'Holgura'!$E$6:$E$11,"Ambos")+COUNTIFS('Entrega'!$B$6:$B$9,$A15,'Entrega'!$E$6:$E$9,"Diego")+COUNTIFS('Entrega'!$B$6:$B$9,$A15,'Entrega'!$E$6:$E$9,"Ambos")+COUNTIFS('Defensa'!$B$6:$B$10,$A15,'Defensa'!$E$6:$E$10,"Diego")+COUNTIFS('Defensa'!$B$6:$B$10,$A15,'Defensa'!$E$6:$E$10,"Ambos")
A16: 46318 | B16: =A16 | C16: =IF(WEEKDAY(A16,2)>5,4,2) | D16: =SUMIFS('S1'!$I$6:$I$32,'S1'!$B$6:$B$32,$A16,'S1'!$E$6:$E$32,"Víctor")+SUMIFS('S1'!$I$6:$I$32,'S1'!$B$6:$B$32,$A16,'S1'!$E$6:$E$32,"Ambos")+SUMIFS('S2'!$I$6:$I$23,'S2'!$B$6:$B$23,$A16,'S2'!$E$6:$E$23,"Víctor")+SUMIFS('S2'!$I$6:$I$23,'S2'!$B$6:$B$23,$A16,'S2'!$E$6:$E$23,"Ambos")+SUMIFS('S3'!$I$6:$I$24,'S3'!$B$6:$B$24,$A16,'S3'!$E$6:$E$24,"Víctor")+SUMIFS('S3'!$I$6:$I$24,'S3'!$B$6:$B$24,$A16,'S3'!$E$6:$E$24,"Ambos")+SUMIFS('S4'!$I$6:$I$22,'S4'!$B$6:$B$22,$A16,'S4'!$E$6:$E$22,"Víctor")+SUMIFS('S4'!$I$6:$I$22,'S4'!$B$6:$B$22,$A16,'S4'!$E$6:$E$22,"Ambos")+SUMIFS('S5'!$I$6:$I$20,'S5'!$B$6:$B$20,$A16,'S5'!$E$6:$E$20,"Víctor")+SUMIFS('S5'!$I$6:$I$20,'S5'!$B$6:$B$20,$A16,'S5'!$E$6:$E$20,"Ambos")+SUMIFS('S6'!$I$6:$I$17,'S6'!$B$6:$B$17,$A16,'S6'!$E$6:$E$17,"Víctor")+SUMIFS('S6'!$I$6:$I$17,'S6'!$B$6:$B$17,$A16,'S6'!$E$6:$E$17,"Ambos")+SUMIFS('S7'!$I$6:$I$19,'S7'!$B$6:$B$19,$A16,'S7'!$E$6:$E$19,"Víctor")+SUMIFS('S7'!$I$6:$I$19,'S7'!$B$6:$B$19,$A16,'S7'!$E$6:$E$19,"Ambos")+SUMIFS('S8'!$I$6:$I$23,'S8'!$B$6:$B$23,$A16,'S8'!$E$6:$E$23,"Víctor")+SUMIFS('S8'!$I$6:$I$23,'S8'!$B$6:$B$23,$A16,'S8'!$E$6:$E$23,"Ambos")+SUMIFS('S9'!$I$6:$I$15,'S9'!$B$6:$B$15,$A16,'S9'!$E$6:$E$15,"Víctor")+SUMIFS('S9'!$I$6:$I$15,'S9'!$B$6:$B$15,$A16,'S9'!$E$6:$E$15,"Ambos")+SUMIFS('S10'!$I$6:$I$13,'S10'!$B$6:$B$13,$A16,'S10'!$E$6:$E$13,"Víctor")+SUMIFS('S10'!$I$6:$I$13,'S10'!$B$6:$B$13,$A16,'S10'!$E$6:$E$13,"Ambos")+SUMIFS('Holgura'!$I$6:$I$11,'Holgura'!$B$6:$B$11,$A16,'Holgura'!$E$6:$E$11,"Víctor")+SUMIFS('Holgura'!$I$6:$I$11,'Holgura'!$B$6:$B$11,$A16,'Holgura'!$E$6:$E$11,"Ambos")+SUMIFS('Entrega'!$I$6:$I$9,'Entrega'!$B$6:$B$9,$A16,'Entrega'!$E$6:$E$9,"Víctor")+SUMIFS('Entrega'!$I$6:$I$9,'Entrega'!$B$6:$B$9,$A16,'Entrega'!$E$6:$E$9,"Ambos")+SUMIFS('Defensa'!$I$6:$I$10,'Defensa'!$B$6:$B$10,$A16,'Defensa'!$E$6:$E$10,"Víctor")+SUMIFS('Defensa'!$I$6:$I$10,'Defensa'!$B$6:$B$10,$A16,'Defensa'!$E$6:$E$10,"Ambos") | E16: =SUMIFS('S1'!$I$6:$I$32,'S1'!$B$6:$B$32,$A16,'S1'!$E$6:$E$32,"Diego")+SUMIFS('S1'!$I$6:$I$32,'S1'!$B$6:$B$32,$A16,'S1'!$E$6:$E$32,"Ambos")+SUMIFS('S2'!$I$6:$I$23,'S2'!$B$6:$B$23,$A16,'S2'!$E$6:$E$23,"Diego")+SUMIFS('S2'!$I$6:$I$23,'S2'!$B$6:$B$23,$A16,'S2'!$E$6:$E$23,"Ambos")+SUMIFS('S3'!$I$6:$I$24,'S3'!$B$6:$B$24,$A16,'S3'!$E$6:$E$24,"Diego")+SUMIFS('S3'!$I$6:$I$24,'S3'!$B$6:$B$24,$A16,'S3'!$E$6:$E$24,"Ambos")+SUMIFS('S4'!$I$6:$I$22,'S4'!$B$6:$B$22,$A16,'S4'!$E$6:$E$22,"Diego")+SUMIFS('S4'!$I$6:$I$22,'S4'!$B$6:$B$22,$A16,'S4'!$E$6:$E$22,"Ambos")+SUMIFS('S5'!$I$6:$I$20,'S5'!$B$6:$B$20,$A16,'S5'!$E$6:$E$20,"Diego")+SUMIFS('S5'!$I$6:$I$20,'S5'!$B$6:$B$20,$A16,'S5'!$E$6:$E$20,"Ambos")+SUMIFS('S6'!$I$6:$I$17,'S6'!$B$6:$B$17,$A16,'S6'!$E$6:$E$17,"Diego")+SUMIFS('S6'!$I$6:$I$17,'S6'!$B$6:$B$17,$A16,'S6'!$E$6:$E$17,"Ambos")+SUMIFS('S7'!$I$6:$I$19,'S7'!$B$6:$B$19,$A16,'S7'!$E$6:$E$19,"Diego")+SUMIFS('S7'!$I$6:$I$19,'S7'!$B$6:$B$19,$A16,'S7'!$E$6:$E$19,"Ambos")+SUMIFS('S8'!$I$6:$I$23,'S8'!$B$6:$B$23,$A16,'S8'!$E$6:$E$23,"Diego")+SUMIFS('S8'!$I$6:$I$23,'S8'!$B$6:$B$23,$A16,'S8'!$E$6:$E$23,"Ambos")+SUMIFS('S9'!$I$6:$I$15,'S9'!$B$6:$B$15,$A16,'S9'!$E$6:$E$15,"Diego")+SUMIFS('S9'!$I$6:$I$15,'S9'!$B$6:$B$15,$A16,'S9'!$E$6:$E$15,"Ambos")+SUMIFS('S10'!$I$6:$I$13,'S10'!$B$6:$B$13,$A16,'S10'!$E$6:$E$13,"Diego")+SUMIFS('S10'!$I$6:$I$13,'S10'!$B$6:$B$13,$A16,'S10'!$E$6:$E$13,"Ambos")+SUMIFS('Holgura'!$I$6:$I$11,'Holgura'!$B$6:$B$11,$A16,'Holgura'!$E$6:$E$11,"Diego")+SUMIFS('Holgura'!$I$6:$I$11,'Holgura'!$B$6:$B$11,$A16,'Holgura'!$E$6:$E$11,"Ambos")+SUMIFS('Entrega'!$I$6:$I$9,'Entrega'!$B$6:$B$9,$A16,'Entrega'!$E$6:$E$9,"Diego")+SUMIFS('Entrega'!$I$6:$I$9,'Entrega'!$B$6:$B$9,$A16,'Entrega'!$E$6:$E$9,"Ambos")+SUMIFS('Defensa'!$I$6:$I$10,'Defensa'!$B$6:$B$10,$A16,'Defensa'!$E$6:$E$10,"Diego")+SUMIFS('Defensa'!$I$6:$I$10,'Defensa'!$B$6:$B$10,$A16,'Defensa'!$E$6:$E$10,"Ambos") | F16: =COUNTIFS('S1'!$B$6:$B$32,$A16,'S1'!$E$6:$E$32,"Víctor")+COUNTIFS('S1'!$B$6:$B$32,$A16,'S1'!$E$6:$E$32,"Ambos")+COUNTIFS('S2'!$B$6:$B$23,$A16,'S2'!$E$6:$E$23,"Víctor")+COUNTIFS('S2'!$B$6:$B$23,$A16,'S2'!$E$6:$E$23,"Ambos")+COUNTIFS('S3'!$B$6:$B$24,$A16,'S3'!$E$6:$E$24,"Víctor")+COUNTIFS('S3'!$B$6:$B$24,$A16,'S3'!$E$6:$E$24,"Ambos")+COUNTIFS('S4'!$B$6:$B$22,$A16,'S4'!$E$6:$E$22,"Víctor")+COUNTIFS('S4'!$B$6:$B$22,$A16,'S4'!$E$6:$E$22,"Ambos")+COUNTIFS('S5'!$B$6:$B$20,$A16,'S5'!$E$6:$E$20,"Víctor")+COUNTIFS('S5'!$B$6:$B$20,$A16,'S5'!$E$6:$E$20,"Ambos")+COUNTIFS('S6'!$B$6:$B$17,$A16,'S6'!$E$6:$E$17,"Víctor")+COUNTIFS('S6'!$B$6:$B$17,$A16,'S6'!$E$6:$E$17,"Ambos")+COUNTIFS('S7'!$B$6:$B$19,$A16,'S7'!$E$6:$E$19,"Víctor")+COUNTIFS('S7'!$B$6:$B$19,$A16,'S7'!$E$6:$E$19,"Ambos")+COUNTIFS('S8'!$B$6:$B$23,$A16,'S8'!$E$6:$E$23,"Víctor")+COUNTIFS('S8'!$B$6:$B$23,$A16,'S8'!$E$6:$E$23,"Ambos")+COUNTIFS('S9'!$B$6:$B$15,$A16,'S9'!$E$6:$E$15,"Víctor")+COUNTIFS('S9'!$B$6:$B$15,$A16,'S9'!$E$6:$E$15,"Ambos")+COUNTIFS('S10'!$B$6:$B$13,$A16,'S10'!$E$6:$E$13,"Víctor")+COUNTIFS('S10'!$B$6:$B$13,$A16,'S10'!$E$6:$E$13,"Ambos")+COUNTIFS('Holgura'!$B$6:$B$11,$A16,'Holgura'!$E$6:$E$11,"Víctor")+COUNTIFS('Holgura'!$B$6:$B$11,$A16,'Holgura'!$E$6:$E$11,"Ambos")+COUNTIFS('Entrega'!$B$6:$B$9,$A16,'Entrega'!$E$6:$E$9,"Víctor")+COUNTIFS('Entrega'!$B$6:$B$9,$A16,'Entrega'!$E$6:$E$9,"Ambos")+COUNTIFS('Defensa'!$B$6:$B$10,$A16,'Defensa'!$E$6:$E$10,"Víctor")+COUNTIFS('Defensa'!$B$6:$B$10,$A16,'Defensa'!$E$6:$E$10,"Ambos") | G16: =COUNTIFS('S1'!$B$6:$B$32,$A16,'S1'!$E$6:$E$32,"Diego")+COUNTIFS('S1'!$B$6:$B$32,$A16,'S1'!$E$6:$E$32,"Ambos")+COUNTIFS('S2'!$B$6:$B$23,$A16,'S2'!$E$6:$E$23,"Diego")+COUNTIFS('S2'!$B$6:$B$23,$A16,'S2'!$E$6:$E$23,"Ambos")+COUNTIFS('S3'!$B$6:$B$24,$A16,'S3'!$E$6:$E$24,"Diego")+COUNTIFS('S3'!$B$6:$B$24,$A16,'S3'!$E$6:$E$24,"Ambos")+COUNTIFS('S4'!$B$6:$B$22,$A16,'S4'!$E$6:$E$22,"Diego")+COUNTIFS('S4'!$B$6:$B$22,$A16,'S4'!$E$6:$E$22,"Ambos")+COUNTIFS('S5'!$B$6:$B$20,$A16,'S5'!$E$6:$E$20,"Diego")+COUNTIFS('S5'!$B$6:$B$20,$A16,'S5'!$E$6:$E$20,"Ambos")+COUNTIFS('S6'!$B$6:$B$17,$A16,'S6'!$E$6:$E$17,"Diego")+COUNTIFS('S6'!$B$6:$B$17,$A16,'S6'!$E$6:$E$17,"Ambos")+COUNTIFS('S7'!$B$6:$B$19,$A16,'S7'!$E$6:$E$19,"Diego")+COUNTIFS('S7'!$B$6:$B$19,$A16,'S7'!$E$6:$E$19,"Ambos")+COUNTIFS('S8'!$B$6:$B$23,$A16,'S8'!$E$6:$E$23,"Diego")+COUNTIFS('S8'!$B$6:$B$23,$A16,'S8'!$E$6:$E$23,"Ambos")+COUNTIFS('S9'!$B$6:$B$15,$A16,'S9'!$E$6:$E$15,"Diego")+COUNTIFS('S9'!$B$6:$B$15,$A16,'S9'!$E$6:$E$15,"Ambos")+COUNTIFS('S10'!$B$6:$B$13,$A16,'S10'!$E$6:$E$13,"Diego")+COUNTIFS('S10'!$B$6:$B$13,$A16,'S10'!$E$6:$E$13,"Ambos")+COUNTIFS('Holgura'!$B$6:$B$11,$A16,'Holgura'!$E$6:$E$11,"Diego")+COUNTIFS('Holgura'!$B$6:$B$11,$A16,'Holgura'!$E$6:$E$11,"Ambos")+COUNTIFS('Entrega'!$B$6:$B$9,$A16,'Entrega'!$E$6:$E$9,"Diego")+COUNTIFS('Entrega'!$B$6:$B$9,$A16,'Entrega'!$E$6:$E$9,"Ambos")+COUNTIFS('Defensa'!$B$6:$B$10,$A16,'Defensa'!$E$6:$E$10,"Diego")+COUNTIFS('Defensa'!$B$6:$B$10,$A16,'Defensa'!$E$6:$E$10,"Ambos")
... A128: 46430 | B128: =A128 | C128: =IF(WEEKDAY(A128,2)>5,4,2) | D128: =SUMIFS('S1'!$I$6:$I$32,'S1'!$B$6:$B$32,$A128,'S1'!$E$6:$E$32,"Víctor")+SUMIFS('S1'!$I$6:$I$32,'S1'!$B$6:$B$32,$A128,'S1'!$E$6:$E$32,"Ambos")+SUMIFS('S2'!$I$6:$I$23,'S2'!$B$6:$B$23,$A128,'S2'!$E$6:$E$23,"Víctor")+SUMIFS('S2'!$I$6:$I$23,'S2'!$B$6:$B$23,$A128,'S2'!$E$6:$E$23,"Ambos")+SUMIFS('S3'!$I$6:$I$24,'S3'!$B$6:$B$24,$A128,'S3'!$E$6:$E$24,"Víctor")+SUMIFS('S3'!$I$6:$I$24,'S3'!$B$6:$B$24,$A128,'S3'!$E$6:$E$24,"Ambos")+SUMIFS('S4'!$I$6:$I$22,'S4'!$B$6:$B$22,$A128,'S4'!$E$6:$E$22,"Víctor")+SUMIFS('S4'!$I$6:$I$22,'S4'!$B$6:$B$22,$A128,'S4'!$E$6:$E$22,"Ambos")+SUMIFS('S5'!$I$6:$I$20,'S5'!$B$6:$B$20,$A128,'S5'!$E$6:$E$20,"Víctor")+SUMIFS('S5'!$I$6:$I$20,'S5'!$B$6:$B$20,$A128,'S5'!$E$6:$E$20,"Ambos")+SUMIFS('S6'!$I$6:$I$17,'S6'!$B$6:$B$17,$A128,'S6'!$E$6:$E$17,"Víctor")+SUMIFS('S6'!$I$6:$I$17,'S6'!$B$6:$B$17,$A128,'S6'!$E$6:$E$17,"Ambos")+SUMIFS('S7'!$I$6:$I$19,'S7'!$B$6:$B$19,$A128,'S7'!$E$6:$E$19,"Víctor")+SUMIFS('S7'!$I$6:$I$19,'S7'!$B$6:$B$19,$A128,'S7'!$E$6:$E$19,"Ambos")+SUMIFS('S8'!$I$6:$I$23,'S8'!$B$6:$B$23,$A128,'S8'!$E$6:$E$23,"Víctor")+SUMIFS('S8'!$I$6:$I$23,'S8'!$B$6:$B$23,$A128,'S8'!$E$6:$E$23,"Ambos")+SUMIFS('S9'!$I$6:$I$15,'S9'!$B$6:$B$15,$A128,'S9'!$E$6:$E$15,"Víctor")+SUMIFS('S9'!$I$6:$I$15,'S9'!$B$6:$B$15,$A128,'S9'!$E$6:$E$15,"Ambos")+SUMIFS('S10'!$I$6:$I$13,'S10'!$B$6:$B$13,$A128,'S10'!$E$6:$E$13,"Víctor")+SUMIFS('S10'!$I$6:$I$13,'S10'!$B$6:$B$13,$A128,'S10'!$E$6:$E$13,"Ambos")+SUMIFS('Holgura'!$I$6:$I$11,'Holgura'!$B$6:$B$11,$A128,'Holgura'!$E$6:$E$11,"Víctor")+SUMIFS('Holgura'!$I$6:$I$11,'Holgura'!$B$6:$B$11,$A128,'Holgura'!$E$6:$E$11,"Ambos")+SUMIFS('Entrega'!$I$6:$I$9,'Entrega'!$B$6:$B$9,$A128,'Entrega'!$E$6:$E$9,"Víctor")+SUMIFS('Entrega'!$I$6:$I$9,'Entrega'!$B$6:$B$9,$A128,'Entrega'!$E$6:$E$9,"Ambos")+SUMIFS('Defensa'!$I$6:$I$10,'Defensa'!$B$6:$B$10,$A128,'Defensa'!$E$6:$E$10,"Víctor")+SUMIFS('Defensa'!$I$6:$I$10,'Defensa'!$B$6:$B$10,$A128,'Defensa'!$E$6:$E$10,"Ambos") | E128: =SUMIFS('S1'!$I$6:$I$32,'S1'!$B$6:$B$32,$A128,'S1'!$E$6:$E$32,"Diego")+SUMIFS('S1'!$I$6:$I$32,'S1'!$B$6:$B$32,$A128,'S1'!$E$6:$E$32,"Ambos")+SUMIFS('S2'!$I$6:$I$23,'S2'!$B$6:$B$23,$A128,'S2'!$E$6:$E$23,"Diego")+SUMIFS('S2'!$I$6:$I$23,'S2'!$B$6:$B$23,$A128,'S2'!$E$6:$E$23,"Ambos")+SUMIFS('S3'!$I$6:$I$24,'S3'!$B$6:$B$24,$A128,'S3'!$E$6:$E$24,"Diego")+SUMIFS('S3'!$I$6:$I$24,'S3'!$B$6:$B$24,$A128,'S3'!$E$6:$E$24,"Ambos")+SUMIFS('S4'!$I$6:$I$22,'S4'!$B$6:$B$22,$A128,'S4'!$E$6:$E$22,"Diego")+SUMIFS('S4'!$I$6:$I$22,'S4'!$B$6:$B$22,$A128,'S4'!$E$6:$E$22,"Ambos")+SUMIFS('S5'!$I$6:$I$20,'S5'!$B$6:$B$20,$A128,'S5'!$E$6:$E$20,"Diego")+SUMIFS('S5'!$I$6:$I$20,'S5'!$B$6:$B$20,$A128,'S5'!$E$6:$E$20,"Ambos")+SUMIFS('S6'!$I$6:$I$17,'S6'!$B$6:$B$17,$A128,'S6'!$E$6:$E$17,"Diego")+SUMIFS('S6'!$I$6:$I$17,'S6'!$B$6:$B$17,$A128,'S6'!$E$6:$E$17,"Ambos")+SUMIFS('S7'!$I$6:$I$19,'S7'!$B$6:$B$19,$A128,'S7'!$E$6:$E$19,"Diego")+SUMIFS('S7'!$I$6:$I$19,'S7'!$B$6:$B$19,$A128,'S7'!$E$6:$E$19,"Ambos")+SUMIFS('S8'!$I$6:$I$23,'S8'!$B$6:$B$23,$A128,'S8'!$E$6:$E$23,"Diego")+SUMIFS('S8'!$I$6:$I$23,'S8'!$B$6:$B$23,$A128,'S8'!$E$6:$E$23,"Ambos")+SUMIFS('S9'!$I$6:$I$15,'S9'!$B$6:$B$15,$A128,'S9'!$E$6:$E$15,"Diego")+SUMIFS('S9'!$I$6:$I$15,'S9'!$B$6:$B$15,$A128,'S9'!$E$6:$E$15,"Ambos")+SUMIFS('S10'!$I$6:$I$13,'S10'!$B$6:$B$13,$A128,'S10'!$E$6:$E$13,"Diego")+SUMIFS('S10'!$I$6:$I$13,'S10'!$B$6:$B$13,$A128,'S10'!$E$6:$E$13,"Ambos")+SUMIFS('Holgura'!$I$6:$I$11,'Holgura'!$B$6:$B$11,$A128,'Holgura'!$E$6:$E$11,"Diego")+SUMIFS('Holgura'!$I$6:$I$11,'Holgura'!$B$6:$B$11,$A128,'Holgura'!$E$6:$E$11,"Ambos")+SUMIFS('Entrega'!$I$6:$I$9,'Entrega'!$B$6:$B$9,$A128,'Entrega'!$E$6:$E$9,"Diego")+SUMIFS('Entrega'!$I$6:$I$9,'Entrega'!$B$6:$B$9,$A128,'Entrega'!$E$6:$E$9,"Ambos")+SUMIFS('Defensa'!$I$6:$I$10,'Defensa'!$B$6:$B$10,$A128,'Defensa'!$E$6:$E$10,"Diego")+SUMIFS('Defensa'!$I$6:$I$10,'Defensa'!$B$6:$B$10,$A128,'Defensa'!$E$6:$E$10,"Ambos") | F128: =COUNTIFS('S1'!$B$6:$B$32,$A128,'S1'!$E$6:$E$32,"Víctor")+COUNTIFS('S1'!$B$6:$B$32,$A128,'S1'!$E$6:$E$32,"Ambos")+COUNTIFS('S2'!$B$6:$B$23,$A128,'S2'!$E$6:$E$23,"Víctor")+COUNTIFS('S2'!$B$6:$B$23,$A128,'S2'!$E$6:$E$23,"Ambos")+COUNTIFS('S3'!$B$6:$B$24,$A128,'S3'!$E$6:$E$24,"Víctor")+COUNTIFS('S3'!$B$6:$B$24,$A128,'S3'!$E$6:$E$24,"Ambos")+COUNTIFS('S4'!$B$6:$B$22,$A128,'S4'!$E$6:$E$22,"Víctor")+COUNTIFS('S4'!$B$6:$B$22,$A128,'S4'!$E$6:$E$22,"Ambos")+COUNTIFS('S5'!$B$6:$B$20,$A128,'S5'!$E$6:$E$20,"Víctor")+COUNTIFS('S5'!$B$6:$B$20,$A128,'S5'!$E$6:$E$20,"Ambos")+COUNTIFS('S6'!$B$6:$B$17,$A128,'S6'!$E$6:$E$17,"Víctor")+COUNTIFS('S6'!$B$6:$B$17,$A128,'S6'!$E$6:$E$17,"Ambos")+COUNTIFS('S7'!$B$6:$B$19,$A128,'S7'!$E$6:$E$19,"Víctor")+COUNTIFS('S7'!$B$6:$B$19,$A128,'S7'!$E$6:$E$19,"Ambos")+COUNTIFS('S8'!$B$6:$B$23,$A128,'S8'!$E$6:$E$23,"Víctor")+COUNTIFS('S8'!$B$6:$B$23,$A128,'S8'!$E$6:$E$23,"Ambos")+COUNTIFS('S9'!$B$6:$B$15,$A128,'S9'!$E$6:$E$15,"Víctor")+COUNTIFS('S9'!$B$6:$B$15,$A128,'S9'!$E$6:$E$15,"Ambos")+COUNTIFS('S10'!$B$6:$B$13,$A128,'S10'!$E$6:$E$13,"Víctor")+COUNTIFS('S10'!$B$6:$B$13,$A128,'S10'!$E$6:$E$13,"Ambos")+COUNTIFS('Holgura'!$B$6:$B$11,$A128,'Holgura'!$E$6:$E$11,"Víctor")+COUNTIFS('Holgura'!$B$6:$B$11,$A128,'Holgura'!$E$6:$E$11,"Ambos")+COUNTIFS('Entrega'!$B$6:$B$9,$A128,'Entrega'!$E$6:$E$9,"Víctor")+COUNTIFS('Entrega'!$B$6:$B$9,$A128,'Entrega'!$E$6:$E$9,"Ambos")+COUNTIFS('Defensa'!$B$6:$B$10,$A128,'Defensa'!$E$6:$E$10,"Víctor")+COUNTIFS('Defensa'!$B$6:$B$10,$A128,'Defensa'!$E$6:$E$10,"Ambos") | G128: =COUNTIFS('S1'!$B$6:$B$32,$A128,'S1'!$E$6:$E$32,"Diego")+COUNTIFS('S1'!$B$6:$B$32,$A128,'S1'!$E$6:$E$32,"Ambos")+COUNTIFS('S2'!$B$6:$B$23,$A128,'S2'!$E$6:$E$23,"Diego")+COUNTIFS('S2'!$B$6:$B$23,$A128,'S2'!$E$6:$E$23,"Ambos")+COUNTIFS('S3'!$B$6:$B$24,$A128,'S3'!$E$6:$E$24,"Diego")+COUNTIFS('S3'!$B$6:$B$24,$A128,'S3'!$E$6:$E$24,"Ambos")+COUNTIFS('S4'!$B$6:$B$22,$A128,'S4'!$E$6:$E$22,"Diego")+COUNTIFS('S4'!$B$6:$B$22,$A128,'S4'!$E$6:$E$22,"Ambos")+COUNTIFS('S5'!$B$6:$B$20,$A128,'S5'!$E$6:$E$20,"Diego")+COUNTIFS('S5'!$B$6:$B$20,$A128,'S5'!$E$6:$E$20,"Ambos")+COUNTIFS('S6'!$B$6:$B$17,$A128,'S6'!$E$6:$E$17,"Diego")+COUNTIFS('S6'!$B$6:$B$17,$A128,'S6'!$E$6:$E$17,"Ambos")+COUNTIFS('S7'!$B$6:$B$19,$A128,'S7'!$E$6:$E$19,"Diego")+COUNTIFS('S7'!$B$6:$B$19,$A128,'S7'!$E$6:$E$19,"Ambos")+COUNTIFS('S8'!$B$6:$B$23,$A128,'S8'!$E$6:$E$23,"Diego")+COUNTIFS('S8'!$B$6:$B$23,$A128,'S8'!$E$6:$E$23,"Ambos")+COUNTIFS('S9'!$B$6:$B$15,$A128,'S9'!$E$6:$E$15,"Diego")+COUNTIFS('S9'!$B$6:$B$15,$A128,'S9'!$E$6:$E$15,"Ambos")+COUNTIFS('S10'!$B$6:$B$13,$A128,'S10'!$E$6:$E$13,"Diego")+COUNTIFS('S10'!$B$6:$B$13,$A128,'S10'!$E$6:$E$13,"Ambos")+COUNTIFS('Holgura'!$B$6:$B$11,$A128,'Holgura'!$E$6:$E$11,"Diego")+COUNTIFS('Holgura'!$B$6:$B$11,$A128,'Holgura'!$E$6:$E$11,"Ambos")+COUNTIFS('Entrega'!$B$6:$B$9,$A128,'Entrega'!$E$6:$E$9,"Diego")+COUNTIFS('Entrega'!$B$6:$B$9,$A128,'Entrega'!$E$6:$E$9,"Ambos")+COUNTIFS('Defensa'!$B$6:$B$10,$A128,'Defensa'!$E$6:$E$10,"Diego")+COUNTIFS('Defensa'!$B$6:$B$10,$A128,'Defensa'!$E$6:$E$10,"Ambos")

Sheet S2
A1: Sprint 2 · 19–25 oct · Redactar capítulos
A2: Objetivo: Primeros borradores de los capítulos 1–3; Diego analiza los datos y dibuja el proceso actual
A3: Avance del sprint: | C3: =IFERROR(COUNTIF(K6:K23,"Hecho")/(COUNTA(D6:D23)-COUNTIF(K6:K23,"Cancelado")),0) | D3: ="Víctor: "&TEXT(IFERROR((COUNTIFS(E6:E23,"Víctor",K6:K23,"Hecho")+COUNTIFS(E6:E23,"Ambos",K6:K23,"Hecho"))/(COUNTIF(E6:E23,"Víctor")+COUNTIF(E6:E23,"Ambos")),0),"0%")&" · Diego: "&TEXT(IFERROR((COUNTIFS(E6:E23,"Diego",K6:K23,"Hecho")+COUNTIFS(E6:E23,"Ambos",K6:K23,"Hecho"))/(COUNTIF(E6:E23,"Diego")+COUNTIF(E6:E23,"Ambos")),0),"0%")&" · Horas: "&TEXT(SUM(I6:I23),"0.0")
A5: ID | B5: Día planificado | C5: Día | D5: Tarea (verbo + qué + para qué) | E5: Responsable | F5: Dónde se hace | G5: Resultado esperado | H5: Cómo sé que terminé | I5: Horas estimadas | J5: Fecha real | K5: Estado | L5: Días de retraso | M5: Entregable (issue) | N5: Notas
A6: S2-T01 | B6: 46314 | C6: =B6 | D6: Escribir el capítulo 1, parte 1 (problema y evidencias), para tener el primer borrador | E6: Víctor | F6: 06_Capitulos/ | G6: Cap1 v0.1 (primera mitad) | H6: Cada cifra enlazada a su ficha verificada | I6: 2 | J6: 46315 | K6: Hecho | L6: =IF(K6="Cancelado","",IF(J6<>"",J6-B6,IF(AND(K6<>"Hecho",TODAY()>B6),TODAY()-B6,0))) | M6: S2-01 (#13) | N6: Bloque doble con: bajar a mano los PDF de la matriz (Oldroyd, Pollitt, Galan, Nyqvist, Lewis y Sauro, Auernhammer) → Claude los verifica · 19-oct: Cap. I parte 1 v0.1 hecha por Claude (control de cambios); Víctor revisa. PDF a mano: esta noche · 20-oct: Víctor aprobó la v0.1; v0.2 en 06_Capitulos/2026-10-20_Cap1_Introduccion_p1_v0.2.docx
A7: S2-T02 | B7: 46314 | C7: =B7 | D7: Analizar los datos de campo (tablas y gráficos simples), para calcular la línea base | E7: Diego | F7: 05_Datos_Campo/LineaBase_2026-10/ | G7: 05_Datos_Campo/LineaBase_2026-10/analisis/ (tablas y script) | H7: Tablas de M1–M4 y M6 | I7: 2 | K7: Movido | L7: =IF(K7="Cancelado","",IF(J7<>"",J7-B7,IF(AND(K7<>"Hecho",TODAY()>B7),TODAY()-B7,0))) | M7: S2-04 (#16) | N7: Depende del campo. Mientras tanto Diego sigue con lo movido del S1 (IA_DIEGO.md) · 27-oct: bloqueada, no hay datos de campo; copia en S4-T17 (reprogramada 27-oct)
A8: S2-T03 | B8: 46315 | C8: =B8 | D8: Escribir el capítulo 1, parte 2 (justificación y objetivos) | E8: Víctor | F8: 06_Capitulos/ | G8: 06_Capitulos/2026-10-20_Cap1_Problema_v0.1.docx | H8: Capítulo completo, revisado una vez | I8: 2 | J8: 46315 | K8: Hecho | L8: =IF(K8="Cancelado","",IF(J8<>"",J8-B8,IF(AND(K8<>"Hecho",TODAY()>B8),TODAY()-B8,0))) | M8: S2-01 (#13) | N8: Bloque doble con: fuentes de CRM A21–A27 (Claude busca y verifica, Víctor revisa) · Adelantada al 19-oct: Cap. I parte 2 v0.1 (justificación, objetivos, metas, alcance); Víctor revisa · 20-oct: Víctor aprobó la v0.1; v0.2 con vacíos A28/A29 documentados (2026-10-20_Cap1_Introduccion_p2_v0.2.docx)
A9: S2-T04 | B9: 46315 | C9: =B9 | D9: Terminar el análisis de datos y escribir lo que muestran, en lenguaje simple | E9: Diego | F9: 05_Datos_Campo/LineaBase_2026-10/ | G9: 05_Datos_Campo/LineaBase_2026-10/analisis/2026-10-20_Resultados_LineaBase_v0.1.md | H9: Víctor entiende cada número | I9: 2 | K9: Movido | L9: =IF(K9="Cancelado","",IF(J9<>"",J9-B9,IF(AND(K9<>"Hecho",TODAY()>B9),TODAY()-B9,0))) | M9: S2-04 (#16) | N9: Depende del campo · 27-oct: bloqueada, no hay datos de campo; copia en S4-T17 (reprogramada 27-oct)
A10: S2-T05 | B10: 46316 | C10: =B10 | D10: Escribir el capítulo 2, parte 1 (CRM, tiempo de respuesta, gestión del conocimiento) | E10: Víctor | F10: 06_Capitulos/ | G10: Cap2 v0.1 (primera mitad) | H10: Solo fuentes verificadas | I10: 2 | J10: 46315 | K10: Hecho | L10: =IF(K10="Cancelado","",IF(J10<>"",J10-B10,IF(AND(K10<>"Hecho",TODAY()>B10),TODAY()-B10,0))) | M10: S2-02 (#14) | N10: Bloque doble con: censo y métodos A40–A41 (biblioteca UPS: Hernández-Sampieri y Mendoza, 2018) · Adelantada al 19-oct: Cap. II v0.1 con lo verificado (7 fuentes nuevas). Falta CRM móvil (A21–A25) y clásicos de KM · 20-oct: Víctor aprobó la v0.1; v0.2 con TEAMSLASH como antecedente propio (DEC-17)
A11: S2-T06 | B11: 46316 | C11: =B11 | D11: Dibujar el proceso actual (AS-IS) en BPMN con lo dicho en las entrevistas | E11: Diego | F11: 07_Flujos_Diseno/ | G11: AS-IS v0.1 (borrador) | H11: Cada paso tiene quién lo hace | I11: 2 | J11: 46320 | K11: Hecho | L11: =IF(K11="Cancelado","",IF(J11<>"",J11-B11,IF(AND(K11<>"Hecho",TODAY()>B11),TODAY()-B11,0))) | M11: S2-05 (#17) | N11: Empezar el borrador con los documentos que hay (informe final del 22-jul y diagnóstico) y completarlo con las entrevistas cuando haya campo · 25-oct: AS-IS v0.1 (.bpmn, .png y .md) con el Informe Final del 22-jul; borrador sin validar en campo
A12: S2-T07 | B12: 46317 | C12: =B12 | D12: Escribir el capítulo 2, parte 2 (IA, RAG, normativa) | E12: Víctor | F12: 06_Capitulos/ | G12: 06_Capitulos/2026-10-22_Cap2_Marco_Teorico_v0.1.docx | H12: Capítulo completo | I12: 2 | J12: 46315 | K12: Hecho | L12: =IF(K12="Cancelado","",IF(J12<>"",J12-B12,IF(AND(K12<>"Hecho",TODAY()>B12),TODAY()-B12,0))) | M12: S2-02 (#14) | N12: Bloque doble con: A44 (Ley de Comercio Electrónico) y A30 (blockchain) · Adelantada al 19-oct: va en el mismo Cap. II v0.1 (RAG, normativa). Faltan Lewis 2020, Kleppmann, SHA-256, A44 · 20-oct: v0.2 con norma SHA-256 (NIST 2015) y vacíos reformulados (2026-10-20_Cap2_Marco_Teorico_v0.2.docx)
A13: S2-T08 | B13: 46317 | C13: =B13 | D13: Terminar el proceso actual (AS-IS) y marcar dónde se pierde tiempo | E13: Diego | F13: 07_Flujos_Diseno/ | G13: 07_Flujos_Diseno/2026-10-22_AS-IS_v0.1 | H13: Validado contra las entrevistas | I13: 2 | J13: 46320 | K13: Hecho | L13: =IF(K13="Cancelado","",IF(J13<>"",J13-B13,IF(AND(K13<>"Hecho",TODAY()>B13),TODAY()-B13,0))) | M13: S2-05 (#17) | N13: 25-oct: 5 puntos donde se pierde tiempo marcados; la validación con entrevistas queda para el campo
A14: S2-T09 | B14: 46318 | C14: =B14 | D14: Buscar fuentes de adopción de IA y automatización comercial 2023–2026, para el marco teórico | E14: Víctor | F14: 02_Fuentes/Tecnologia_IA/ | G14: ≥5 fichas | H14: Cada ficha con estado | I14: 1 | J14: 46314 | K14: Hecho | L14: =IF(K14="Cancelado","",IF(J14<>"",J14-B14,IF(AND(K14<>"Hecho",TODAY()>B14),TODAY()-B14,0))) | M14: S2-02 (#14) | N14: 19-oct: 4 fichas nuevas de IA (rodriguez_2025, chatterjee_2023a, bohm_2026, hernandezvega_2026) + 10 de CTX-IA ya verificadas
A15: S2-T10 | B15: 46318 | C15: =B15 | D15: Armar el lienzo del modelo de negocio y la propuesta de valor (primer borrador) | E15: Víctor | F15: 06_Capitulos/Modelo_Negocio/ | G15: 06_Capitulos/Modelo_Negocio/2026-10-23_Lienzo_Modelo_Negocio_v0.1.docx | H15: 9 bloques completos | I15: 1 | J15: 46315 | K15: Hecho | L15: =IF(K15="Cancelado","",IF(J15<>"",J15-B15,IF(AND(K15<>"Hecho",TODAY()>B15),TODAY()-B15,0))) | M15: S2-07 (#58) | N15: Adelantada al 19-oct: lienzo v0.1 (propuesta de valor para Torvesa + TEAMSLASH como anexo, D7); Víctor revisa · 20-oct: lienzo v0.2 con DEC-16 (bóveda en Estándar, IA solo en Premium)
A16: S2-T11 | B16: 46318 | C16: =B16 | D16: Hacer el inventario de herramientas candidatas, con criterios de comparación | E16: Diego | F16: 07_Flujos_Diseno/ | G16: Inventario v0.1 (borrador) | H16: ≥3 opciones por componente | I16: 2 | J16: 46320 | K16: Hecho | L16: =IF(K16="Cancelado","",IF(J16<>"",J16-B16,IF(AND(K16<>"Hecho",TODAY()>B16),TODAY()-B16,0))) | M16: S2-06 (#18) | N16: 25-oct: 07_Flujos_Diseno/2026-10-25_Inventario_Herramientas_v0.1.xlsx (13 herramientas, criterios C1–C8)
A17: S2-T12 | B17: 46319 | C17: =B17 | D17: Escribir el capítulo 3, parte 1 (enfoque, DSR y población) | E17: Víctor | F17: 06_Capitulos/ | G17: Cap3 v0.1 (primera mitad) | H17: Coherente con D1 y D2 | I17: 3 | J17: 46315 | K17: Hecho | L17: =IF(K17="Cancelado","",IF(J17<>"",J17-B17,IF(AND(K17<>"Hecho",TODAY()>B17),TODAY()-B17,0))) | M17: S2-03 (#15) | N17: Adelantada al 19-oct: Cap. III completo v0.1 (partes 1 y 2); Víctor revisa · 20-oct: Víctor aprobó la v0.1; v0.2 (2026-10-20_Cap3_Metodologia_v0.2.docx)
A18: S2-T13 | B18: 46319 | C18: =B18 | D18: Escribir un resumen de 1 página para Diego del capítulo 1 | E18: Víctor | F18: 06_Capitulos/ | G18: 06_Capitulos/2026-10-24_Resumen_Cap1.md | H18: Diego lo leyó | I18: 0.5 | K18: En curso | L18: =IF(K18="Cancelado","",IF(J18<>"",J18-B18,IF(AND(K18<>"Hecho",TODAY()>B18),TODAY()-B18,0))) | M18: S2-01 (#13) | N18: Adelantada al 19-oct: 06_Capitulos/2026-10-19_Resumen_Cap1.md; Víctor lo revisa y lo envía
A19: S2-T14 | B19: 46319 | C19: =B19 | D19: Terminar el inventario de herramientas con precios y criterios | E19: Diego | F19: 07_Flujos_Diseno/ | G19: 07_Flujos_Diseno/2026-10-24_Inventario_Herramientas_v0.1.xlsx | H19: Cada precio con fuente | I19: 2.5 | J19: 46320 | K19: Hecho | L19: =IF(K19="Cancelado","",IF(J19<>"",J19-B19,IF(AND(K19<>"Hecho",TODAY()>B19),TODAY()-B19,0))) | M19: S2-06 (#18) | N19: 25-oct: inventario v0.2 con pesos y puntuación
A20: S2-T15 | B20: 46319 | C20: =B20 | D20: Escribir un resumen de 1 página para Víctor del proceso actual | E20: Diego | F20: 07_Flujos_Diseno/ | G20: 07_Flujos_Diseno/2026-10-24_Resumen_AS-IS.md | H20: Víctor lo leyó | I20: 0.5 | K20: Movido | L20: =IF(K20="Cancelado","",IF(J20<>"",J20-B20,IF(AND(K20<>"Hecho",TODAY()>B20),TODAY()-B20,0))) | M20: S2-05 (#17) | N20: 27-oct: la descripción está en 2026-10-25_AS-IS_v0.1.md, pero falta el resumen de 1 página; copia en S3-T19 (reprogramada 27-oct)
A21: S2-T16 | B21: 46320 | C21: =B21 | D21: Escribir el capítulo 3, parte 2 (instrumentos, análisis y ética) | E21: Víctor | F21: 06_Capitulos/ | G21: 06_Capitulos/2026-10-25_Cap3_Metodologia_v0.1.docx | H21: Capítulo completo | I21: 2 | J21: 46315 | K21: Hecho | L21: =IF(K21="Cancelado","",IF(J21<>"",J21-B21,IF(AND(K21<>"Hecho",TODAY()>B21),TODAY()-B21,0))) | M21: S2-03 (#15) | N21: Adelantada al 19-oct: va en el mismo Cap. III v0.1; Víctor revisa · 20-oct: va en el mismo Cap. III v0.2
A22: S2-T17 | B22: 46320 | C22: =B22 | D22: Preparar las gráficas de datos para la Revisión 1 | E22: Diego | F22: 05_Datos_Campo/LineaBase_2026-10/ | G22: 05_Datos_Campo/LineaBase_2026-10/analisis/figuras/ | H22: Gráficas legibles con título | I22: 2 | K22: Movido | L22: =IF(K22="Cancelado","",IF(J22<>"",J22-B22,IF(AND(K22<>"Hecho",TODAY()>B22),TODAY()-B22,0))) | M22: S2-04 (#16) | N22: 27-oct: bloqueada, sin datos; en la Revisión 1 se muestra el AS-IS; copia en S4-T17 (reprogramada 27-oct)
A23: S2-T18 | B23: 46320 | C23: =B23 | D23: Revisar el sprint (qué hicimos, qué no, qué aprendimos), hacer 20 min de «explícame lo tuyo» y planificar el siguiente | E23: Ambos | F23: Llamada Víctor–Diego · 11_Planificacion/Bitacora_Semanal.md y 11_Planificacion/Cronograma_Tesis.xlsx | G23: Sección de la semana en la bitácora + hoja del sprint siguiente ajustada | H23: El informe del domingo (21:00) sale con la sección nueva | I23: 1 | K23: Movido | L23: =IF(K23="Cancelado","",IF(J23<>"",J23-B23,IF(AND(K23<>"Hecho",TODAY()>B23),TODAY()-B23,0))) | M23: S2-08 (#59) | N23: 27-oct: revisión escrita en la bitácora; la llamada con Diego se hace junto con el ensayo (S3-T03, reprogramada 27-oct)

Sheet S3
A1: Sprint 3 · 26 oct–1 nov · Revisión 1 con la tutora
A2: Objetivo: Mostrar avance, corregir, y preparar el diseño
A3: Avance del sprint: | C3: =IFERROR(COUNTIF(K6:K24,"Hecho")/(COUNTA(D6:D24)-COUNTIF(K6:K24,"Cancelado")),0) | D3: ="Víctor: "&TEXT(IFERROR((COUNTIFS(E6:E24,"Víctor",K6:K24,"Hecho")+COUNTIFS(E6:E24,"Ambos",K6:K24,"Hecho"))/(COUNTIF(E6:E24,"Víctor")+COUNTIF(E6:E24,"Ambos")),0),"0%")&" · Diego: "&TEXT(IFERROR((COUNTIFS(E6:E24,"Diego",K6:K24,"Hecho")+COUNTIFS(E6:E24,"Ambos",K6:K24,"Hecho"))/(COUNTIF(E6:E24,"Diego")+COUNTIF(E6:E24,"Ambos")),0),"0%")&" · Horas: "&TEXT(SUM(I6:I24),"0.0")
A5: ID | B5: Día planificado | C5: Día | D5: Tarea (verbo + qué + para qué) | E5: Responsable | F5: Dónde se hace | G5: Resultado esperado | H5: Cómo sé que terminé | I5: Horas estimadas | J5: Fecha real | K5: Estado | L5: Días de retraso | M5: Entregable (issue) | N5: Notas
A6: S3-T01 | B6: 46321 | C6: =B6 | D6: Preparar la presentación de avance (capítulos 1–3 y fuentes), para la Revisión 1 | E6: Víctor | F6: 08_Reuniones_Tutora/ | G6: 08_Reuniones_Tutora/2026-10-27_Presentacion_Revision1.pptx | H6: Máx. 12 diapositivas | I6: 2 | K6: Pendiente | L6: =IF(K6="Cancelado","",IF(J6<>"",J6-B6,IF(AND(K6<>"Hecho",TODAY()>B6),TODAY()-B6,0))) | M6: S3-01 (#19)
A7: S3-T02 | B7: 46321 | C7: =B7 | D7: Exportar el proceso actual y las gráficas para la presentación | E7: Diego | F7: 07_Flujos_Diseno/ | G7: Imágenes en la presentación | H7: Se leen bien proyectadas | I7: 2 | K7: En curso | L7: =IF(K7="Cancelado","",IF(J7<>"",J7-B7,IF(AND(K7<>"Hecho",TODAY()>B7),TODAY()-B7,0))) | M7: S3-03 (#21) | N7: 27-oct: la figura ya existe (07_Flujos_Diseno/2026-10-25_AS-IS_v0.1.png); no hay gráficas de datos porque no hay campo
A8: S3-T03 | B8: 46322 | C8: =B8 | D8: Ensayar la presentación de la Revisión 1 | E8: Ambos | F8: Llamada Víctor–Diego | G8: Ensayo cronometrado | H8: Dura ≤15 min | I8: 1 | K8: Pendiente | L8: =IF(K8="Cancelado","",IF(J8<>"",J8-B8,IF(AND(K8<>"Hecho",TODAY()>B8),TODAY()-B8,0))) | M8: S3-01 (#19) | N8: 27-oct en la noche; incluye la revisión del sprint 2 que quedó pendiente (S2-T18)
A9: S3-T04 | B9: 46322 | C9: =B9 | D9: Escribir cómo estructuré mi bóveda 1 (patrones, no datos), parte 1 | E9: Víctor | F9: 07_Flujos_Diseno/ | G9: Patrones v0.1 (primera mitad) | H9: Sin datos de CRISFE | I9: 1 | K9: Pendiente | L9: =IF(K9="Cancelado","",IF(J9<>"",J9-B9,IF(AND(K9<>"Hecho",TODAY()>B9),TODAY()-B9,0))) | M9: S3-04 (#60)
A10: S3-T05 | B10: 46323 | C10: =B10 | D10: Asistir a la Revisión 1 con la tutora (fecha a confirmar) | E10: Ambos | F10: UPS Quito, en persona | G10: Observaciones anotadas | H10: Reunión realizada | I10: 1.5 | K10: Pendiente | L10: =IF(K10="Cancelado","",IF(J10<>"",J10-B10,IF(AND(K10<>"Hecho",TODAY()>B10),TODAY()-B10,0))) | M10: S3-01 (#19) | N10: Confirmar fecha con la tutora
A11: S3-T06 | B11: 46323 | C11: =B11 | D11: Escribir el acta de la Revisión 1 | E11: Víctor | F11: 08_Reuniones_Tutora/ | G11: 08_Reuniones_Tutora/2026-10-28_Acta_Revision1.md | H11: Cada observación con responsable y plazo | I11: 0.5 | K11: Pendiente | L11: =IF(K11="Cancelado","",IF(J11<>"",J11-B11,IF(AND(K11<>"Hecho",TODAY()>B11),TODAY()-B11,0))) | M11: S3-02 (#20)
A12: S3-T07 | B12: 46324 | C12: =B12 | D12: Corregir los capítulos según las observaciones, parte 1 | E12: Víctor | F12: 06_Capitulos/ | G12: Capítulos v0.2 | H12: Observaciones marcadas como cerradas | I12: 2 | K12: Pendiente | L12: =IF(K12="Cancelado","",IF(J12<>"",J12-B12,IF(AND(K12<>"Hecho",TODAY()>B12),TODAY()-B12,0))) | M12: S3-02 (#20)
A13: S3-T08 | B13: 46324 | C13: =B13 | D13: Corregir el proceso actual y las gráficas según las observaciones | E13: Diego | F13: 07_Flujos_Diseno/ | G13: AS-IS v0.2 | H13: Observaciones cerradas | I13: 2 | K13: Pendiente | L13: =IF(K13="Cancelado","",IF(J13<>"",J13-B13,IF(AND(K13<>"Hecho",TODAY()>B13),TODAY()-B13,0))) | M13: S3-03 (#21)
A14: S3-T09 | B14: 46325 | C14: =B14 | D14: Escribir cómo estructuré mi bóveda 1, parte 2 | E14: Víctor | F14: 07_Flujos_Diseno/ | G14: 07_Flujos_Diseno/2026-10-30_Patrones_Boveda1_v0.1.docx | H14: Documento completo, sin datos | I14: 1.5 | K14: Pendiente | L14: =IF(K14="Cancelado","",IF(J14<>"",J14-B14,IF(AND(K14<>"Hecho",TODAY()>B14),TODAY()-B14,0))) | M14: S3-04 (#60)
A15: S3-T10 | B15: 46325 | C15: =B15 | D15: Leer el documento de patrones de la bóveda 1 y anotar preguntas | E15: Diego | F15: 07_Flujos_Diseno/ | G15: Preguntas en el issue de S3-04 | H15: Preguntas enviadas | I15: 1 | K15: Pendiente | L15: =IF(K15="Cancelado","",IF(J15<>"",J15-B15,IF(AND(K15<>"Hecho",TODAY()>B15),TODAY()-B15,0))) | M15: S3-04 (#60)
A16: S3-T11 | B16: 46326 | C16: =B16 | D16: Corregir los capítulos según las observaciones, parte 2 | E16: Víctor | F16: 06_Capitulos/ | G16: Capítulos v0.2 completos | H16: Todas las observaciones cerradas | I16: 3 | K16: Pendiente | L16: =IF(K16="Cancelado","",IF(J16<>"",J16-B16,IF(AND(K16<>"Hecho",TODAY()>B16),TODAY()-B16,0))) | M16: S3-02 (#20)
A17: S3-T12 | B17: 46326 | C17: =B17 | D17: Preparar la plantilla de los flujos TO-BE (Mermaid o Miro) | E17: Diego | F17: 07_Flujos_Diseno/ | G17: Plantilla de flujos | H17: Lista para el lunes | I17: 2 | K17: Pendiente | L17: =IF(K17="Cancelado","",IF(J17<>"",J17-B17,IF(AND(K17<>"Hecho",TODAY()>B17),TODAY()-B17,0))) | M17: S4-01 (#22)
A18: S3-T13 | B18: 46327 | C18: =B18 | D18: Sesión: Víctor explica a Diego los conceptos de negocio (embudo, tiempo de respuesta, propuesta de valor) | E18: Ambos | F18: Llamada Víctor–Diego · Conceptos_Negocio.pdf (raíz) | G18: Diego traduce cada concepto a una función del sistema | H18: Lista de funciones anotada | I18: 1 | K18: Pendiente | L18: =IF(K18="Cancelado","",IF(J18<>"",J18-B18,IF(AND(K18<>"Hecho",TODAY()>B18),TODAY()-B18,0))) | M18: S3-05 (#61)
A19: S3-T14 | B19: 46327 | C19: =B19 | D19: Revisar el sprint (qué hicimos, qué no, qué aprendimos), hacer 20 min de «explícame lo tuyo» y planificar el siguiente | E19: Ambos | F19: Llamada Víctor–Diego · 11_Planificacion/Bitacora_Semanal.md y 11_Planificacion/Cronograma_Tesis.xlsx | G19: Sección de la semana en la bitácora + hoja del sprint siguiente ajustada | H19: El informe del domingo (21:00) sale con la sección nueva | I19: 1 | K19: Pendiente | L19: =IF(K19="Cancelado","",IF(J19<>"",J19-B19,IF(AND(K19<>"Hecho",TODAY()>B19),TODAY()-B19,0))) | M19: S3-05 (#61)
A20: S3-T15 | B20: 46322 | C20: =B20 | D20: Confirmar si TEAMSLASH guarda los datos en Google Sheets o en PostgreSQL, para el documento de elicitación | E20: Diego | F20: WhatsApp a Víctor · repositorio de TEAMSLASH | G20: Respuesta con evidencia (captura o enlace) | H20: Víctor tiene la respuesta | I20: 0.25 | K20: Pendiente | L20: =IF(K20="Cancelado","",IF(J20<>"",J20-B20,IF(AND(K20<>"Hecho",TODAY()>B20),TODAY()-B20,0))) | M20: S4-04 (#25) | N20: Pendiente desde el 20-oct (reprogramada 27-oct)
A21: S3-T16 | B21: 46323 | C21: =B21 | D21: Conseguir la respuesta de Torvesa (autorización de campo, nota de respaldo y catálogo), para medir la línea base | E21: Diego | F21: Torvesa (llamada o visita al Ing. Torres) | G21: Autorización por escrito o fecha de campo comprometida | H21: Víctor tiene la respuesta y la fecha del campo | I21: 0.5 | K21: Pendiente | L21: =IF(K21="Cancelado","",IF(J21<>"",J21-B21,IF(AND(K21<>"Hecho",TODAY()>B21),TODAY()-B21,0))) | M21: S1-09 (#9) | N21: Riesgo principal. Si no hay respuesta el 30-oct: pedir carta de respaldo a la tutora (reprogramada 27-oct)
A22: S3-T17 | B22: 46325 | C22: =B22 | D22: Revisar y completar la elicitación y análisis de requerimientos v0.1, parte 1: requerimientos técnicos (no funcionales y restricciones) y TEAMSLASH | E22: Diego | F22: 07_Flujos_Diseno/2026-10-27_Elicitacion_Requerimientos_v0.1.docx (Word, control de cambios) | G22: Cambios y comentarios de Diego en el Word | H22: Cada requerimiento técnico con criterio de aceptación y fuente | I22: 1 | K22: Pendiente | L22: =IF(K22="Cancelado","",IF(J22<>"",J22-B22,IF(AND(K22<>"Hecho",TODAY()>B22),TODAY()-B22,0))) | M22: S4-04 (#25) | N22: Tarea nueva (27-oct). Claude saca la v0.2 con lo que marque Diego
A23: S3-T18 | B23: 46326 | C23: =B23 | D23: Completar la elicitación v0.1, parte 2: diagrama de casos de uso y modelo conceptual | E23: Diego | F23: 07_Flujos_Diseno/ (editable en draw.io, demo.bpmn.io o Mermaid) | G23: Casos de uso y modelo conceptual en PNG + archivo editable | H23: Cada caso de uso enlazado a un escenario ESC-xx | I23: 2 | K23: Pendiente | L23: =IF(K23="Cancelado","",IF(J23<>"",J23-B23,IF(AND(K23<>"Hecho",TODAY()>B23),TODAY()-B23,0))) | M23: S4-04 (#25) | N23: Tarea nueva (27-oct). Va al anexo E del documento de elicitación
A24: S3-T19 | B24: 46327 | C24: =B24 | D24: Escribir el resumen de 1 página del proceso actual (AS-IS) para Víctor | E24: Diego | F24: 07_Flujos_Diseno/ | G24: 07_Flujos_Diseno/2026-11-01_Resumen_AS-IS.md | H24: Víctor lo leyó | I24: 0.5 | K24: Pendiente | L24: =IF(K24="Cancelado","",IF(J24<>"",J24-B24,IF(AND(K24<>"Hecho",TODAY()>B24),TODAY()-B24,0))) | M24: S2-05 (#17) | N24: Copia de S2-T15 (reprogramada 27-oct)

Sheet S4
A1: Sprint 4 · 2–8 nov · Diseñar el sistema
A2: Objetivo: Flujos TO-BE, bóveda del sistema, requisitos, matriz de herramientas, costos
A3: Avance del sprint: | C3: =IFERROR(COUNTIF(K6:K22,"Hecho")/(COUNTA(D6:D22)-COUNTIF(K6:K22,"Cancelado")),0) | D3: ="Víctor: "&TEXT(IFERROR((COUNTIFS(E6:E22,"Víctor",K6:K22,"Hecho")+COUNTIFS(E6:E22,"Ambos",K6:K22,"Hecho"))/(COUNTIF(E6:E22,"Víctor")+COUNTIF(E6:E22,"Ambos")),0),"0%")&" · Diego: "&TEXT(IFERROR((COUNTIFS(E6:E22,"Diego",K6:K22,"Hecho")+COUNTIFS(E6:E22,"Ambos",K6:K22,"Hecho"))/(COUNTIF(E6:E22,"Diego")+COUNTIF(E6:E22,"Ambos")),0),"0%")&" · Horas: "&TEXT(SUM(I6:I22),"0.0")
A5: ID | B5: Día planificado | C5: Día | D5: Tarea (verbo + qué + para qué) | E5: Responsable | F5: Dónde se hace | G5: Resultado esperado | H5: Cómo sé que terminé | I5: Horas estimadas | J5: Fecha real | K5: Estado | L5: Días de retraso | M5: Entregable (issue) | N5: Notas
A6: S4-T01 | B6: 46328 | C6: =B6 | D6: Dibujar los procesos con el sistema (TO-BE), parte 1: recepción y asignación | E6: Diego | F6: 07_Flujos_Diseno/ | G6: TO-BE v0.1 (parte 1) | H6: Cada paso con disparador y responsable | I6: 2 | K6: Pendiente | L6: =IF(K6="Cancelado","",IF(J6<>"",J6-B6,IF(AND(K6<>"Hecho",TODAY()>B6),TODAY()-B6,0))) | M6: S4-01 (#22)
A7: S4-T02 | B7: 46328 | C7: =B7 | D7: Escribir los requisitos funcionales (qué debe hacer el sistema) | E7: Víctor | F7: 06_Capitulos/ | G7: Requisitos v0.1 (funcionales) | H7: Cada requisito con su origen | I7: 2 | K7: Pendiente | L7: =IF(K7="Cancelado","",IF(J7<>"",J7-B7,IF(AND(K7<>"Hecho",TODAY()>B7),TODAY()-B7,0))) | M7: S4-04 (#25)
A8: S4-T03 | B8: 46329 | C8: =B8 | D8: Dibujar los procesos TO-BE, parte 2: cotización asistida e historial | E8: Diego | F8: 07_Flujos_Diseno/ | G8: TO-BE v0.1 (parte 2) | H8: Cubre los pasos 3–4 | I8: 2 | K8: Pendiente | L8: =IF(K8="Cancelado","",IF(J8<>"",J8-B8,IF(AND(K8<>"Hecho",TODAY()>B8),TODAY()-B8,0))) | M8: S4-01 (#22)
A9: S4-T04 | B9: 46329 | C9: =B9 | D9: Escribir los requisitos no funcionales (seguridad, sin conexión, ley de datos) | E9: Víctor | F9: 06_Capitulos/ | G9: 06_Capitulos/2026-11-03_Requisitos_v0.1.docx | H9: Requisitos completos | I9: 2 | K9: Pendiente | L9: =IF(K9="Cancelado","",IF(J9<>"",J9-B9,IF(AND(K9<>"Hecho",TODAY()>B9),TODAY()-B9,0))) | M9: S4-04 (#25)
A10: S4-T05 | B10: 46330 | C10: =B10 | D10: Dibujar los procesos TO-BE, parte 3: recordatorios y reasignación | E10: Diego | F10: 07_Flujos_Diseno/ | G10: 07_Flujos_Diseno/2026-11-04_TO-BE_v0.1 | H10: Cubre los 6 pasos | I10: 2 | K10: Pendiente | L10: =IF(K10="Cancelado","",IF(J10<>"",J10-B10,IF(AND(K10<>"Hecho",TODAY()>B10),TODAY()-B10,0))) | M10: S4-01 (#22)
A11: S4-T06 | B11: 46330 | C11: =B11 | D11: Validar los flujos TO-BE contra los requisitos | E11: Víctor | F11: 07_Flujos_Diseno/ | G11: Comentarios en los flujos | H11: Cada requisito ligado a un flujo | I11: 1.5 | K11: Pendiente | L11: =IF(K11="Cancelado","",IF(J11<>"",J11-B11,IF(AND(K11<>"Hecho",TODAY()>B11),TODAY()-B11,0))) | M11: S4-02 (#23)
A12: S4-T07 | B12: 46331 | C12: =B12 | D12: Construir la bóveda del sistema: carpetas y plantillas | E12: Diego | F12: 07_Flujos_Diseno/ | G12: 07_Flujos_Diseno/Boveda_Sistema/ | H12: Estructura creada | I12: 2 | K12: Pendiente | L12: =IF(K12="Cancelado","",IF(J12<>"",J12-B12,IF(AND(K12<>"Hecho",TODAY()>B12),TODAY()-B12,0))) | M12: S4-03 (#24)
A13: S4-T08 | B13: 46331 | C13: =B13 | D13: Armar la matriz de decisión de herramientas en Excel (fórmulas vivas) | E13: Víctor | F13: 06_Capitulos/Modelo_Negocio/ | G13: 06_Capitulos/Modelo_Negocio/2026-11-05_Matriz_Decision_Herramientas_v0.1.xlsx | H13: Ponderaciones y sensibilidad | I13: 2 | K13: Pendiente | L13: =IF(K13="Cancelado","",IF(J13<>"",J13-B13,IF(AND(K13<>"Hecho",TODAY()>B13),TODAY()-B13,0))) | M13: S4-05 (#26)
A14: S4-T09 | B14: 46332 | C14: =B14 | D14: Construir la bóveda del sistema: fichas de ejemplo con datos ficticios | E14: Diego | F14: 07_Flujos_Diseno/ | G14: Fichas CLI-0001… | H14: Plantillas funcionando | I14: 2 | K14: Pendiente | L14: =IF(K14="Cancelado","",IF(J14<>"",J14-B14,IF(AND(K14<>"Hecho",TODAY()>B14),TODAY()-B14,0))) | M14: S4-03 (#24)
A15: S4-T10 | B15: 46332 | C15: =B15 | D15: Calcular CAPEX (inversión inicial) con fuente para cada precio | E15: Víctor | F15: 06_Capitulos/Modelo_Negocio/ | G15: Hoja Costos del modelo financiero | H15: Cada precio con enlace y fecha | I15: 2 | K15: Pendiente | L15: =IF(K15="Cancelado","",IF(J15<>"",J15-B15,IF(AND(K15<>"Hecho",TODAY()>B15),TODAY()-B15,0))) | M15: S4-06 (#27)
A16: S4-T11 | B16: 46333 | C16: =B16 | D16: Construir la bóveda del sistema: tableros y enlaces | E16: Diego | F16: 07_Flujos_Diseno/ | G16: Tableros de pendientes | H16: Se ven los pendientes por vendedor | I16: 3 | K16: Pendiente | L16: =IF(K16="Cancelado","",IF(J16<>"",J16-B16,IF(AND(K16<>"Hecho",TODAY()>B16),TODAY()-B16,0))) | M16: S4-03 (#24)
A17: S4-T12 | B17: 46333 | C17: =B17 | D17: Calcular OPEX (gasto mensual) con fuente para cada precio | E17: Víctor | F17: 06_Capitulos/Modelo_Negocio/ | G17: 06_Capitulos/Modelo_Negocio/2026-11-07_Modelo_Financiero_v0.1.xlsx | H17: Hoja Costos completa | I17: 3 | K17: Pendiente | L17: =IF(K17="Cancelado","",IF(J17<>"",J17-B17,IF(AND(K17<>"Hecho",TODAY()>B17),TODAY()-B17,0))) | M17: S4-06 (#27)
... A20: S4-T15 | B20: 46334 | C20: =B20 | D20: Revisar el sprint (qué hicimos, qué no, qué aprendimos), hacer 20 min de «explícame lo tuyo» y planificar el siguiente | E20: Ambos | F20: Llamada Víctor–Diego · 11_Planificacion/Bitacora_Semanal.md y 11_Planificacion/Cronograma_Tesis.xlsx | G20: Sección de la semana en la bitácora + hoja del sprint siguiente ajustada | H20: El informe del domingo (21:00) sale con la sección nueva | I20: 1 | K20: Pendiente | L20: =IF(K20="Cancelado","",IF(J20<>"",J20-B20,IF(AND(K20<>"Hecho",TODAY()>B20),TODAY()-B20,0))) | M20: S4-07 (#62)
A21: S4-T16 | B21: 46329 | C21: =B21 | D21: Hacer el campo en Torvesa (si autorizó): cronometrar cotizaciones (P2-A) y revisar solicitudes de los últimos 3 meses (P2-B) | E21: Diego | F21: Torvesa (oficina, Quito) | G21: 05_Datos_Campo/LineaBase_2026-10/P2A_cronometraje.csv y P2B_muestra_documental.csv | H21: Todas las cotizaciones observables registradas | I21: 4 | K21: Pendiente | L21: =IF(K21="Cancelado","",IF(J21<>"",J21-B21,IF(AND(K21<>"Hecho",TODAY()>B21),TODAY()-B21,0))) | M21: S1-09 (#9) | N21: Copia de S1-T16 y S1-T18 (reprogramada 27-oct). Solo si Torvesa autorizó. Día cargado: S4-T03 se termina el 8-nov si hace falta
A22: S4-T17 | B22: 46334 | C22: =B22 | D22: Analizar los datos de campo y preparar las gráficas de la línea base (M1–M4 y M6) | E22: Diego | F22: 05_Datos_Campo/LineaBase_2026-10/ | G22: 05_Datos_Campo/LineaBase_2026-10/analisis/ (Resultados_LineaBase_v0.1.md + figuras/) | H22: Víctor entiende cada número | I22: 2 | K22: Pendiente | L22: =IF(K22="Cancelado","",IF(J22<>"",J22-B22,IF(AND(K22<>"Hecho",TODAY()>B22),TODAY()-B22,0))) | M22: S2-04 (#16) | N22: Copia de S2-T02, S2-T04 y S2-T17 (reprogramada 27-oct). Solo si hubo campo

Sheet S5
A1: Sprint 5 · 9–15 nov · Prueba de concepto y finanzas
A2: Objetivo: Diego construye la prueba de concepto; Víctor calcula VAN, TIR y riesgos
A3: Avance del sprint: | C3: =IFERROR(COUNTIF(K6:K20,"Hecho")/(COUNTA(D6:D20)-COUNTIF(K6:K20,"Cancelado")),0) | D3: ="Víctor: "&TEXT(IFERROR((COUNTIFS(E6:E20,"Víctor",K6:K20,"Hecho")+COUNTIFS(E6:E20,"Ambos",K6:K20,"Hecho"))/(COUNTIF(E6:E20,"Víctor")+COUNTIF(E6:E20,"Ambos")),0),"0%")&" · Diego: "&TEXT(IFERROR((COUNTIFS(E6:E20,"Diego",K6:K20,"Hecho")+COUNTIFS(E6:E20,"Ambos",K6:K20,"Hecho"))/(COUNTIF(E6:E20,"Diego")+COUNTIF(E6:E20,"Ambos")),0),"0%")&" · Horas: "&TEXT(SUM(I6:I20),"0.0")
A5: ID | B5: Día planificado | C5: Día | D5: Tarea (verbo + qué + para qué) | E5: Responsable | F5: Dónde se hace | G5: Resultado esperado | H5: Cómo sé que terminé | I5: Horas estimadas | J5: Fecha real | K5: Estado | L5: Días de retraso | M5: Entregable (issue) | N5: Notas
A6: S5-T01 | B6: 46335 | C6: =B6 | D6: Estimar los beneficios con supuestos explícitos (horas ahorradas, clientes no perdidos) | E6: Víctor | F6: 06_Capitulos/Modelo_Negocio/ | G6: Hoja Beneficios | H6: Cada supuesto con fuente o dato de campo | I6: 2 | K6: Pendiente | L6: =IF(K6="Cancelado","",IF(J6<>"",J6-B6,IF(AND(K6<>"Hecho",TODAY()>B6),TODAY()-B6,0))) | M6: S5-01 (#28)
A7: S5-T02 | B7: 46335 | C7: =B7 | D7: Construir la prueba de concepto, parte 1: formulario → servidor | E7: Diego | F7: Repositorio de la prueba de concepto | G7: Formulario guarda en la base de datos | H7: Demo funcionando | I7: 2 | K7: Pendiente | L7: =IF(K7="Cancelado","",IF(J7<>"",J7-B7,IF(AND(K7<>"Hecho",TODAY()>B7),TODAY()-B7,0))) | M7: S5-04 (#31)
A8: S5-T03 | B8: 46336 | C8: =B8 | D8: Calcular VAN, TIR y período de recuperación en 3 escenarios | E8: Víctor | F8: 06_Capitulos/Modelo_Negocio/ | G8: Hoja Escenarios | H8: Pesimista, base y optimista | I8: 2 | K8: Pendiente | L8: =IF(K8="Cancelado","",IF(J8<>"",J8-B8,IF(AND(K8<>"Hecho",TODAY()>B8),TODAY()-B8,0))) | M8: S5-01 (#28)
A9: S5-T04 | B9: 46336 | C9: =B9 | D9: Construir la prueba de concepto, parte 2: servidor → bóveda | E9: Diego | F9: Repositorio de la prueba de concepto | G9: La ficha del cliente aparece en la bóveda | H9: Demo funcionando | I9: 2 | K9: Pendiente | L9: =IF(K9="Cancelado","",IF(J9<>"",J9-B9,IF(AND(K9<>"Hecho",TODAY()>B9),TODAY()-B9,0))) | M9: S5-04 (#31)
A10: S5-T05 | B10: 46337 | C10: =B10 | D10: Hacer el análisis de sensibilidad (qué pasa si cambian los supuestos) | E10: Víctor | F10: 06_Capitulos/Modelo_Negocio/ | G10: Hoja Sensibilidad | H10: Tabla y gráfico | I10: 2 | K10: Pendiente | L10: =IF(K10="Cancelado","",IF(J10<>"",J10-B10,IF(AND(K10<>"Hecho",TODAY()>B10),TODAY()-B10,0))) | M10: S5-01 (#28)
A11: S5-T06 | B11: 46337 | C11: =B11 | D11: Construir la prueba de concepto, parte 3: borrador de cotización con IA | E11: Diego | F11: Repositorio de la prueba de concepto | G11: Borrador generado desde la bóveda | H11: Demo funcionando | I11: 2 | K11: Pendiente | L11: =IF(K11="Cancelado","",IF(J11<>"",J11-B11,IF(AND(K11<>"Hecho",TODAY()>B11),TODAY()-B11,0))) | M11: S5-04 (#31)
A12: S5-T07 | B12: 46338 | C12: =B12 | D12: Escribir la matriz de riesgos | E12: Víctor | F12: 06_Capitulos/ | G12: 06_Capitulos/2026-11-12_Riesgos_v0.1.xlsx | H12: Probabilidad × impacto + mitigación | I12: 2 | K12: Pendiente | L12: =IF(K12="Cancelado","",IF(J12<>"",J12-B12,IF(AND(K12<>"Hecho",TODAY()>B12),TODAY()-B12,0))) | M12: S5-02 (#29)
A13: S5-T08 | B13: 46338 | C13: =B13 | D13: Construir la prueba de concepto, parte 4: alertas y registro de eventos | E13: Diego | F13: Repositorio de la prueba de concepto | G13: Eventos registrados | H13: Demo funcionando | I13: 2 | K13: Pendiente | L13: =IF(K13="Cancelado","",IF(J13<>"",J13-B13,IF(AND(K13<>"Hecho",TODAY()>B13),TODAY()-B13,0))) | M13: S5-04 (#31)
A14: S5-T09 | B14: 46339 | C14: =B14 | D14: Escribir el capítulo de normativa (LOPDP) | E14: Víctor | F14: 06_Capitulos/ | G14: 06_Capitulos/2026-11-13_Normativa_v0.1.docx | H14: Artículos del texto oficial | I14: 2 | K14: Pendiente | L14: =IF(K14="Cancelado","",IF(J14<>"",J14-B14,IF(AND(K14<>"Hecho",TODAY()>B14),TODAY()-B14,0))) | M14: S5-03 (#30)
A15: S5-T10 | B15: 46339 | C15: =B15 | D15: Probar la prueba de concepto completa y corregir errores | E15: Diego | F15: Repositorio de la prueba de concepto | G15: Flujo completo sin errores | H15: Demo de punta a punta | I15: 2 | K15: Pendiente | L15: =IF(K15="Cancelado","",IF(J15<>"",J15-B15,IF(AND(K15<>"Hecho",TODAY()>B15),TODAY()-B15,0))) | M15: S5-04 (#31)
A16: S5-T11 | B16: 46340 | C16: =B16 | D16: Escribir el pitch de 1 página para inversionista | E16: Víctor | F16: 06_Capitulos/Modelo_Negocio/ | G16: 06_Capitulos/Modelo_Negocio/2026-11-14_Pitch_1pagina_v0.1.docx | H16: Una página con VAN, TIR y propuesta de valor | I16: 2 | K16: Pendiente | L16: =IF(K16="Cancelado","",IF(J16<>"",J16-B16,IF(AND(K16<>"Hecho",TODAY()>B16),TODAY()-B16,0))) | M16: S5-06 (#63)
A17: S5-T12 | B17: 46340 | C17: =B17 | D17: Terminar el capítulo de normativa | E17: Víctor | F17: 06_Capitulos/ | G17: Normativa v0.1 completa | H17: Revisado una vez | I17: 1.5 | K17: Pendiente | L17: =IF(K17="Cancelado","",IF(J17<>"",J17-B17,IF(AND(K17<>"Hecho",TODAY()>B17),TODAY()-B17,0))) | M17: S5-03 (#30)
... A20: S5-T15 | B20: 46341 | C20: =B20 | D20: Revisar el sprint (qué hicimos, qué no, qué aprendimos), hacer 20 min de «explícame lo tuyo» y planificar el siguiente | E20: Ambos | F20: Llamada Víctor–Diego · 11_Planificacion/Bitacora_Semanal.md y 11_Planificacion/Cronograma_Tesis.xlsx | G20: Sección de la semana en la bitácora + hoja del sprint siguiente ajustada | H20: El informe del domingo (21:00) sale con la sección nueva | I20: 1 | K20: Pendiente | L20: =IF(K20="Cancelado","",IF(J20<>"",J20-B20,IF(AND(K20<>"Hecho",TODAY()>B20),TODAY()-B20,0))) | M20: S5-07 (#64)

Sheet S6
A1: Sprint 6 · 16–22 nov · Revisión 2 con la tutora
A2: Objetivo: Mostrar diseño, flujos, datos y viabilidad; preparar la validación
A3: Avance del sprint: | C3: =IFERROR(COUNTIF(K6:K17,"Hecho")/(COUNTA(D6:D17)-COUNTIF(K6:K17,"Cancelado")),0) | D3: ="Víctor: "&TEXT(IFERROR((COUNTIFS(E6:E17,"Víctor",K6:K17,"Hecho")+COUNTIFS(E6:E17,"Ambos",K6:K17,"Hecho"))/(COUNTIF(E6:E17,"Víctor")+COUNTIF(E6:E17,"Ambos")),0),"0%")&" · Diego: "&TEXT(IFERROR((COUNTIFS(E6:E17,"Diego",K6:K17,"Hecho")+COUNTIFS(E6:E17,"Ambos",K6:K17,"Hecho"))/(COUNTIF(E6:E17,"Diego")+COUNTIF(E6:E17,"Ambos")),0),"0%")&" · Horas: "&TEXT(SUM(I6:I17),"0.0")
A5: ID | B5: Día planificado | C5: Día | D5: Tarea (verbo + qué + para qué) | E5: Responsable | F5: Dónde se hace | G5: Resultado esperado | H5: Cómo sé que terminé | I5: Horas estimadas | J5: Fecha real | K5: Estado | L5: Días de retraso | M5: Entregable (issue) | N5: Notas
A6: S6-T01 | B6: 46342 | C6: =B6 | D6: Preparar la presentación de la Revisión 2 (diseño, flujos, datos y viabilidad) | E6: Ambos | F6: 08_Reuniones_Tutora/ | G6: 08_Reuniones_Tutora/2026-11-17_Presentacion_Revision2.pptx | H6: Máx. 15 diapositivas | I6: 2 | K6: Pendiente | L6: =IF(K6="Cancelado","",IF(J6<>"",J6-B6,IF(AND(K6<>"Hecho",TODAY()>B6),TODAY()-B6,0))) | M6: S6-01 (#33)
A7: S6-T02 | B7: 46343 | C7: =B7 | D7: Ensayar la presentación de la Revisión 2 | E7: Ambos | F7: Llamada Víctor–Diego | G7: Ensayo cronometrado | H7: Dura ≤20 min | I7: 1 | K7: Pendiente | L7: =IF(K7="Cancelado","",IF(J7<>"",J7-B7,IF(AND(K7<>"Hecho",TODAY()>B7),TODAY()-B7,0))) | M7: S6-01 (#33)
A8: S6-T03 | B8: 46343 | C8: =B8 | D8: Estabilizar la prueba de concepto para la demostración | E8: Diego | F8: Repositorio de la prueba de concepto | G8: Demo sin fallas | H8: 3 corridas seguidas sin error | I8: 1 | K8: Pendiente | L8: =IF(K8="Cancelado","",IF(J8<>"",J8-B8,IF(AND(K8<>"Hecho",TODAY()>B8),TODAY()-B8,0))) | M8: S5-04 (#31)
A9: S6-T04 | B9: 46344 | C9: =B9 | D9: Asistir a la Revisión 2 con la tutora (fecha a confirmar) | E9: Ambos | F9: UPS Quito, en persona | G9: Observaciones anotadas | H9: Reunión realizada | I9: 1.5 | K9: Pendiente | L9: =IF(K9="Cancelado","",IF(J9<>"",J9-B9,IF(AND(K9<>"Hecho",TODAY()>B9),TODAY()-B9,0))) | M9: S6-01 (#33) | N9: Confirmar fecha con la tutora
A10: S6-T05 | B10: 46344 | C10: =B10 | D10: Escribir el acta de la Revisión 2 | E10: Víctor | F10: 08_Reuniones_Tutora/ | G10: 08_Reuniones_Tutora/2026-11-18_Acta_Revision2.md | H10: Observaciones con responsable y plazo | I10: 0.5 | K10: Pendiente | L10: =IF(K10="Cancelado","",IF(J10<>"",J10-B10,IF(AND(K10<>"Hecho",TODAY()>B10),TODAY()-B10,0))) | M10: S6-02 (#34)
A11: S6-T06 | B11: 46345 | C11: =B11 | D11: Preparar el protocolo de la validación del diseño en operación experimental controlada | E11: Víctor | F11: 04_Instrumentos/ | G11: 04_Instrumentos/2026-11-19_Protocolo_Validacion_v0.1.md | H11: Fechas, participantes y mediciones definidos | I11: 2 | K11: Pendiente | L11: =IF(K11="Cancelado","",IF(J11<>"",J11-B11,IF(AND(K11<>"Hecho",TODAY()>B11),TODAY()-B11,0))) | M11: S7-02 (#36)
A12: S6-T07 | B12: 46345 | C12: =B12 | D12: Dejar estable la prueba de concepto para la validación | E12: Diego | F12: Repositorio de la prueba de concepto | G12: Versión congelada | H12: Etiqueta de versión en el repositorio | I12: 2 | K12: Pendiente | L12: =IF(K12="Cancelado","",IF(J12<>"",J12-B12,IF(AND(K12<>"Hecho",TODAY()>B12),TODAY()-B12,0))) | M12: S5-04 (#31)
A13: S6-T08 | B13: 46346 | C13: =B13 | D13: Pedir a Torvesa la autorización y las fechas de la validación | E13: Víctor | F13: Correo electrónico | G13: Autorización escrita | H13: Respuesta recibida | I13: 1 | K13: Pendiente | L13: =IF(K13="Cancelado","",IF(J13<>"",J13-B13,IF(AND(K13<>"Hecho",TODAY()>B13),TODAY()-B13,0))) | M13: S7-02 (#36)
A14: S6-T09 | B14: 46346 | C14: =B14 | D14: Probar la prueba de concepto con los 3 casos de prueba antes de la validación | E14: Diego | F14: 07_Flujos_Diseno/ | G14: Resultados preliminares | H14: Los 3 casos pasan | I14: 2 | K14: Pendiente | L14: =IF(K14="Cancelado","",IF(J14<>"",J14-B14,IF(AND(K14<>"Hecho",TODAY()>B14),TODAY()-B14,0))) | M14: S5-05 (#32)
A15: S6-T10 | B15: 46347 | C15: =B15 | D15: Incorporar las observaciones de la Revisión 2 (documento) | E15: Víctor | F15: 06_Capitulos/ | G15: Versiones nuevas | H15: Observaciones cerradas | I15: 3 | K15: Pendiente | L15: =IF(K15="Cancelado","",IF(J15<>"",J15-B15,IF(AND(K15<>"Hecho",TODAY()>B15),TODAY()-B15,0))) | M15: S7-01 (#35)
A16: S6-T11 | B16: 46347 | C16: =B16 | D16: Incorporar las observaciones de la Revisión 2 (técnicas) | E16: Diego | F16: 07_Flujos_Diseno/ | G16: Versiones nuevas | H16: Observaciones cerradas | I16: 3 | K16: Pendiente | L16: =IF(K16="Cancelado","",IF(J16<>"",J16-B16,IF(AND(K16<>"Hecho",TODAY()>B16),TODAY()-B16,0))) | M16: S7-01 (#35)
A17: S6-T12 | B17: 46348 | C17: =B17 | D17: Revisar el sprint (qué hicimos, qué no, qué aprendimos), hacer 20 min de «explícame lo tuyo» y planificar el siguiente | E17: Ambos | F17: Llamada Víctor–Diego · 11_Planificacion/Bitacora_Semanal.md y 11_Planificacion/Cronograma_Tesis.xlsx | G17: Sección de la semana en la bitácora + hoja del sprint siguiente ajustada | H17: El informe del domingo (21:00) sale con la sección nueva | I17: 1 | K17: Pendiente | L17: =IF(K17="Cancelado","",IF(J17<>"",J17-B17,IF(AND(K17<>"Hecho",TODAY()>B17),TODAY()-B17,0))) | M17: S6-03 (#65)

Sheet S7
A1: Sprint 7 · 23–29 nov · Arranca la validación
A2: Objetivo: Capacitar a Torvesa y arrancar la validación del diseño en operación experimental controlada
A3: Avance del sprint: | C3: =IFERROR(COUNTIF(K6:K19,"Hecho")/(COUNTA(D6:D19)-COUNTIF(K6:K19,"Cancelado")),0) | D3: ="Víctor: "&TEXT(IFERROR((COUNTIFS(E6:E19,"Víctor",K6:K19,"Hecho")+COUNTIFS(E6:E19,"Ambos",K6:K19,"Hecho"))/(COUNTIF(E6:E19,"Víctor")+COUNTIF(E6:E19,"Ambos")),0),"0%")&" · Diego: "&TEXT(IFERROR((COUNTIFS(E6:E19,"Diego",K6:K19,"Hecho")+COUNTIFS(E6:E19,"Ambos",K6:K19,"Hecho"))/(COUNTIF(E6:E19,"Diego")+COUNTIF(E6:E19,"Ambos")),0),"0%")&" · Horas: "&TEXT(SUM(I6:I19),"0.0")
A5: ID | B5: Día planificado | C5: Día | D5: Tarea (verbo + qué + para qué) | E5: Responsable | F5: Dónde se hace | G5: Resultado esperado | H5: Cómo sé que terminé | I5: Horas estimadas | J5: Fecha real | K5: Estado | L5: Días de retraso | M5: Entregable (issue) | N5: Notas
A6: S7-T01 | B6: 46348 | C6: =B6 | D6: Preparar el sistema para la validación (accesos, respaldo) | E6: Diego | F6: Repositorio de la prueba de concepto | G6: Accesos listos | H6: Prueba de acceso de cada usuario | I6: 1 | K6: Pendiente | L6: =IF(K6="Cancelado","",IF(J6<>"",J6-B6,IF(AND(K6<>"Hecho",TODAY()>B6),TODAY()-B6,0))) | M6: S7-03 (#37)
A7: S7-T02 | B7: 46349 | C7: =B7 | D7: Capacitar al equipo de Torvesa para la validación | E7: Ambos | F7: Torvesa (oficina, Quito) | G7: Equipo capacitado | H7: Lista de asistentes | I7: 1.5 | K7: Pendiente | L7: =IF(K7="Cancelado","",IF(J7<>"",J7-B7,IF(AND(K7<>"Hecho",TODAY()>B7),TODAY()-B7,0))) | M7: S7-02 (#36)
A8: S7-T03 | B8: 46350 | C8: =B8 | D8: Arrancar la validación del diseño en operación experimental controlada | E8: Diego | F8: Torvesa (oficina, Quito) | G8: Primeros eventos registrados | H8: Eventos sin errores | I8: 1 | K8: Pendiente | L8: =IF(K8="Cancelado","",IF(J8<>"",J8-B8,IF(AND(K8<>"Hecho",TODAY()>B8),TODAY()-B8,0))) | M8: S7-03 (#37)
A9: S7-T04 | B9: 46350 | C9: =B9 | D9: Escribir el capítulo de diagnóstico, parte 1 (línea base real) | E9: Víctor | F9: 06_Capitulos/ | G9: Cap4 v0.1 (primera mitad) | H9: Solo datos con registro de procedencia | I9: 2 | K9: Pendiente | L9: =IF(K9="Cancelado","",IF(J9<>"",J9-B9,IF(AND(K9<>"Hecho",TODAY()>B9),TODAY()-B9,0))) | M9: S7-04 (#66)
A10: S7-T05 | B10: 46351 | C10: =B10 | D10: Monitorear la validación y anotar incidencias | E10: Diego | F10: Registro de eventos del sistema | G10: Bitácora de incidencias | H10: Revisada a diario | I10: 0.5 | K10: Pendiente | L10: =IF(K10="Cancelado","",IF(J10<>"",J10-B10,IF(AND(K10<>"Hecho",TODAY()>B10),TODAY()-B10,0))) | M10: S7-03 (#37)
A11: S7-T06 | B11: 46351 | C11: =B11 | D11: Incorporar observaciones técnicas pendientes | E11: Diego | F11: 07_Flujos_Diseno/ | G11: Versiones nuevas | H11: Observaciones cerradas | I11: 1.5 | K11: Pendiente | L11: =IF(K11="Cancelado","",IF(J11<>"",J11-B11,IF(AND(K11<>"Hecho",TODAY()>B11),TODAY()-B11,0))) | M11: S7-01 (#35)
A12: S7-T07 | B12: 46351 | C12: =B12 | D12: Escribir el capítulo de diagnóstico, parte 2 | E12: Víctor | F12: 06_Capitulos/ | G12: Cap4 v0.1 | H12: Capítulo completo | I12: 2 | K12: Pendiente | L12: =IF(K12="Cancelado","",IF(J12<>"",J12-B12,IF(AND(K12<>"Hecho",TODAY()>B12),TODAY()-B12,0))) | M12: S7-04 (#66)
A13: S7-T08 | B13: 46352 | C13: =B13 | D13: Monitorear la validación y anotar incidencias | E13: Diego | F13: Registro de eventos del sistema | G13: Bitácora de incidencias | H13: Revisada a diario | I13: 0.5 | K13: Pendiente | L13: =IF(K13="Cancelado","",IF(J13<>"",J13-B13,IF(AND(K13<>"Hecho",TODAY()>B13),TODAY()-B13,0))) | M13: S7-03 (#37)
A14: S7-T09 | B14: 46352 | C14: =B14 | D14: Incorporar observaciones pendientes del documento | E14: Víctor | F14: 06_Capitulos/ | G14: Versiones nuevas | H14: Observaciones cerradas | I14: 2 | K14: Pendiente | L14: =IF(K14="Cancelado","",IF(J14<>"",J14-B14,IF(AND(K14<>"Hecho",TODAY()>B14),TODAY()-B14,0))) | M14: S7-01 (#35)
A15: S7-T10 | B15: 46353 | C15: =B15 | D15: Monitorear la validación y anotar incidencias | E15: Diego | F15: Registro de eventos del sistema | G15: Bitácora de incidencias | H15: Revisada a diario | I15: 0.5 | K15: Pendiente | L15: =IF(K15="Cancelado","",IF(J15<>"",J15-B15,IF(AND(K15<>"Hecho",TODAY()>B15),TODAY()-B15,0))) | M15: S7-03 (#37)
A16: S7-T11 | B16: 46353 | C16: =B16 | D16: Revisar el capítulo de diagnóstico | E16: Víctor | F16: 06_Capitulos/ | G16: 06_Capitulos/2026-11-28_Cap4_Diagnostico_v0.1.docx | H16: Revisado una vez | I16: 2 | K16: Pendiente | L16: =IF(K16="Cancelado","",IF(J16<>"",J16-B16,IF(AND(K16<>"Hecho",TODAY()>B16),TODAY()-B16,0))) | M16: S7-04 (#66)
A17: S7-T12 | B17: 46354 | C17: =B17 | D17: Monitorear la validación y empezar a documentar las herramientas | E17: Diego | F17: Registro de eventos · 07_Flujos_Diseno/ | G17: Bitácora + borrador de herramientas | H17: Revisada | I17: 3 | K17: Pendiente | L17: =IF(K17="Cancelado","",IF(J17<>"",J17-B17,IF(AND(K17<>"Hecho",TODAY()>B17),TODAY()-B17,0))) | M17: S8-01 (#38)
... A19: S7-T14 | B19: 46355 | C19: =B19 | D19: Revisar el sprint (qué hicimos, qué no, qué aprendimos), hacer 20 min de «explícame lo tuyo» y planificar el siguiente | E19: Ambos | F19: Llamada Víctor–Diego · 11_Planificacion/Bitacora_Semanal.md y 11_Planificacion/Cronograma_Tesis.xlsx | G19: Sección de la semana en la bitácora + hoja del sprint siguiente ajustada | H19: El informe del domingo (21:00) sale con la sección nueva | I19: 1 | K19: Pendiente | L19: =IF(K19="Cancelado","",IF(J19<>"",J19-B19,IF(AND(K19<>"Hecho",TODAY()>B19),TODAY()-B19,0))) | M19: S7-05 (#67)

Sheet S8
A1: Sprint 8 · 30 nov–6 dic · Documentar el sistema
A2: Objetivo: La validación sigue hasta el 5-dic; Diego documenta, Víctor escribe el capítulo de diseño
A3: Avance del sprint: | C3: =IFERROR(COUNTIF(K6:K23,"Hecho")/(COUNTA(D6:D23)-COUNTIF(K6:K23,"Cancelado")),0) | D3: ="Víctor: "&TEXT(IFERROR((COUNTIFS(E6:E23,"Víctor",K6:K23,"Hecho")+COUNTIFS(E6:E23,"Ambos",K6:K23,"Hecho"))/(COUNTIF(E6:E23,"Víctor")+COUNTIF(E6:E23,"Ambos")),0),"0%")&" · Diego: "&TEXT(IFERROR((COUNTIFS(E6:E23,"Diego",K6:K23,"Hecho")+COUNTIFS(E6:E23,"Ambos",K6:K23,"Hecho"))/(COUNTIF(E6:E23,"Diego")+COUNTIF(E6:E23,"Ambos")),0),"0%")&" · Horas: "&TEXT(SUM(I6:I23),"0.0")
A5: ID | B5: Día planificado | C5: Día | D5: Tarea (verbo + qué + para qué) | E5: Responsable | F5: Dónde se hace | G5: Resultado esperado | H5: Cómo sé que terminé | I5: Horas estimadas | J5: Fecha real | K5: Estado | L5: Días de retraso | M5: Entregable (issue) | N5: Notas
A6: S8-T01 | B6: 46356 | C6: =B6 | D6: Documentar las herramientas elegidas y descartadas, con justificación | E6: Diego | F6: 07_Flujos_Diseno/ | G6: 07_Flujos_Diseno/Herramientas | H6: Cada decisión con criterio | I6: 1.5 | K6: Pendiente | L6: =IF(K6="Cancelado","",IF(J6<>"",J6-B6,IF(AND(K6<>"Hecho",TODAY()>B6),TODAY()-B6,0))) | M6: S8-01 (#38)
A7: S8-T02 | B7: 46356 | C7: =B7 | D7: Monitorear la validación | E7: Diego | F7: Registro de eventos del sistema | G7: Bitácora | H7: Revisada | I7: 0.5 | K7: Pendiente | L7: =IF(K7="Cancelado","",IF(J7<>"",J7-B7,IF(AND(K7<>"Hecho",TODAY()>B7),TODAY()-B7,0))) | M7: S7-03 (#37)
A8: S8-T03 | B8: 46356 | C8: =B8 | D8: Escribir el capítulo de diseño y viabilidad, parte 1 (arquitectura y flujos) | E8: Víctor | F8: 06_Capitulos/ | G8: Cap5 v0.1 (parte 1) | H8: Integra los flujos TO-BE | I8: 2 | K8: Pendiente | L8: =IF(K8="Cancelado","",IF(J8<>"",J8-B8,IF(AND(K8<>"Hecho",TODAY()>B8),TODAY()-B8,0))) | M8: S8-06 (#68)
A9: S8-T04 | B9: 46357 | C9: =B9 | D9: Documentar el modelo de datos y el registro de eventos | E9: Diego | F9: 07_Flujos_Diseno/ | G9: 07_Flujos_Diseno/Modelo_Datos | H9: Coincide con la prueba de concepto | I9: 1.5 | K9: Pendiente | L9: =IF(K9="Cancelado","",IF(J9<>"",J9-B9,IF(AND(K9<>"Hecho",TODAY()>B9),TODAY()-B9,0))) | M9: S8-02 (#39)
A10: S8-T05 | B10: 46357 | C10: =B10 | D10: Monitorear la validación | E10: Diego | F10: Registro de eventos del sistema | G10: Bitácora | H10: Revisada | I10: 0.5 | K10: Pendiente | L10: =IF(K10="Cancelado","",IF(J10<>"",J10-B10,IF(AND(K10<>"Hecho",TODAY()>B10),TODAY()-B10,0))) | M10: S7-03 (#37)
A11: S8-T06 | B11: 46357 | C11: =B11 | D11: Escribir el capítulo de diseño y viabilidad, parte 2 (costos y VAN/TIR) | E11: Víctor | F11: 06_Capitulos/ | G11: Cap5 v0.1 (parte 2) | H11: Integra el modelo financiero | I11: 2 | K11: Pendiente | L11: =IF(K11="Cancelado","",IF(J11<>"",J11-B11,IF(AND(K11<>"Hecho",TODAY()>B11),TODAY()-B11,0))) | M11: S8-06 (#68)
A12: S8-T07 | B12: 46358 | C12: =B12 | D12: Documentar las plantillas de cotización y el asistente de IA | E12: Diego | F12: 07_Flujos_Diseno/ | G12: 07_Flujos_Diseno/Asistente_IA | H12: Revisado por Víctor | I12: 1.5 | K12: Pendiente | L12: =IF(K12="Cancelado","",IF(J12<>"",J12-B12,IF(AND(K12<>"Hecho",TODAY()>B12),TODAY()-B12,0))) | M12: S8-03 (#40)
A13: S8-T08 | B13: 46358 | C13: =B13 | D13: Monitorear la validación | E13: Diego | F13: Registro de eventos del sistema | G13: Bitácora | H13: Revisada | I13: 0.5 | K13: Pendiente | L13: =IF(K13="Cancelado","",IF(J13<>"",J13-B13,IF(AND(K13<>"Hecho",TODAY()>B13),TODAY()-B13,0))) | M13: S7-03 (#37)
A14: S8-T09 | B14: 46358 | C14: =B14 | D14: Escribir el capítulo de diseño y viabilidad, parte 3 (normativa y riesgos) | E14: Víctor | F14: 06_Capitulos/ | G14: Cap5 v0.1 (parte 3) | H14: Integra normativa y riesgos | I14: 2 | K14: Pendiente | L14: =IF(K14="Cancelado","",IF(J14<>"",J14-B14,IF(AND(K14<>"Hecho",TODAY()>B14),TODAY()-B14,0))) | M14: S8-06 (#68)
A15: S8-T10 | B15: 46359 | C15: =B15 | D15: Ejecutar los casos de prueba | E15: Diego | F15: 07_Flujos_Diseno/ | G15: 07_Flujos_Diseno/Resultados_Casos_Prueba | H15: Resultado por caso | I15: 1.5 | K15: Pendiente | L15: =IF(K15="Cancelado","",IF(J15<>"",J15-B15,IF(AND(K15<>"Hecho",TODAY()>B15),TODAY()-B15,0))) | M15: S8-04 (#41)
A16: S8-T11 | B16: 46359 | C16: =B16 | D16: Monitorear la validación | E16: Diego | F16: Registro de eventos del sistema | G16: Bitácora | H16: Revisada | I16: 0.5 | K16: Pendiente | L16: =IF(K16="Cancelado","",IF(J16<>"",J16-B16,IF(AND(K16<>"Hecho",TODAY()>B16),TODAY()-B16,0))) | M16: S7-03 (#37)
A17: S8-T12 | B17: 46359 | C17: =B17 | D17: Revisar los documentos técnicos de Diego | E17: Víctor | F17: 07_Flujos_Diseno/ | G17: Comentarios | H17: Comentarios enviados | I17: 2 | K17: Pendiente | L17: =IF(K17="Cancelado","",IF(J17<>"",J17-B17,IF(AND(K17<>"Hecho",TODAY()>B17),TODAY()-B17,0))) | M17: S8-03 (#40)
... A23: S8-T18 | B23: 46362 | C23: =B23 | D23: Revisar el sprint (qué hicimos, qué no, qué aprendimos), hacer 20 min de «explícame lo tuyo» y planificar el siguiente | E23: Ambos | F23: Llamada Víctor–Diego · 11_Planificacion/Bitacora_Semanal.md y 11_Planificacion/Cronograma_Tesis.xlsx | G23: Sección de la semana en la bitácora + hoja del sprint siguiente ajustada | H23: El informe del domingo (21:00) sale con la sección nueva | I23: 1 | K23: Pendiente | L23: =IF(K23="Cancelado","",IF(J23<>"",J23-B23,IF(AND(K23<>"Hecho",TODAY()>B23),TODAY()-B23,0))) | M23: S8-07 (#69)

Sheet S9
A1: Sprint 9 · 7–13 dic · Medir el «después» y comparar
A2: Objetivo: Medición post, análisis pre-post y pruebas
A3: Avance del sprint: | C3: =IFERROR(COUNTIF(K6:K15,"Hecho")/(COUNTA(D6:D15)-COUNTIF(K6:K15,"Cancelado")),0) | D3: ="Víctor: "&TEXT(IFERROR((COUNTIFS(E6:E15,"Víctor",K6:K15,"Hecho")+COUNTIFS(E6:E15,"Ambos",K6:K15,"Hecho"))/(COUNTIF(E6:E15,"Víctor")+COUNTIF(E6:E15,"Ambos")),0),"0%")&" · Diego: "&TEXT(IFERROR((COUNTIFS(E6:E15,"Diego",K6:K15,"Hecho")+COUNTIFS(E6:E15,"Ambos",K6:K15,"Hecho"))/(COUNTIF(E6:E15,"Diego")+COUNTIF(E6:E15,"Ambos")),0),"0%")&" · Horas: "&TEXT(SUM(I6:I15),"0.0")
A5: ID | B5: Día planificado | C5: Día | D5: Tarea (verbo + qué + para qué) | E5: Responsable | F5: Dónde se hace | G5: Resultado esperado | H5: Cómo sé que terminé | I5: Horas estimadas | J5: Fecha real | K5: Estado | L5: Días de retraso | M5: Entregable (issue) | N5: Notas
A6: S9-T01 | B6: 46363 | C6: =B6 | D6: Hacer la medición «después», día 1 (encuesta a colaboradores y SUS) | E6: Ambos | F6: Torvesa (oficina, Quito) | G6: Datos post + registro de procedencia | H6: Cada aplicación registrada | I6: 2 | K6: Pendiente | L6: =IF(K6="Cancelado","",IF(J6<>"",J6-B6,IF(AND(K6<>"Hecho",TODAY()>B6),TODAY()-B6,0))) | M6: S9-01 (#43)
A7: S9-T02 | B7: 46364 | C7: =B7 | D7: Hacer la medición «después», día 2 (prueba de recuperación) | E7: Ambos | F7: Torvesa (oficina, Quito) | G7: Datos post | H7: Cada aplicación registrada | I7: 2 | K7: Pendiente | L7: =IF(K7="Cancelado","",IF(J7<>"",J7-B7,IF(AND(K7<>"Hecho",TODAY()>B7),TODAY()-B7,0))) | M7: S9-01 (#43)
A8: S9-T03 | B8: 46365 | C8: =B8 | D8: Hacer la medición «después», día 3 (clientes y entrevistas de cierre) | E8: Ambos | F8: Torvesa (oficina, Quito) | G8: Datos post | H8: Cada aplicación registrada | I8: 2 | K8: Pendiente | L8: =IF(K8="Cancelado","",IF(J8<>"",J8-B8,IF(AND(K8<>"Hecho",TODAY()>B8),TODAY()-B8,0))) | M8: S9-01 (#43)
A9: S9-T04 | B9: 46366 | C9: =B9 | D9: Comparar el antes y el después (análisis pre-post) | E9: Víctor | F9: 05_Datos_Campo/LineaBase_2026-10/ | G9: Tablas pre-post | H9: Pruebas del borrador + tamaño del efecto | I9: 2 | K9: Pendiente | L9: =IF(K9="Cancelado","",IF(J9<>"",J9-B9,IF(AND(K9<>"Hecho",TODAY()>B9),TODAY()-B9,0))) | M9: S9-02 (#44)
A10: S9-T05 | B10: 46366 | C10: =B10 | D10: ✂ Hacer pruebas de carga simuladas con scripts | E10: Diego | F10: 07_Flujos_Diseno/ | G10: 07_Flujos_Diseno/Pruebas_Carga | H10: Escenarios reproducibles | I10: 2 | K10: Pendiente | L10: =IF(K10="Cancelado","",IF(J10<>"",J10-B10,IF(AND(K10<>"Hecho",TODAY()>B10),TODAY()-B10,0))) | M10: S9-03 (#45)
A11: S9-T06 | B11: 46367 | C11: =B11 | D11: Terminar el análisis pre-post | E11: Víctor | F11: 05_Datos_Campo/LineaBase_2026-10/ | G11: Resultados listos | H11: Revisados con Diego | I11: 2 | K11: Pendiente | L11: =IF(K11="Cancelado","",IF(J11<>"",J11-B11,IF(AND(K11<>"Hecho",TODAY()>B11),TODAY()-B11,0))) | M11: S9-02 (#44)
A12: S9-T07 | B12: 46367 | C12: =B12 | D12: Hacer pruebas de uso y preparar las gráficas de resultados | E12: Diego | F12: 07_Flujos_Diseno/ | G12: Gráficas | H12: Legibles y con título | I12: 2 | K12: Pendiente | L12: =IF(K12="Cancelado","",IF(J12<>"",J12-B12,IF(AND(K12<>"Hecho",TODAY()>B12),TODAY()-B12,0))) | M12: S9-02 (#44)
A13: S9-T08 | B13: 46368 | C13: =B13 | D13: Escribir el capítulo de resultados | E13: Víctor | F13: 06_Capitulos/ | G13: 06_Capitulos/2026-12-12_Cap6_Resultados_v0.1.docx | H13: Capítulo completo | I13: 3 | K13: Pendiente | L13: =IF(K13="Cancelado","",IF(J13<>"",J13-B13,IF(AND(K13<>"Hecho",TODAY()>B13),TODAY()-B13,0))) | M13: S9-02 (#44)
A14: S9-T09 | B14: 46368 | C14: =B14 | D14: Revisar el capítulo de resultados (parte técnica) | E14: Diego | F14: 06_Capitulos/ | G14: Comentarios | H14: Comentarios enviados | I14: 2 | K14: Pendiente | L14: =IF(K14="Cancelado","",IF(J14<>"",J14-B14,IF(AND(K14<>"Hecho",TODAY()>B14),TODAY()-B14,0))) | M14: S9-02 (#44)
A15: S9-T10 | B15: 46369 | C15: =B15 | D15: Revisar el sprint (qué hicimos, qué no, qué aprendimos), hacer 20 min de «explícame lo tuyo» y planificar el siguiente | E15: Ambos | F15: Llamada Víctor–Diego · 11_Planificacion/Bitacora_Semanal.md y 11_Planificacion/Cronograma_Tesis.xlsx | G15: Sección de la semana en la bitácora + hoja del sprint siguiente ajustada | H15: El informe del domingo (21:00) sale con la sección nueva | I15: 1 | K15: Pendiente | L15: =IF(K15="Cancelado","",IF(J15<>"",J15-B15,IF(AND(K15<>"Hecho",TODAY()>B15),TODAY()-B15,0))) | M15: S9-04 (#70)

Sheet S10
A1: Sprint 10 · 14–20 dic · Cierre e hito del 90 %
A2: Objetivo: Ciclos con la tutora y tesis al 90 %
A3: Avance del sprint: | C3: =IFERROR(COUNTIF(K6:K13,"Hecho")/(COUNTA(D6:D13)-COUNTIF(K6:K13,"Cancelado")),0) | D3: ="Víctor: "&TEXT(IFERROR((COUNTIFS(E6:E13,"Víctor",K6:K13,"Hecho")+COUNTIFS(E6:E13,"Ambos",K6:K13,"Hecho"))/(COUNTIF(E6:E13,"Víctor")+COUNTIF(E6:E13,"Ambos")),0),"0%")&" · Diego: "&TEXT(IFERROR((COUNTIFS(E6:E13,"Diego",K6:K13,"Hecho")+COUNTIFS(E6:E13,"Ambos",K6:K13,"Hecho"))/(COUNTIF(E6:E13,"Diego")+COUNTIF(E6:E13,"Ambos")),0),"0%")&" · Horas: "&TEXT(SUM(I6:I13),"0.0")
A5: ID | B5: Día planificado | C5: Día | D5: Tarea (verbo + qué + para qué) | E5: Responsable | F5: Dónde se hace | G5: Resultado esperado | H5: Cómo sé que terminé | I5: Horas estimadas | J5: Fecha real | K5: Estado | L5: Días de retraso | M5: Entregable (issue) | N5: Notas
A6: S10-T01 | B6: 46370 | C6: =B6 | D6: Enviar a la tutora la tesis completa para revisión | E6: Víctor | F6: Correo electrónico | G6: Tesis enviada | H6: Acuse de recibo | I6: 1 | K6: Pendiente | L6: =IF(K6="Cancelado","",IF(J6<>"",J6-B6,IF(AND(K6<>"Hecho",TODAY()>B6),TODAY()-B6,0))) | M6: S10-01 (#46)
A7: S10-T02 | B7: 46370 | C7: =B7 | D7: Revisar anexos técnicos y figuras | E7: Diego | F7: 06_Capitulos/ | G7: Anexos revisados | H7: Sin errores | I7: 2 | K7: Pendiente | L7: =IF(K7="Cancelado","",IF(J7<>"",J7-B7,IF(AND(K7<>"Hecho",TODAY()>B7),TODAY()-B7,0))) | M7: S10-02 (#47)
A8: S10-T03 | B8: 46371 | C8: =B8 | D8: ✂ Ciclo con la tutora: recibir observaciones | E8: Víctor | F8: 08_Reuniones_Tutora/ | G8: Observaciones | H8: Acta corta | I8: 1 | K8: Pendiente | L8: =IF(K8="Cancelado","",IF(J8<>"",J8-B8,IF(AND(K8<>"Hecho",TODAY()>B8),TODAY()-B8,0))) | M8: S10-01 (#46)
A9: S10-T04 | B9: 46372 | C9: =B9 | D9: Corregir según las observaciones | E9: Ambos | F9: 06_Capitulos/ | G9: Versión corregida | H9: Observaciones cerradas | I9: 2 | K9: Pendiente | L9: =IF(K9="Cancelado","",IF(J9<>"",J9-B9,IF(AND(K9<>"Hecho",TODAY()>B9),TODAY()-B9,0))) | M9: S10-01 (#46)
A10: S10-T05 | B10: 46373 | C10: =B10 | D10: ✂ Ciclo con la tutora: segunda revisión | E10: Víctor | F10: 08_Reuniones_Tutora/ | G10: Observaciones | H10: Acta corta | I10: 1 | K10: Pendiente | L10: =IF(K10="Cancelado","",IF(J10<>"",J10-B10,IF(AND(K10<>"Hecho",TODAY()>B10),TODAY()-B10,0))) | M10: S10-01 (#46)
A11: S10-T06 | B11: 46374 | C11: =B11 | D11: HITO: dejar la tesis al 90 % | E11: Ambos | F11: 06_Capitulos/ | G11: Tesis completa | H11: Todos los capítulos + bibliografía verificada | I11: 2 | K11: Pendiente | L11: =IF(K11="Cancelado","",IF(J11<>"",J11-B11,IF(AND(K11<>"Hecho",TODAY()>B11),TODAY()-B11,0))) | M11: S10-02 (#47) | N11: Escenario B confirmado (entrega 4-ene-2027): las tareas ✂ se mantienen
A12: S10-T07 | B12: 46375 | C12: =B12 | D12: Integrar todo y revisar coherencia entre capítulos | E12: Ambos | F12: 06_Capitulos/ | G12: Versión integrada | H12: Lectura completa hecha | I12: 3 | K12: Pendiente | L12: =IF(K12="Cancelado","",IF(J12<>"",J12-B12,IF(AND(K12<>"Hecho",TODAY()>B12),TODAY()-B12,0))) | M12: S10-02 (#47)
A13: S10-T08 | B13: 46376 | C13: =B13 | D13: Revisar el sprint (qué hicimos, qué no, qué aprendimos), hacer 20 min de «explícame lo tuyo» y planificar el siguiente | E13: Ambos | F13: Llamada Víctor–Diego · 11_Planificacion/Bitacora_Semanal.md y 11_Planificacion/Cronograma_Tesis.xlsx | G13: Sección de la semana en la bitácora + hoja del sprint siguiente ajustada | H13: El informe del domingo (21:00) sale con la sección nueva | I13: 1 | K13: Pendiente | L13: =IF(K13="Cancelado","",IF(J13<>"",J13-B13,IF(AND(K13<>"Hecho",TODAY()>B13),TODAY()-B13,0))) | M13: S10-03 (#71)

Sheet Holgura
A1: Holgura · 21 dic–3 ene · Pulir
A2: Objetivo: Revisión APA, citas y bibliografía en bloques cortos
A3: Avance del sprint: | C3: =IFERROR(COUNTIF(K6:K11,"Hecho")/(COUNTA(D6:D11)-COUNTIF(K6:K11,"Cancelado")),0) | D3: ="Víctor: "&TEXT(IFERROR((COUNTIFS(E6:E11,"Víctor",K6:K11,"Hecho")+COUNTIFS(E6:E11,"Ambos",K6:K11,"Hecho"))/(COUNTIF(E6:E11,"Víctor")+COUNTIF(E6:E11,"Ambos")),0),"0%")&" · Diego: "&TEXT(IFERROR((COUNTIFS(E6:E11,"Diego",K6:K11,"Hecho")+COUNTIFS(E6:E11,"Ambos",K6:K11,"Hecho"))/(COUNTIF(E6:E11,"Diego")+COUNTIF(E6:E11,"Ambos")),0),"0%")&" · Horas: "&TEXT(SUM(I6:I11),"0.0")
A5: ID | B5: Día planificado | C5: Día | D5: Tarea (verbo + qué + para qué) | E5: Responsable | F5: Dónde se hace | G5: Resultado esperado | H5: Cómo sé que terminé | I5: Horas estimadas | J5: Fecha real | K5: Estado | L5: Días de retraso | M5: Entregable (issue) | N5: Notas
A6: Holgura-T01 | B6: 46378 | C6: =B6 | D6: Revisar las citas del capítulo 1 y 2 contra sus fichas | E6: Víctor | F6: 06_Capitulos/ | G6: Citas verificadas | H6: 0 citas sin ficha | I6: 1.5 | K6: Pendiente | L6: =IF(K6="Cancelado","",IF(J6<>"",J6-B6,IF(AND(K6<>"Hecho",TODAY()>B6),TODAY()-B6,0))) | M6: H-01 (#48)
A7: Holgura-T02 | B7: 46379 | C7: =B7 | D7: Revisar los anexos técnicos y su numeración | E7: Diego | F7: 06_Capitulos/ | G7: Anexos ordenados | H7: Índice correcto | I7: 1.5 | K7: Pendiente | L7: =IF(K7="Cancelado","",IF(J7<>"",J7-B7,IF(AND(K7<>"Hecho",TODAY()>B7),TODAY()-B7,0))) | M7: H-01 (#48)
A8: Holgura-T03 | B8: 46382 | C8: =B8 | D8: Revisar las citas de los capítulos 3–6 | E8: Víctor | F8: 06_Capitulos/ | G8: Citas verificadas | H8: 0 citas sin ficha | I8: 2 | K8: Pendiente | L8: =IF(K8="Cancelado","",IF(J8<>"",J8-B8,IF(AND(K8<>"Hecho",TODAY()>B8),TODAY()-B8,0))) | M8: H-01 (#48)
A9: Holgura-T04 | B9: 46385 | C9: =B9 | D9: Revisar la bibliografía en APA 7 | E9: Víctor | F9: 06_Capitulos/ | G9: Bibliografía final | H9: Formato APA en todas | I9: 2 | K9: Pendiente | L9: =IF(K9="Cancelado","",IF(J9<>"",J9-B9,IF(AND(K9<>"Hecho",TODAY()>B9),TODAY()-B9,0))) | M9: H-01 (#48)
A10: Holgura-T05 | B10: 46386 | C10: =B10 | D10: Revisar figuras, tablas y diagramas | E10: Diego | F10: 06_Capitulos/ | G10: Figuras finales | H10: Numeradas y citadas | I10: 1.5 | K10: Pendiente | L10: =IF(K10="Cancelado","",IF(J10<>"",J10-B10,IF(AND(K10<>"Hecho",TODAY()>B10),TODAY()-B10,0))) | M10: H-01 (#48)
A11: Holgura-T06 | B11: 46389 | C11: =B11 | D11: Leer la tesis completa una vez más | E11: Ambos | F11: 06_Capitulos/ | G11: Lista de últimos cambios | H11: Lista cerrada | I11: 3 | K11: Pendiente | L11: =IF(K11="Cancelado","",IF(J11<>"",J11-B11,IF(AND(K11<>"Hecho",TODAY()>B11),TODAY()-B11,0))) | M11: H-01 (#48) | N11: Última lectura antes de la fecha límite del lunes 4-ene-2027

Sheet Entrega
A1: Entrega · 4–10 ene · Revisión final y firma
A2: Objetivo: Escenario A: la entrega es el 15-dic
A3: Avance del sprint: | C3: =IFERROR(COUNTIF(K6:K9,"Hecho")/(COUNTA(D6:D9)-COUNTIF(K6:K9,"Cancelado")),0) | D3: ="Víctor: "&TEXT(IFERROR((COUNTIFS(E6:E9,"Víctor",K6:K9,"Hecho")+COUNTIFS(E6:E9,"Ambos",K6:K9,"Hecho"))/(COUNTIF(E6:E9,"Víctor")+COUNTIF(E6:E9,"Ambos")),0),"0%")&" · Diego: "&TEXT(IFERROR((COUNTIFS(E6:E9,"Diego",K6:K9,"Hecho")+COUNTIFS(E6:E9,"Ambos",K6:K9,"Hecho"))/(COUNTIF(E6:E9,"Diego")+COUNTIF(E6:E9,"Ambos")),0),"0%")&" · Horas: "&TEXT(SUM(I6:I9),"0.0")
A5: ID | B5: Día planificado | C5: Día | D5: Tarea (verbo + qué + para qué) | E5: Responsable | F5: Dónde se hace | G5: Resultado esperado | H5: Cómo sé que terminé | I5: Horas estimadas | J5: Fecha real | K5: Estado | L5: Días de retraso | M5: Entregable (issue) | N5: Notas
A6: Entrega-T01 | B6: 46391 | C6: =B6 | D6: Enviar la versión final a la tutora | E6: Víctor | F6: Correo electrónico | G6: Versión final enviada | H6: Acuse de recibo | I6: 1 | K6: Pendiente | L6: =IF(K6="Cancelado","",IF(J6<>"",J6-B6,IF(AND(K6<>"Hecho",TODAY()>B6),TODAY()-B6,0))) | M6: E-01 (#49) | N6: FECHA LÍMITE (D5, Víctor 18-oct): el lunes 4-ene-2027 el documento final está completo y listo para la revisión de la tutora
A7: Entrega-T02 | B7: 46393 | C7: =B7 | D7: Hacer las últimas correcciones | E7: Ambos | F7: 06_Capitulos/ | G7: Versión final corregida | H7: Observaciones cerradas | I7: 2 | K7: Pendiente | L7: =IF(K7="Cancelado","",IF(J7<>"",J7-B7,IF(AND(K7<>"Hecho",TODAY()>B7),TODAY()-B7,0))) | M7: E-01 (#49)
A8: Entrega-T03 | B8: 46394 | C8: =B8 | D8: Conseguir la firma de la tutora | E8: Víctor | F8: UPS Quito, en persona | G8: Tesis firmada | H8: Firma | I8: 1 | K8: Pendiente | L8: =IF(K8="Cancelado","",IF(J8<>"",J8-B8,IF(AND(K8<>"Hecho",TODAY()>B8),TODAY()-B8,0))) | M8: E-01 (#49)
A9: Entrega-T04 | B9: 46395 | C9: =B9 | D9: Entregar la tesis a la carrera | E9: Ambos | F9: Sistema de la UPS | G9: Comprobante | H9: Comprobante recibido | I9: 1 | K9: Pendiente | L9: =IF(K9="Cancelado","",IF(J9<>"",J9-B9,IF(AND(K9<>"Hecho",TODAY()>B9),TODAY()-B9,0))) | M9: E-02 (#50)

Sheet Defensa
A1: Defensa · 11 ene–12 feb · Preparar y defender
A2: Objetivo: Los dos deben poder responder sobre todo el proyecto
A3: Avance del sprint: | C3: =IFERROR(COUNTIF(K6:K10,"Hecho")/(COUNTA(D6:D10)-COUNTIF(K6:K10,"Cancelado")),0) | D3: ="Víctor: "&TEXT(IFERROR((COUNTIFS(E6:E10,"Víctor",K6:K10,"Hecho")+COUNTIFS(E6:E10,"Ambos",K6:K10,"Hecho"))/(COUNTIF(E6:E10,"Víctor")+COUNTIF(E6:E10,"Ambos")),0),"0%")&" · Diego: "&TEXT(IFERROR((COUNTIFS(E6:E10,"Diego",K6:K10,"Hecho")+COUNTIFS(E6:E10,"Ambos",K6:K10,"Hecho"))/(COUNTIF(E6:E10,"Diego")+COUNTIF(E6:E10,"Ambos")),0),"0%")&" · Horas: "&TEXT(SUM(I6:I10),"0.0")
A5: ID | B5: Día planificado | C5: Día | D5: Tarea (verbo + qué + para qué) | E5: Responsable | F5: Dónde se hace | G5: Resultado esperado | H5: Cómo sé que terminé | I5: Horas estimadas | J5: Fecha real | K5: Estado | L5: Días de retraso | M5: Entregable (issue) | N5: Notas
A6: Defensa-T01 | B6: 46399 | C6: =B6 | D6: Escribir el resumen de contribuciones (quién hizo qué) | E6: Ambos | F6: 09_Registro_Contribuciones/ | G6: Resumen de contribuciones | H6: Aprobado por los dos | I6: 2 | K6: Pendiente | L6: =IF(K6="Cancelado","",IF(J6<>"",J6-B6,IF(AND(K6<>"Hecho",TODAY()>B6),TODAY()-B6,0))) | M6: D-01 (#51)
A7: Defensa-T02 | B7: 46410 | C7: =B7 | D7: Dividir la exposición y armar las diapositivas | E7: Ambos | F7: Llamada Víctor–Diego | G7: Guion + diapositivas | H7: Cada uno sabe su parte y la del otro | I7: 3 | K7: Pendiente | L7: =IF(K7="Cancelado","",IF(J7<>"",J7-B7,IF(AND(K7<>"Hecho",TODAY()>B7),TODAY()-B7,0))) | M7: D-02 (#52)
A8: Defensa-T03 | B8: 46417 | C8: =B8 | D8: Armar el banco de preguntas del tribunal y hacer el simulacro 1 | E8: Ambos | F8: Llamada Víctor–Diego | G8: Banco de preguntas + simulacro | H8: Simulacro cronometrado | I8: 3 | K8: Pendiente | L8: =IF(K8="Cancelado","",IF(J8<>"",J8-B8,IF(AND(K8<>"Hecho",TODAY()>B8),TODAY()-B8,0))) | M8: D-02 (#52)
A9: Defensa-T04 | B9: 46424 | C9: =B9 | D9: Hacer el simulacro 2 con preguntas cruzadas (cada uno responde lo del otro) | E9: Ambos | F9: Llamada Víctor–Diego | G9: Simulacro 2 | H9: Ambos responden todo el banco | I9: 3 | K9: Pendiente | L9: =IF(K9="Cancelado","",IF(J9<>"",J9-B9,IF(AND(K9<>"Hecho",TODAY()>B9),TODAY()-B9,0))) | M9: D-02 (#52)
A10: Defensa-T05 | B10: 46427 | C10: =B10 | D10: Defender la tesis (fecha a confirmar por la carrera) | E10: Ambos | F10: UPS Quito, en persona | G10: Defensa | H10: Aprobada | I10: 2 | K10: Pendiente | L10: =IF(K10="Cancelado","",IF(J10<>"",J10-B10,IF(AND(K10<>"Hecho",TODAY()>B10),TODAY()-B10,0))) | M10: D-03 (#53)
